Workbook

Sheet cleaned_orders
A1: order_id | B1: order_date | C1: ship_date | D1: customer_id | E1: customer_name | F1: segment | G1: region | H1: state | I1: city | J1: category | K1: sub_category | L1: product_name | M1: ship_mode | N1: quantity | O1: unit_price | P1: discount | Q1: sales | R1: cost | S1: profit | T1: payment_status | U1: order_status | V1: Joint | W1: conflicting_duplicates | X1: exact_duplicate_rows | Y1: duplicate_order_id_flag | Z1: duplicate_review_flag | AA1: data_quality_flag | AB1: date_quality_flag | AC1: shipping_delay_days | AD1: shipping_date_issue | AE1: date_format_flag | AF1: flag_valid_order_date | AG1: flag_valid_shipping_date | AH1: flag_missing_order_date | AI1: flag_missing_shipping_date | AJ1: flag_missing_region | AK1: flag_missing_ship_mode | AL1: flag_missing_discount | AM1: flag_negative_discount | AN1: flag_discount_out_of_range | AO1: flag_invalid_shipping | AP1: any_rule_flag | AQ1: cleaned_discount | AR1: calculated_sales | AS1: sales difference | AT1: calculated_profit | AU1: profit diff | AV1: Profit_margin | AW1: Order Month | AX1: Order year
A2: ORD-2024-10001 | B2: 45494 | C2: 45500 | D2: CUST-4655 | E2: Karan Malhotra | F2: Consumer | G2: North | H2: Rajasthan | I2: Jaipur | J2: Office Supplies | K2: Paper | L2: Pro Paper 122 | M2: Second Class | N2: 8 | O2: 2976.45 | P2: 0.2 | Q2: 19049.28 | R2: 15841.89 | S2: 3207.39 | T2: Paid | U2: Completed | V2: =TEXTJOIN("|",TRUE,A2:U2) -> #NAME? | X2: =COUNTIF(V:V,V2)>1 -> TRUE | Y2: =IF(COUNTIF($A:$A,A2)>1,"Duplicate Order ID","Unique") -> Unique | Z2: =IF( COUNTIFS($A:$A,A2,$B:$B,B2)=COUNTIF($A:$A,A2), "Exact Duplicate", "Conflicting Duplicate" ) -> Exact Duplicate | AA2: =IF( OR(AQ2<0, AQ2>1, C2<B2), "Invalid", IF( OR(G2="Unknown", M2="Unknown"), "Warning", "Clean" ) ) -> Clean | AB2: =IF( OR( B2="", C2="", NOT(ISNUMBER(B2)), NOT(ISNUMBER(C2)), C2<B2 ), "Invalid", "Valid" ) -> Valid | AC2: 6 | AD2: =IF(C2<B2,"Invalid Shipping Date","Valid") -> Valid | AE2: =IF(AND(B2<>"",NOT(ISNUMBER(B2))),"Text Not Date","Valid") -> Valid | AF2: =IF(ISNUMBER(B2),"Valid","Invalid") -> Valid | AG2: =IF(ISNUMBER(C2),"Valid","Invalid") -> Valid | AH2: =IF(OR(B2="",ISBLANK(B2)),"Missing","Valid") -> Valid | AI2: =IF(OR(C2="",ISBLANK(C2)),"Missing","Valid") -> Valid | AJ2: FALSE | AK2: FALSE | AL2: FALSE | AM2: FALSE | AN2: FALSE | AO2: FALSE | AP2: FALSE | AQ2: =IF(OR(P2="",ISBLANK(P2)),0,P2) -> 0.2 | AR2: =N2*O2*(1-AQ2) -> 19049.28 | AS2: =Q2-AR2 -> 0 | AT2: =AR2-R2 -> 3207.39 | AU2: =S2-AT2 -> 0 | AV2: =AT2/AR2 -> 0.16837329 | AW2: =TEXT(B2,"mmmm") -> July | AX2: =YEAR(B2) -> 2024
A3: ORD-2024-10002 | B3: 45535 | C3: 45540 | D3: CUST-2054 | E3: Mira Das | F3: Small Business | G3: East | H3: Odisha | I3: Bhubaneswar | J3: Furniture | K3: Tables | L3: Pro Tables 258 | M3: Same Day | N3: 3 | O3: 2437.5 | P3: 0 | Q3: 7312.5 | R3: 4904.73 | S3: 2407.77 | T3: Paid | U3: Completed | V3: =TEXTJOIN("|",TRUE,A3:U3) -> #NAME? | X3: =COUNTIF(V:V,V3)>1 -> TRUE | Y3: =IF(COUNTIF($A:$A,A3)>1,"Duplicate Order ID","Unique") -> Unique | AA3: =IF( OR(AQ3<0, AQ3>1, C3<B3), "Invalid", IF( OR(G3="Unknown", M3="Unknown"), "Warning", "Clean" ) ) -> Clean | AB3: =IF( OR( B3="", C3="", NOT(ISNUMBER(B3)), NOT(ISNUMBER(C3)), C3<B3 ), "Invalid", "Valid" ) -> Valid | AC3: 5 | AD3: =IF(C3<B3,"Invalid Shipping Date","Valid") -> Valid | AE3: =IF(AND(B3<>"",NOT(ISNUMBER(B3))),"Text Not Date","Valid") -> Valid | AF3: =IF(ISNUMBER(B3),"Valid","Invalid") -> Valid | AG3: =IF(ISNUMBER(C3),"Valid","Invalid") -> Valid | AH3: =IF(OR(B3="",ISBLANK(B3)),"Missing","Valid") -> Valid | AI3: =IF(OR(C3="",ISBLANK(C3)),"Missing","Valid") -> Valid | AJ3: FALSE | AK3: FALSE | AL3: FALSE | AM3: FALSE | AN3: FALSE | AO3: FALSE | AP3: FALSE | AQ3: =IF(OR(P3="",ISBLANK(P3)),0,P3) -> 0 | AR3: =N3*O3*(1-AQ3) -> 7312.5 | AS3: =Q3-AR3 -> 0 | AT3: =AR3-R3 -> 2407.77 | AU3: =S3-AT3 -> 0 | AV3: =AT3/AR3 -> 0.32926769 | AW3: =TEXT(B3,"mmmm") -> August | AX3: =YEAR(B3) -> 2024
A4: ORD-2024-10003 | B4: 45451 | C4: 45458 | D4: CUST-6843 | E4: Isha Nair | F4: Consumer | G4: East | H4: Odisha | I4: Bhubaneswar | J4: Office Supplies | K4: Art | L4: Elite Art 525 | M4: First Class | N4: 4 | O4: 1065.43 | P4: 0.55 | Q4: 4261.72 | R4: 2465.69 | S4: 1796.03 | T4: Paid | U4: Completed | V4: =TEXTJOIN("|",TRUE,A4:U4) -> #NAME? | X4: =COUNTIF(V:V,V4)>1 -> TRUE | Y4: =IF(COUNTIF($A:$A,A4)>1,"Duplicate Order ID","Unique") -> Unique | AA4: =IF( OR(AQ4<0, AQ4>1, C4<B4), "Invalid", IF( OR(G4="Unknown", M4="Unknown"), "Warning", "Clean" ) ) -> Clean | AB4: =IF( OR( B4="", C4="", NOT(ISNUMBER(B4)), NOT(ISNUMBER(C4)), C4<B4 ), "Invalid", "Valid" ) -> Valid | AC4: 7 | AD4: =IF(C4<B4,"Invalid Shipping Date","Valid") -> Valid | AE4: =IF(AND(B4<>"",NOT(ISNUMBER(B4))),"Text Not Date","Valid") -> Valid | AF4: =IF(ISNUMBER(B4),"Valid","Invalid") -> Valid | AG4: =IF(ISNUMBER(C4),"Valid","Invalid") -> Valid | AH4: =IF(OR(B4="",ISBLANK(B4)),"Missing","Valid") -> Valid | AI4: =IF(OR(C4="",ISBLANK(C4)),"Missing","Valid") -> Valid | AJ4: FALSE | AK4: FALSE | AL4: FALSE | AM4: FALSE | AN4: FALSE | AO4: FALSE | AP4: FALSE | AQ4: =IF(OR(P4="",ISBLANK(P4)),0,P4) -> 0.55 | AR4: =N4*O4*(1-AQ4) -> 1917.774 | AS4: =Q4-AR4 -> 2343.946 | AT4: =AR4-R4 -> -547.916 | AU4: =S4-AT4 -> 2343.946 | AV4: =AT4/AR4 -> -0.28570415 | AW4: =TEXT(B4,"mmmm") -> June | AX4: =YEAR(B4) -> 2024
A5: ORD-2024-10004 | B5: 45624 | C5: 45625 | D5: CUST-3722 | E5: Arjun Bose | F5: Small Business | G5: South | H5: Telangana | I5: Hyderabad | J5: Furniture | K5: Furnishings | L5: Smart Furnishings 294 | M5: Standard Class | N5: 6 | O5: 1848.43 | P5: 0.25 | Q5: 8317.93 | R5: 6796.77 | S5: 1521.16 | T5: Paid | U5: Completed | V5: =TEXTJOIN("|",TRUE,A5:U5) -> #NAME? | X5: =COUNTIF(V:V,V5)>1 -> TRUE | Y5: =IF(COUNTIF($A:$A,A5)>1,"Duplicate Order ID","Unique") -> Unique | AA5: =IF( OR(AQ5<0, AQ5>1, C5<B5), "Invalid", IF( OR(G5="Unknown", M5="Unknown"), "Warning", "Clean" ) ) -> Clean | AB5: =IF( OR( B5="", C5="", NOT(ISNUMBER(B5)), NOT(ISNUMBER(C5)), C5<B5 ), "Invalid", "Valid" ) -> Valid | AC5: 1 | AD5: =IF(C5<B5,"Invalid Shipping Date","Valid") -> Valid | AE5: =IF(AND(B5<>"",NOT(ISNUMBER(B5))),"Text Not Date","Valid") -> Valid | AF5: =IF(ISNUMBER(B5),"Valid","Invalid") -> Valid | AG5: =IF(ISNUMBER(C5),"Valid","Invalid") -> Valid | AH5: =IF(OR(B5="",ISBLANK(B5)),"Missing","Valid") -> Valid | AI5: =IF(OR(C5="",ISBLANK(C5)),"Missing","Valid") -> Valid | AJ5: FALSE | AK5: FALSE | AL5: FALSE | AM5: FALSE | AN5: FALSE | AO5: FALSE | AP5: FALSE | AQ5: =IF(OR(P5="",ISBLANK(P5)),0,P5) -> 0.25 | AR5: =N5*O5*(1-AQ5) -> 8317.935 | AS5: =Q5-AR5 -> -0.005 | AT5: =AR5-R5 -> 1521.165 | AU5: =S5-AT5 -> -0.005 | AV5: =AT5/AR5 -> 0.18287772 | AW5: =TEXT(B5,"mmmm") -> November | AX5: =YEAR(B5) -> 2024
A6: ORD-2025-10005 | B6: 45898 | C6: 45901 | D6: CUST-8130 | E6: Ananya Rao | F6: Small Business | G6: West | H6: Maharashtra | I6: Mumbai | J6: Furniture | K6: Chairs | L6: Elite Chairs 543 | M6: First Class | N6: 7 | O6: 2973.76 | P6: 0 | Q6: 20816.32 | R6: 17705.37 | S6: 3110.95 | T6: Paid | U6: Cancelled | V6: =TEXTJOIN("|",TRUE,A6:U6) -> #NAME? | X6: =COUNTIF(V:V,V6)>1 -> TRUE | Y6: =IF(COUNTIF($A:$A,A6)>1,"Duplicate Order ID","Unique") -> Unique | AA6: =IF( OR(AQ6<0, AQ6>1, C6<B6), "Invalid", IF( OR(G6="Unknown", M6="Unknown"), "Warning", "Clean" ) ) -> Clean | AB6: =IF( OR( B6="", C6="", NOT(ISNUMBER(B6)), NOT(ISNUMBER(C6)), C6<B6 ), "Invalid", "Valid" ) -> Valid | AC6: 3 | AD6: =IF(C6<B6,"Invalid Shipping Date","Valid") -> Valid | AE6: =IF(AND(B6<>"",NOT(ISNUMBER(B6))),"Text Not Date","Valid") -> Valid | AF6: =IF(ISNUMBER(B6),"Valid","Invalid") -> Valid | AG6: =IF(ISNUMBER(C6),"Valid","Invalid") -> Valid | AH6: =IF(OR(B6="",ISBLANK(B6)),"Missing","Valid") -> Valid | AI6: =IF(OR(C6="",ISBLANK(C6)),"Missing","Valid") -> Valid | AJ6: FALSE | AK6: FALSE | AL6: FALSE | AM6: FALSE | AN6: FALSE | AO6: FALSE | AP6: FALSE | AQ6: =IF(OR(P6="",ISBLANK(P6)),0,P6) -> 0 | AR6: =N6*O6*(1-AQ6) -> 20816.32 | AS6: =Q6-AR6 -> 0 | AT6: =AR6-R6 -> 3110.95 | AU6: =S6-AT6 -> 0 | AV6: =AT6/AR6 -> 0.14944764 | AW6: =TEXT(B6,"mmmm") -> August | AX6: =YEAR(B6) -> 2025
A7: ORD-2024-10006 | B7: 45436 | C7: 45440 | D7: CUST-6056 | E7: Vikram Iyer | F7: Small Business | G7: West | H7: Madhya Pradesh | I7: Indore | J7: Technology | K7: Accessories | L7: Pro Accessories 821 | M7: Same Day | N7: 3 | O7: 1053.11 | P7: 0.2 | Q7: 2527.46 | R7: 1533.58 | S7: 993.88 | T7: Paid | U7: Completed | V7: =TEXTJOIN("|",TRUE,A7:U7) -> #NAME? | X7: =COUNTIF(V:V,V7)>1 -> TRUE | Y7: =IF(COUNTIF($A:$A,A7)>1,"Duplicate Order ID","Unique") -> Unique | AA7: =IF( OR(AQ7<0, AQ7>1, C7<B7), "Invalid", IF( OR(G7="Unknown", M7="Unknown"), "Warning", "Clean" ) ) -> Clean | AB7: =IF( OR( B7="", C7="", NOT(ISNUMBER(B7)), NOT(ISNUMBER(C7)), C7<B7 ), "Invalid", "Valid" ) -> Valid | AC7: 4 | AD7: =IF(C7<B7,"Invalid Shipping Date","Valid") -> Valid | AE7: =IF(AND(B7<>"",NOT(ISNUMBER(B7))),"Text Not Date","Valid") -> Valid | AF7: =IF(ISNUMBER(B7),"Valid","Invalid") -> Valid | AG7: =IF(ISNUMBER(C7),"Valid","Invalid") -> Valid | AH7: =IF(OR(B7="",ISBLANK(B7)),"Missing","Valid") -> Valid | AI7: =IF(OR(C7="",ISBLANK(C7)),"Missing","Valid") -> Valid | AJ7: FALSE | AK7: FALSE | AL7: FALSE | AM7: FALSE | AN7: FALSE | AO7: FALSE | AP7: FALSE | AQ7: =IF(OR(P7="",ISBLANK(P7)),0,P7) -> 0.2 | AR7: =N7*O7*(1-AQ7) -> 2527.464 | AS7: =Q7-AR7 -> -0.004 | AT7: =AR7-R7 -> 993.884 | AU7: =S7-AT7 -> -0.004 | AV7: =AT7/AR7 -> 0.39323369 | AW7: =TEXT(B7,"mmmm") -> May | AX7: =YEAR(B7) -> 2024
A8: ORD-2025-10007 | B8: 45757 | C8: 45763 | D8: CUST-3656 | E8: Neha Gupta | F8: Consumer | G8: East | H8: Odisha | I8: Bhubaneswar | J8: Technology | K8: Copiers | L8: Eco Copiers 790 | M8: Standard Class | N8: 4 | O8: 1719.87 | P8: 0.15 | Q8: 5847.56 | R8: 4727.25 | S8: 1120.31 | T8: Paid | U8: Completed | V8: =TEXTJOIN("|",TRUE,A8:U8) -> #NAME? | W8: =IFERROR(__xludf.DUMMYFUNCTION("IF(COUNTIF($A:$A,A2)=1, ""Unique"", IF(COUNTUNIQUE(FILTER($V$2:$V$934,$A$2:$A$934=A2))>1, ""Conflicting Duplicate"", ""Exact Duplicate""))"),"Unique") -> Unique | X8: =COUNTIF(V:V,V8)>1 -> TRUE | Y8: =IF(COUNTIF($A:$A,A8)>1,"Duplicate Order ID","Unique") -> Duplicate Order ID | AA8: =IF( OR(AQ8<0, AQ8>1, C8<B8), "Invalid", IF( OR(G8="Unknown", M8="Unknown"), "Warning", "Clean" ) ) -> Clean | AB8: =IF( OR( B8="", C8="", NOT(ISNUMBER(B8)), NOT(ISNUMBER(C8)), C8<B8 ), "Invalid", "Valid" ) -> Valid | AC8: 6 | AD8: =IF(C8<B8,"Invalid Shipping Date","Valid") -> Valid | AE8: =IF(AND(B8<>"",NOT(ISNUMBER(B8))),"Text Not Date","Valid") -> Valid | AF8: =IF(ISNUMBER(B8),"Valid","Invalid") -> Valid | AG8: =IF(ISNUMBER(C8),"Valid","Invalid") -> Valid | AH8: =IF(OR(B8="",ISBLANK(B8)),"Missing","Valid") -> Valid | AI8: =IF(OR(C8="",ISBLANK(C8)),"Missing","Valid") -> Valid | AJ8: FALSE | AK8: FALSE | AL8: FALSE | AM8: FALSE | AN8: FALSE | AO8: FALSE | AP8: FALSE | AQ8: =IF(OR(P8="",ISBLANK(P8)),0,P8) -> 0.15 | AR8: =N8*O8*(1-AQ8) -> 5847.558 | AS8: =Q8-AR8 -> 0.002 | AT8: =AR8-R8 -> 1120.308 | AU8: =S8-AT8 -> 0.002 | AV8: =AT8/AR8 -> 0.19158562 | AW8: =TEXT(B8,"mmmm") -> April | AX8: =YEAR(B8) -> 2025
A9: ORD-2025-10008 | B9: 45711 | C9: 45714 | D9: CUST-4683 | E9: Isha Nair | F9: Small Business | G9: South | H9: Andhra Pradesh | I9: Vijayawada | J9: Office Supplies | K9: Art | L9: Eco Art 848 | M9: First Class | N9: 1 | O9: 2980.71 | P9: 0 | Q9: 2980.71 | R9: 2357.22 | S9: 623.49 | T9: Paid | U9: Completed | V9: =TEXTJOIN("|",TRUE,A9:U9) -> #NAME? | W9: =IFERROR(__xludf.DUMMYFUNCTION("IF(COUNTIF($A:$A,A3)=1, ""Unique"", IF(COUNTUNIQUE(FILTER($V$2:$V$934,$A$2:$A$934=A3))>1, ""Conflicting Duplicate"", ""Exact Duplicate""))"),"Unique") -> Unique | X9: =COUNTIF(V:V,V9)>1 -> TRUE | Y9: =IF(COUNTIF($A:$A,A9)>1,"Duplicate Order ID","Unique") -> Unique | AA9: =IF( OR(AQ9<0, AQ9>1, C9<B9), "Invalid", IF( OR(G9="Unknown", M9="Unknown"), "Warning", "Clean" ) ) -> Clean | AB9: =IF( OR( B9="", C9="", NOT(ISNUMBER(B9)), NOT(ISNUMBER(C9)), C9<B9 ), "Invalid", "Valid" ) -> Valid | AC9: 3 | AD9: =IF(C9<B9,"Invalid Shipping Date","Valid") -> Valid | AE9: =IF(AND(B9<>"",NOT(ISNUMBER(B9))),"Text Not Date","Valid") -> Valid | AF9: =IF(ISNUMBER(B9),"Valid","Invalid") -> Valid | AG9: =IF(ISNUMBER(C9),"Valid","Invalid") -> Valid | AH9: =IF(OR(B9="",ISBLANK(B9)),"Missing","Valid") -> Valid | AI9: =IF(OR(C9="",ISBLANK(C9)),"Missing","Valid") -> Valid | AJ9: FALSE | AK9: FALSE | AL9: FALSE | AM9: FALSE | AN9: FALSE | AO9: FALSE | AP9: FALSE | AQ9: =IF(OR(P9="",ISBLANK(P9)),0,P9) -> 0 | AR9: =N9*O9*(1-AQ9) -> 2980.71 | AS9: =Q9-AR9 -> 0 | AT9: =AR9-R9 -> 623.49 | AU9: =S9-AT9 -> 0 | AV9: =AT9/AR9 -> 0.209175 | AW9: =TEXT(B9,"mmmm") -> February | AX9: =YEAR(B9) -> 2025
A10: ORD-2024-10009 | B10: 45601 | C10: 45606 | D10: CUST-2598 | E10: Aditi Sen | F10: Corporate | G10: South | H10: Telangana | I10: Hyderabad | J10: Office Supplies | K10: Labels | L10: Classic Labels 815 | M10: First Class | N10: 8 | O10: 3134.2 | P10: 0 | Q10: 25073.6 | R10: 17347.23 | S10: 7726.37 | T10: Paid | U10: Completed | V10: =TEXTJOIN("|",TRUE,A10:U10) -> #NAME? | W10: =IFERROR(__xludf.DUMMYFUNCTION("IF(COUNTIF($A:$A,A4)=1, ""Unique"", IF(COUNTUNIQUE(FILTER($V$2:$V$934,$A$2:$A$934=A4))>1, ""Conflicting Duplicate"", ""Exact Duplicate""))"),"Unique") -> Unique | X10: =COUNTIF(V:V,V10)>1 -> TRUE | Y10: =IF(COUNTIF($A:$A,A10)>1,"Duplicate Order ID","Unique") -> Unique | AA10: =IF( OR(AQ10<0, AQ10>1, C10<B10), "Invalid", IF( OR(G10="Unknown", M10="Unknown"), "Warning", "Clean" ) ) -> Clean | AB10: =IF( OR( B10="", C10="", NOT(ISNUMBER(B10)), NOT(ISNUMBER(C10)), C10<B10 ), "Invalid", "Valid" ) -> Valid | AC10: 5 | AD10: =IF(C10<B10,"Invalid Shipping Date","Valid") -> Valid | AE10: =IF(AND(B10<>"",NOT(ISNUMBER(B10))),"Text Not Date","Valid") -> Valid | AF10: =IF(ISNUMBER(B10),"Valid","Invalid") -> Valid | AG10: =IF(ISNUMBER(C10),"Valid","Invalid") -> Valid | AH10: =IF(OR(B10="",ISBLANK(B10)),"Missing","Valid") -> Valid | AI10: =IF(OR(C10="",ISBLANK(C10)),"Missing","Valid") -> Valid | AJ10: FALSE | AK10: FALSE | AL10: FALSE | AM10: FALSE | AN10: FALSE | AO10: FALSE | AP10: FALSE | AQ10: =IF(OR(P10="",ISBLANK(P10)),0,P10) -> 0 | AR10: =N10*O10*(1-AQ10) -> 25073.6 | AS10: =Q10-AR10 -> 0 | AT10: =AR10-R10 -> 7726.37 | AU10: =S10-AT10 -> 0 | AV10: =AT10/AR10 -> 0.30814761 | AW10: =TEXT(B10,"mmmm") -> November | AX10: =YEAR(B10) -> 2024
A11: ORD-2025-10010 | B11: 45907 | C11: 45912 | D11: CUST-2483 | E11: Mira Das | F11: Home Office | G11: South | H11: Telangana | I11: Hyderabad | J11: Office Supplies | K11: Paper | L11: Pro Paper 622 | M11: Second Class | N11: 9 | O11: 852.04 | P11: 0.2 | Q11: 6134.69 | R11: 3800.19 | S11: 2334.5 | T11: Paid | U11: Completed | V11: =TEXTJOIN("|",TRUE,A11:U11) -> #NAME? | W11: =IFERROR(__xludf.DUMMYFUNCTION("IF(COUNTIF($A:$A,A5)=1, ""Unique"", IF(COUNTUNIQUE(FILTER($V$2:$V$934,$A$2:$A$934=A5))>1, ""Conflicting Duplicate"", ""Exact Duplicate""))"),"Unique") -> Unique | X11: =COUNTIF(V:V,V11)>1 -> TRUE | Y11: =IF(COUNTIF($A:$A,A11)>1,"Duplicate Order ID","Unique") -> Unique | AA11: =IF( OR(AQ11<0, AQ11>1, C11<B11), "Invalid", IF( OR(G11="Unknown", M11="Unknown"), "Warning", "Clean" ) ) -> Clean | AB11: =IF( OR( B11="", C11="", NOT(ISNUMBER(B11)), NOT(ISNUMBER(C11)), C11<B11 ), "Invalid", "Valid" ) -> Valid | AC11: 5 | AD11: =IF(C11<B11,"Invalid Shipping Date","Valid") -> Valid | AE11: =IF(AND(B11<>"",NOT(ISNUMBER(B11))),"Text Not Date","Valid") -> Valid | AF11: =IF(ISNUMBER(B11),"Valid","Invalid") -> Valid | AG11: =IF(ISNUMBER(C11),"Valid","Invalid") -> Valid | AH11: =IF(OR(B11="",ISBLANK(B11)),"Missing","Valid") -> Valid | AI11: =IF(OR(C11="",ISBLANK(C11)),"Missing","Valid") -> Valid | AJ11: FALSE | AK11: FALSE | AL11: FALSE | AM11: FALSE | AN11: FALSE | AO11: FALSE | AP11: FALSE | AQ11: =IF(OR(P11="",ISBLANK(P11)),0,P11) -> 0.2 | AR11: =N11*O11*(1-AQ11) -> 6134.688 | AS11: =Q11-AR11 -> 0.002 | AT11: =AR11-R11 -> 2334.498 | AU11: =S11-AT11 -> 0.002 | AV11: =AT11/AR11 -> 0.38054062 | AW11: =TEXT(B11,"mmmm") -> September | AX11: =YEAR(B11) -> 2025
A12: ORD-2025-10011 | B12: 45797 | C12: 45797 | D12: CUST-8092 | E12: Ananya Rao | F12: Corporate | G12: East | H12: West Bengal | I12: Kolkata | J12: Office Supplies | K12: Labels | L12: Prime Labels 644 | M12: Second Class | N12: 3 | O12: 3534.83 | P12: 0.05 | Q12: 10074.27 | R12: 6048.27 | S12: 4026 | T12: Refunded | U12: Returned | V12: =TEXTJOIN("|",TRUE,A12:U12) -> #NAME? | W12: =IFERROR(__xludf.DUMMYFUNCTION("IF(COUNTIF($A:$A,A6)=1, ""Unique"", IF(COUNTUNIQUE(FILTER($V$2:$V$934,$A$2:$A$934=A6))>1, ""Conflicting Duplicate"", ""Exact Duplicate""))"),"Unique") -> Unique | X12: =COUNTIF(V:V,V12)>1 -> TRUE | Y12: =IF(COUNTIF($A:$A,A12)>1,"Duplicate Order ID","Unique") -> Unique | AA12: =IF( OR(AQ12<0, AQ12>1, C12<B12), "Invalid", IF( OR(G12="Unknown", M12="Unknown"), "Warning", "Clean" ) ) -> Clean | AB12: =IF( OR( B12="", C12="", NOT(ISNUMBER(B12)), NOT(ISNUMBER(C12)), C12<B12 ), "Invalid", "Valid" ) -> Valid | AC12: 0 | AD12: =IF(C12<B12,"Invalid Shipping Date","Valid") -> Valid | AE12: =IF(AND(B12<>"",NOT(ISNUMBER(B12))),"Text Not Date","Valid") -> Valid | AF12: =IF(ISNUMBER(B12),"Valid","Invalid") -> Valid | AG12: =IF(ISNUMBER(C12),"Valid","Invalid") -> Valid | AH12: =IF(OR(B12="",ISBLANK(B12)),"Missing","Valid") -> Valid | AI12: =IF(OR(C12="",ISBLANK(C12)),"Missing","Valid") -> Valid | AJ12: FALSE | AK12: FALSE | AL12: FALSE | AM12: FALSE | AN12: FALSE | AO12: FALSE | AP12: FALSE | AQ12: =IF(OR(P12="",ISBLANK(P12)),0,P12) -> 0.05 | AR12: =N12*O12*(1-AQ12) -> 10074.265 | AS12: =Q12-AR12 -> 0.0045 | AT12: =AR12-R12 -> 4025.9955 | AU12: =S12-AT12 -> 0.0045 | AV12: =AT12/AR12 -> 0.39963167 | AW12: =TEXT(B12,"mmmm") -> May | AX12: =YEAR(B12) -> 2025
A13: ORD-2024-10012 | B13: 45495 | C13: 45496 | D13: CUST-6528 | E13: Vikram Iyer | F13: Small Business | G13: East | H13: Odisha | I13: Bhubaneswar | J13: Technology | K13: Accessories | L13: Smart Accessories 603 | M13: Same Day | N13: 6 | O13: 2005.95 | P13: 0.2 | Q13: 9628.56 | R13: 8038.59 | S13: 1589.97 | T13: Paid | U13: Completed | V13: =TEXTJOIN("|",TRUE,A13:U13) -> #NAME? | W13: =IFERROR(__xludf.DUMMYFUNCTION("IF(COUNTIF($A:$A,A7)=1, ""Unique"", IF(COUNTUNIQUE(FILTER($V$2:$V$934,$A$2:$A$934=A7))>1, ""Conflicting Duplicate"", ""Exact Duplicate""))"),"Unique") -> Unique | X13: =COUNTIF(V:V,V13)>1 -> TRUE | Y13: =IF(COUNTIF($A:$A,A13)>1,"Duplicate Order ID","Unique") -> Unique | AA13: =IF( OR(AQ13<0, AQ13>1, C13<B13), "Invalid", IF( OR(G13="Unknown", M13="Unknown"), "Warning", "Clean" ) ) -> Clean | AB13: =IF( OR( B13="", C13="", NOT(ISNUMBER(B13)), NOT(ISNUMBER(C13)), C13<B13 ), "Invalid", "Valid" ) -> Valid | AC13: 1 | AD13: =IF(C13<B13,"Invalid Shipping Date","Valid") -> Valid | AE13: =IF(AND(B13<>"",NOT(ISNUMBER(B13))),"Text Not Date","Valid") -> Valid | AF13: =IF(ISNUMBER(B13),"Valid","Invalid") -> Valid | AG13: =IF(ISNUMBER(C13),"Valid","Invalid") -> Valid | AH13: =IF(OR(B13="",ISBLANK(B13)),"Missing","Valid") -> Valid | AI13: =IF(OR(C13="",ISBLANK(C13)),"Missing","Valid") -> Valid | AJ13: FALSE | AK13: FALSE | AL13: FALSE | AM13: FALSE | AN13: FALSE | AO13: FALSE | AP13: FALSE | AQ13: =IF(OR(P13="",ISBLANK(P13)),0,P13) -> 0.2 | AR13: =N13*O13*(1-AQ13) -> 9628.56 | AS13: =Q13-AR13 -> 0 | AT13: =AR13-R13 -> 1589.97 | AU13: =S13-AT13 -> 0 | AV13: =AT13/AR13 -> 0.16513061 | AW13: =TEXT(B13,"mmmm") -> July | AX13: =YEAR(B13) -> 2024
A14: ORD-2024-10013 | B14: 45646 | C14: 45647 | D14: CUST-2648 | E14: Ananya Rao | F14: Corporate | G14: West | H14: Rajasthan | I14: Udaipur | J14: Office Supplies | K14: Paper | L14: Pro Paper 481 | M14: First Class | N14: 1 | O14: 702.14 | P14: 0.15 | Q14: 596.82 | R14: 380.25 | S14: 216.57 | T14: Pending | U14: Returned | V14: =TEXTJOIN("|",TRUE,A14:U14) -> #NAME? | W14: =IFERROR(__xludf.DUMMYFUNCTION("IF(COUNTIF($A:$A,A8)=1, ""Unique"", IF(COUNTUNIQUE(FILTER($V$2:$V$934,$A$2:$A$934=A8))>1, ""Conflicting Duplicate"", ""Exact Duplicate""))"),"Exact Duplicate") -> Exact Duplicate | X14: =COUNTIF(V:V,V14)>1 -> TRUE | Y14: =IF(COUNTIF($A:$A,A14)>1,"Duplicate Order ID","Unique") -> Unique | AA14: =IF( OR(AQ14<0, AQ14>1, C14<B14), "Invalid", IF( OR(G14="Unknown", M14="Unknown"), "Warning", "Clean" ) ) -> Clean | AB14: =IF( OR( B14="", C14="", NOT(ISNUMBER(B14)), NOT(ISNUMBER(C14)), C14<B14 ), "Invalid", "Valid" ) -> Valid | AC14: 1 | AD14: =IF(C14<B14,"Invalid Shipping Date","Valid") -> Valid | AE14: =IF(AND(B14<>"",NOT(ISNUMBER(B14))),"Text Not Date","Valid") -> Valid | AF14: =IF(ISNUMBER(B14),"Valid","Invalid") -> Valid | AG14: =IF(ISNUMBER(C14),"Valid","Invalid") -> Valid | AH14: =IF(OR(B14="",ISBLANK(B14)),"Missing","Valid") -> Valid | AI14: =IF(OR(C14="",ISBLANK(C14)),"Missing","Valid") -> Valid | AJ14: FALSE | AK14: FALSE | AL14: FALSE | AM14: FALSE | AN14: FALSE | AO14: FALSE | AP14: FALSE | AQ14: =IF(OR(P14="",ISBLANK(P14)),0,P14) -> 0.15 | AR14: =N14*O14*(1-AQ14) -> 596.819 | AS14: =Q14-AR14 -> 0.001 | AT14: =AR14-R14 -> 216.569 | AU14: =S14-AT14 -> 0.001 | AV14: =AT14/AR14 -> 0.36287216 | AW14: =TEXT(B14,"mmmm") -> December | AX14: =YEAR(B14) -> 2024
A15: ORD-2025-10014 | B15: 45942 | C15: 45946 | D15: CUST-7482 | E15: Priya Menon | F15: Small Business | G15: West | H15: Maharashtra | I15: Mumbai | J15: Office Supplies | K15: Art | L15: Smart Art 795 | M15: Second Class | N15: 7 | O15: 3964.72 | P15: 0.05 | Q15: 26365.39 | R15: 22306.24 | S15: 4059.15 | T15: Paid | U15: Completed | V15: =TEXTJOIN("|",TRUE,A15:U15) -> #NAME? | W15: =IFERROR(__xludf.DUMMYFUNCTION("IF(COUNTIF($A:$A,A9)=1, ""Unique"", IF(COUNTUNIQUE(FILTER($V$2:$V$934,$A$2:$A$934=A9))>1, ""Conflicting Duplicate"", ""Exact Duplicate""))"),"Unique") -> Unique | X15: =COUNTIF(V:V,V15)>1 -> TRUE | Y15: =IF(COUNTIF($A:$A,A15)>1,"Duplicate Order ID","Unique") -> Unique | AA15: =IF( OR(AQ15<0, AQ15>1, C15<B15), "Invalid", IF( OR(G15="Unknown", M15="Unknown"), "Warning", "Clean" ) ) -> Clean | AB15: =IF( OR( B15="", C15="", NOT(ISNUMBER(B15)), NOT(ISNUMBER(C15)), C15<B15 ), "Invalid", "Valid" ) -> Valid | AC15: 4 | AD15: =IF(C15<B15,"Invalid Shipping Date","Valid") -> Valid | AE15: =IF(AND(B15<>"",NOT(ISNUMBER(B15))),"Text Not Date","Valid") -> Valid | AF15: =IF(ISNUMBER(B15),"Valid","Invalid") -> Valid | AG15: =IF(ISNUMBER(C15),"Valid","Invalid") -> Valid | AH15: =IF(OR(B15="",ISBLANK(B15)),"Missing","Valid") -> Valid | AI15: =IF(OR(C15="",ISBLANK(C15)),"Missing","Valid") -> Valid | AJ15: FALSE | AK15: FALSE | AL15: FALSE | AM15: FALSE | AN15: FALSE | AO15: FALSE | AP15: FALSE | AQ15: =IF(OR(P15="",ISBLANK(P15)),0,P15) -> 0.05 | AR15: =N15*O15*(1-AQ15) -> 26365.388 | AS15: =Q15-AR15 -> 0.002 | AT15: =AR15-R15 -> 4059.148 | AU15: =S15-AT15 -> 0.002 | AV15: =AT15/AR15 -> 0.15395745 | AW15: =TEXT(B15,"mmmm") -> October | AX15: =YEAR(B15) -> 2025
A16: ORD-2024-10015 | B16: 45653 | C16: 45654 | D16: CUST-4912 | E16: Rahul Verma | F16: Consumer | G16: West | H16: Rajasthan | I16: Udaipur | J16: Technology | K16: Copiers | L16: Max Copiers 983 | M16: Standard Class | N16: 2 | O16: 2737.83 | P16: 0.25 | Q16: 4106.74 | R16: 2666.3 | S16: 1440.44 | T16: Paid | U16: Completed | V16: =TEXTJOIN("|",TRUE,A16:U16) -> #NAME? | W16: =IFERROR(__xludf.DUMMYFUNCTION("IF(COUNTIF($A:$A,A10)=1, ""Unique"", IF(COUNTUNIQUE(FILTER($V$2:$V$934,$A$2:$A$934=A10))>1, ""Conflicting Duplicate"", ""Exact Duplicate""))"),"Unique") -> Unique | X16: =COUNTIF(V:V,V16)>1 -> TRUE | Y16: =IF(COUNTIF($A:$A,A16)>1,"Duplicate Order ID","Unique") -> Unique | AA16: =IF( OR(AQ16<0, AQ16>1, C16<B16), "Invalid", IF( OR(G16="Unknown", M16="Unknown"), "Warning", "Clean" ) ) -> Clean | AB16: =IF( OR( B16="", C16="", NOT(ISNUMBER(B16)), NOT(ISNUMBER(C16)), C16<B16 ), "Invalid", "Valid" ) -> Valid | AC16: 1 | AD16: =IF(C16<B16,"Invalid Shipping Date","Valid") -> Valid | AE16: =IF(AND(B16<>"",NOT(ISNUMBER(B16))),"Text Not Date","Valid") -> Valid | AF16: =IF(ISNUMBER(B16),"Valid","Invalid") -> Valid | AG16: =IF(ISNUMBER(C16),"Valid","Invalid") -> Valid | AH16: =IF(OR(B16="",ISBLANK(B16)),"Missing","Valid") -> Valid | AI16: =IF(OR(C16="",ISBLANK(C16)),"Missing","Valid") -> Valid | AJ16: FALSE | AK16: FALSE | AL16: FALSE | AM16: FALSE | AN16: FALSE | AO16: FALSE | AP16: FALSE | AQ16: =IF(OR(P16="",ISBLANK(P16)),0,P16) -> 0.25 | AR16: =N16*O16*(1-AQ16) -> 4106.745 | AS16: =Q16-AR16 -> -0.005 | AT16: =AR16-R16 -> 1440.445 | AU16: =S16-AT16 -> -0.005 | AV16: =AT16/AR16 -> 0.35075102 | AW16: =TEXT(B16,"mmmm") -> December | AX16: =YEAR(B16) -> 2024
A17: ORD-2024-10016 | B17: 45482 | C17: 45482 | D17: CUST-7656 | E17: Karan Malhotra | F17: Small Business | G17: North | H17: Punjab | I17: Ludhiana | J17: Office Supplies | K17: Storage | L17: Classic Storage 198 | M17: Second Class | N17: 6 | O17: 3965.76 | P17: 0 | Q17: 23794.56 | R17: 15698.47 | S17: 8096.09 | T17: Paid | U17: Completed | V17: =TEXTJOIN("|",TRUE,A17:U17) -> #NAME? | W17: =IFERROR(__xludf.DUMMYFUNCTION("IF(COUNTIF($A:$A,A11)=1, ""Unique"", IF(COUNTUNIQUE(FILTER($V$2:$V$934,$A$2:$A$934=A11))>1, ""Conflicting Duplicate"", ""Exact Duplicate""))"),"Unique") -> Unique | X17: =COUNTIF(V:V,V17)>1 -> TRUE | Y17: =IF(COUNTIF($A:$A,A17)>1,"Duplicate Order ID","Unique") -> Unique | AA17: =IF( OR(AQ17<0, AQ17>1, C17<B17), "Invalid", IF( OR(G17="Unknown", M17="Unknown"), "Warning", "Clean" ) ) -> Clean | AB17: =IF( OR( B17="", C17="", NOT(ISNUMBER(B17)), NOT(ISNUMBER(C17)), C17<B17 ), "Invalid", "Valid" ) -> Valid | AC17: 0 | AD17: =IF(C17<B17,"Invalid Shipping Date","Valid") -> Valid | AE17: =IF(AND(B17<>"",NOT(ISNUMBER(B17))),"Text Not Date","Valid") -> Valid | AF17: =IF(ISNUMBER(B17),"Valid","Invalid") -> Valid | AG17: =IF(ISNUMBER(C17),"Valid","Invalid") -> Valid | AH17: =IF(OR(B17="",ISBLANK(B17)),"Missing","Valid") -> Valid | AI17: =IF(OR(C17="",ISBLANK(C17)),"Missing","Valid") -> Valid | AJ17: FALSE | AK17: FALSE | AL17: FALSE | AM17: FALSE | AN17: FALSE | AO17: FALSE | AP17: FALSE | AQ17: =IF(OR(P17="",ISBLANK(P17)),0,P17) -> 0 | AR17: =N17*O17*(1-AQ17) -> 23794.56 | AS17: =Q17-AR17 -> 0 | AT17: =AR17-R17 -> 8096.09 | AU17: =S17-AT17 -> 0 | AV17: =AT17/AR17 -> 0.34024962 | AW17: =TEXT(B17,"mmmm") -> July | AX17: =YEAR(B17) -> 2024
A18: ORD-2024-10017 | B18: 45420 | C18: 45427 | D18: CUST-6214 | E18: Aarav Sharma | F18: Consumer | G18: South | H18: Telangana | I18: Hyderabad | J18: Office Supplies | K18: Art | L18: Basic Art 204 | M18: First Class | N18: 4 | O18: 3323.51 | P18: 0.25 | Q18: 9970.53 | R18: 5668.17 | S18: 4302.36 | T18: Paid | U18: Completed | V18: =TEXTJOIN("|",TRUE,A18:U18) -> #NAME? | W18: =IFERROR(__xludf.DUMMYFUNCTION("IF(COUNTIF($A:$A,A12)=1, ""Unique"", IF(COUNTUNIQUE(FILTER($V$2:$V$934,$A$2:$A$934=A12))>1, ""Conflicting Duplicate"", ""Exact Duplicate""))"),"Unique") -> Unique | X18: =COUNTIF(V:V,V18)>1 -> TRUE | Y18: =IF(COUNTIF($A:$A,A18)>1,"Duplicate Order ID","Unique") -> Unique | AA18: =IF( OR(AQ18<0, AQ18>1, C18<B18), "Invalid", IF( OR(G18="Unknown", M18="Unknown"), "Warning", "Clean" ) ) -> Clean | AB18: =IF( OR( B18="", C18="", NOT(ISNUMBER(B18)), NOT(ISNUMBER(C18)), C18<B18 ), "Invalid", "Valid" ) -> Valid | AC18: 7 | AD18: =IF(C18<B18,"Invalid Shipping Date","Valid") -> Valid | AE18: =IF(AND(B18<>"",NOT(ISNUMBER(B18))),"Text Not Date","Valid") -> Valid | AF18: =IF(ISNUMBER(B18),"Valid","Invalid") -> Valid | AG18: =IF(ISNUMBER(C18),"Valid","Invalid") -> Valid | AH18: =IF(OR(B18="",ISBLANK(B18)),"Missing","Valid") -> Valid | AI18: =IF(OR(C18="",ISBLANK(C18)),"Missing","Valid") -> Valid | AJ18: FALSE | AK18: FALSE | AL18: FALSE | AM18: FALSE | AN18: FALSE | AO18: FALSE | AP18: FALSE | AQ18: =IF(OR(P18="",ISBLANK(P18)),0,P18) -> 0.25 | AR18: =N18*O18*(1-AQ18) -> 9970.53 | AS18: =Q18-AR18 -> 0 | AT18: =AR18-R18 -> 4302.36 | AU18: =S18-AT18 -> 0 | AV18: =AT18/AR18 -> 0.43150765 | AW18: =TEXT(B18,"mmmm") -> May | AX18: =YEAR(B18) -> 2024
A19: ORD-2024-10018 | B19: 45298 | C19: 45299 | D19: CUST-1626 | E19: Sneha Kapoor | F19: Small Business | G19: North | H19: Rajasthan | I19: Jaipur | J19: Furniture | K19: Furnishings | L19: Basic Furnishings 434 | M19: Same Day | N19: 5 | O19: 1526.78 | P19: 0 | Q19: 7633.9 | R19: 4706.91 | S19: 2926.99 | T19: Paid | U19: Completed | V19: =TEXTJOIN("|",TRUE,A19:U19) -> #NAME? | W19: =IFERROR(__xludf.DUMMYFUNCTION("IF(COUNTIF($A:$A,A13)=1, ""Unique"", IF(COUNTUNIQUE(FILTER($V$2:$V$934,$A$2:$A$934=A13))>1, ""Conflicting Duplicate"", ""Exact Duplicate""))"),"Unique") -> Unique | X19: =COUNTIF(V:V,V19)>1 -> TRUE | Y19: =IF(COUNTIF($A:$A,A19)>1,"Duplicate Order ID","Unique") -> Unique | AA19: =IF( OR(AQ19<0, AQ19>1, C19<B19), "Invalid", IF( OR(G19="Unknown", M19="Unknown"), "Warning", "Clean" ) ) -> Clean | AB19: =IF( OR( B19="", C19="", NOT(ISNUMBER(B19)), NOT(ISNUMBER(C19)), C19<B19 ), "Invalid", "Valid" ) -> Valid | AC19: 1 | AD19: =IF(C19<B19,"Invalid Shipping Date","Valid") -> Valid | AE19: =IF(AND(B19<>"",NOT(ISNUMBER(B19))),"Text Not Date","Valid") -> Valid | AF19: =IF(ISNUMBER(B19),"Valid","Invalid") -> Valid | AG19: =IF(ISNUMBER(C19),"Valid","Invalid") -> Valid | AH19: =IF(OR(B19="",ISBLANK(B19)),"Missing","Valid") -> Valid | AI19: =IF(OR(C19="",ISBLANK(C19)),"Missing","Valid") -> Valid | AJ19: FALSE | AK19: FALSE | AL19: FALSE | AM19: FALSE | AN19: FALSE | AO19: FALSE | AP19: FALSE | AQ19: =IF(OR(P19="",ISBLANK(P19)),0,P19) -> 0 | AR19: =N19*O19*(1-AQ19) -> 7633.9 | AS19: =Q19-AR19 -> 0 | AT19: =AR19-R19 -> 2926.99 | AU19: =S19-AT19 -> 0 | AV19: =AT19/AR19 -> 0.38342001 | AW19: =TEXT(B19,"mmmm") -> January | AX19: =YEAR(B19) -> 2024
A20: ORD-2025-10019 | B20: 45853 | C20: 45855 | D20: CUST-2110 | E20: Aarav Sharma | F20: Home Office | G20: North | H20: Uttar Pradesh | I20: Noida | J20: Technology | K20: Copiers | L20: Eco Copiers 755 | M20: First Class | N20: 2 | O20: 1997.99 | P20: 0 | Q20: 3995.98 | R20: 2633.2 | S20: 1362.78 | T20: Refunded | U20: Cancelled | V20: =TEXTJOIN("|",TRUE,A20:U20) -> #NAME? | W20: =IFERROR(__xludf.DUMMYFUNCTION("IF(COUNTIF($A:$A,A14)=1, ""Unique"", IF(COUNTUNIQUE(FILTER($V$2:$V$934,$A$2:$A$934=A14))>1, ""Conflicting Duplicate"", ""Exact Duplicate""))"),"Unique") -> Unique | X20: =COUNTIF(V:V,V20)>1 -> TRUE | Y20: =IF(COUNTIF($A:$A,A20)>1,"Duplicate Order ID","Unique") -> Unique | AA20: =IF( OR(AQ20<0, AQ20>1, C20<B20), "Invalid", IF( OR(G20="Unknown", M20="Unknown"), "Warning", "Clean" ) ) -> Clean | AB20: =IF( OR( B20="", C20="", NOT(ISNUMBER(B20)), NOT(ISNUMBER(C20)), C20<B20 ), "Invalid", "Valid" ) -> Valid | AC20: 2 | AD20: =IF(C20<B20,"Invalid Shipping Date","Valid") -> Valid | AE20: =IF(AND(B20<>"",NOT(ISNUMBER(B20))),"Text Not Date","Valid") -> Valid | AF20: =IF(ISNUMBER(B20),"Valid","Invalid") -> Valid | AG20: =IF(ISNUMBER(C20),"Valid","Invalid") -> Valid | AH20: =IF(OR(B20="",ISBLANK(B20)),"Missing","Valid") -> Valid | AI20: =IF(OR(C20="",ISBLANK(C20)),"Missing","Valid") -> Valid | AJ20: FALSE | AK20: FALSE | AL20: FALSE | AM20: FALSE | AN20: FALSE | AO20: FALSE | AP20: FALSE | AQ20: =IF(OR(P20="",ISBLANK(P20)),0,P20) -> 0 | AR20: =N20*O20*(1-AQ20) -> 3995.98 | AS20: =Q20-AR20 -> 0 | AT20: =AR20-R20 -> 1362.78 | AU20: =S20-AT20 -> 0 | AV20: =AT20/AR20 -> 0.34103774 | AW20: =TEXT(B20,"mmmm") -> July | AX20: =YEAR(B20) -> 2025
A21: ORD-2024-10020 | B21: 45500 | C21: 45504 | D21: CUST-3186 | E21: Rohan Mehta | F21: Home Office | G21: West | H21: Madhya Pradesh | I21: Indore | J21: Office Supplies | K21: Storage | L21: Prime Storage 121 | M21: Second Class | N21: 3 | O21: 3887.94 | P21: -0.19 | Q21: 9331.06 | R21: 7529.31 | S21: 1801.75 | T21: Paid | U21: Completed | V21: =TEXTJOIN("|",TRUE,A21:U21) -> #NAME? | W21: =IFERROR(__xludf.DUMMYFUNCTION("IF(COUNTIF($A:$A,A15)=1, ""Unique"", IF(COUNTUNIQUE(FILTER($V$2:$V$934,$A$2:$A$934=A15))>1, ""Conflicting Duplicate"", ""Exact Duplicate""))"),"Unique") -> Unique | X21: =COUNTIF(V:V,V21)>1 -> TRUE | Y21: =IF(COUNTIF($A:$A,A21)>1,"Duplicate Order ID","Unique") -> Unique | AA21: =IF( OR(AQ21<0, AQ21>1, C21<B21), "Invalid", IF( OR(G21="Unknown", M21="Unknown"), "Warning", "Clean" ) ) -> Invalid | AB21: =IF( OR( B21="", C21="", NOT(ISNUMBER(B21)), NOT(ISNUMBER(C21)), C21<B21 ), "Invalid", "Valid" ) -> Valid | AC21: 4 | AD21: =IF(C21<B21,"Invalid Shipping Date","Valid") -> Valid | AE21: =IF(AND(B21<>"",NOT(ISNUMBER(B21))),"Text Not Date","Valid") -> Valid | AF21: =IF(ISNUMBER(B21),"Valid","Invalid") -> Valid | AG21: =IF(ISNUMBER(C21),"Valid","Invalid") -> Valid | AH21: =IF(OR(B21="",ISBLANK(B21)),"Missing","Valid") -> Valid | AI21: =IF(OR(C21="",ISBLANK(C21)),"Missing","Valid") -> Valid | AJ21: FALSE | AK21: FALSE | AL21: FALSE | AM21: TRUE | AN21: FALSE | AO21: FALSE | AP21: TRUE | AQ21: =IF(OR(P21="",ISBLANK(P21)),0,P21) -> -0.19 | AR21: =N21*O21*(1-AQ21) -> 13879.946 | AS21: =Q21-AR21 -> -4548.8858 | AT21: =AR21-R21 -> 6350.6358 | AU21: =S21-AT21 -> -4548.8858 | AV21: =AT21/AR21 -> 0.45754039 | AW21: =TEXT(B21,"mmmm") -> July | AX21: =YEAR(B21) -> 2024
A22: ORD-2025-10021 | B22: 45678 | C22: 45680 | D22: CUST-3190 | E22: Aditi Sen | F22: Home Office | G22: East | H22: Bihar | I22: Patna | J22: Technology | K22: Copiers | L22: Elite Copiers 233 | M22: First Class | N22: 5 | O22: 4373.06 | P22: 0.25 | Q22: 16398.98 | R22: 9556.52 | S22: 6842.46 | T22: Paid | U22: Completed | V22: =TEXTJOIN("|",TRUE,A22:U22) -> #NAME? | W22: =IFERROR(__xludf.DUMMYFUNCTION("IF(COUNTIF($A:$A,A16)=1, ""Unique"", IF(COUNTUNIQUE(FILTER($V$2:$V$934,$A$2:$A$934=A16))>1, ""Conflicting Duplicate"", ""Exact Duplicate""))"),"Unique") -> Unique | X22: =COUNTIF(V:V,V22)>1 -> TRUE | Y22: =IF(COUNTIF($A:$A,A22)>1,"Duplicate Order ID","Unique") -> Unique | AA22: =IF( OR(AQ22<0, AQ22>1, C22<B22), "Invalid", IF( OR(G22="Unknown", M22="Unknown"), "Warning", "Clean" ) ) -> Clean | AB22: =IF( OR( B22="", C22="", NOT(ISNUMBER(B22)), NOT(ISNUMBER(C22)), C22<B22 ), "Invalid", "Valid" ) -> Valid | AC22: 2 | AD22: =IF(C22<B22,"Invalid Shipping Date","Valid") -> Valid | AE22: =IF(AND(B22<>"",NOT(ISNUMBER(B22))),"Text Not Date","Valid") -> Valid | AF22: =IF(ISNUMBER(B22),"Valid","Invalid") -> Valid | AG22: =IF(ISNUMBER(C22),"Valid","Invalid") -> Valid | AH22: =IF(OR(B22="",ISBLANK(B22)),"Missing","Valid") -> Valid | AI22: =IF(OR(C22="",ISBLANK(C22)),"Missing","Valid") -> Valid | AJ22: FALSE | AK22: FALSE | AL22: FALSE | AM22: FALSE | AN22: FALSE | AO22: FALSE | AP22: FALSE | AQ22: =IF(OR(P22="",ISBLANK(P22)),0,P22) -> 0.25 | AR22: =N22*O22*(1-AQ22) -> 16398.975 | AS22: =Q22-AR22 -> 0.005 | AT22: =AR22-R22 -> 6842.455 | AU22: =S22-AT22 -> 0.005 | AV22: =AT22/AR22 -> 0.41724894 | AW22: =TEXT(B22,"mmmm") -> January | AX22: =YEAR(B22) -> 2025
A23: ORD-2025-10022 | B23: 45681 | C23: 45687 | D23: CUST-3036 | E23: Sneha Kapoor | F23: Consumer | G23: West | H23: Madhya Pradesh | I23: Indore | J23: Furniture | K23: Furnishings | L23: Eco Furnishings 897 | M23: Second Class | N23: 4 | O23: 697.69 | P23: -0.23 | Q23: 2790.76 | R23: 2037.71 | S23: 753.05 | T23: Paid | U23: Completed | V23: =TEXTJOIN("|",TRUE,A23:U23) -> #NAME? | W23: =IFERROR(__xludf.DUMMYFUNCTION("IF(COUNTIF($A:$A,A17)=1, ""Unique"", IF(COUNTUNIQUE(FILTER($V$2:$V$934,$A$2:$A$934=A17))>1, ""Conflicting Duplicate"", ""Exact Duplicate""))"),"Unique") -> Unique | X23: =COUNTIF(V:V,V23)>1 -> TRUE | Y23: =IF(COUNTIF($A:$A,A23)>1,"Duplicate Order ID","Unique") -> Unique | AA23: =IF( OR(AQ23<0, AQ23>1, C23<B23), "Invalid", IF( OR(G23="Unknown", M23="Unknown"), "Warning", "Clean" ) ) -> Invalid | AB23: =IF( OR( B23="", C23="", NOT(ISNUMBER(B23)), NOT(ISNUMBER(C23)), C23<B23 ), "Invalid", "Valid" ) -> Valid | AC23: 6 | AD23: =IF(C23<B23,"Invalid Shipping Date","Valid") -> Valid | AE23: =IF(AND(B23<>"",NOT(ISNUMBER(B23))),"Text Not Date","Valid") -> Valid | AF23: =IF(ISNUMBER(B23),"Valid","Invalid") -> Valid | AG23: =IF(ISNUMBER(C23),"Valid","Invalid") -> Valid | AH23: =IF(OR(B23="",ISBLANK(B23)),"Missing","Valid") -> Valid | AI23: =IF(OR(C23="",ISBLANK(C23)),"Missing","Valid") -> Valid | AJ23: FALSE | AK23: FALSE | AL23: FALSE | AM23: TRUE | AN23: FALSE | AO23: FALSE | AP23: TRUE | AQ23: =IF(OR(P23="",ISBLANK(P23)),0,P23) -> -0.23 | AR23: =N23*O23*(1-AQ23) -> 3432.6348 | AS23: =Q23-AR23 -> -641.8748 | AT23: =AR23-R23 -> 1394.9248 | AU23: =S23-AT23 -> -641.8748 | AV23: =AT23/AR23 -> 0.40637146 | AW23: =TEXT(B23,"mmmm") -> January | AX23: =YEAR(B23) -> 2025
A24: ORD-2025-10023 | B24: 45676 | C24: 45678 | D24: CUST-3588 | E24: Mira Das | F24: Consumer | G24: South | H24: Telangana | I24: Hyderabad | J24: Office Supplies | K24: Binders | L24: Max Binders 355 | M24: Standard Class | N24: 8 | O24: 1219.34 | P24: 0.15 | Q24: 8291.51 | R24: 6685.03 | S24: 1606.48 | T24: Failed | U24: Returned | V24: =TEXTJOIN("|",TRUE,A24:U24) -> #NAME? | W24: =IFERROR(__xludf.DUMMYFUNCTION("IF(COUNTIF($A:$A,A18)=1, ""Unique"", IF(COUNTUNIQUE(FILTER($V$2:$V$934,$A$2:$A$934=A18))>1, ""Conflicting Duplicate"", ""Exact Duplicate""))"),"Unique") -> Unique | X24: =COUNTIF(V:V,V24)>1 -> TRUE | Y24: =IF(COUNTIF($A:$A,A24)>1,"Duplicate Order ID","Unique") -> Unique | AA24: =IF( OR(AQ24<0, AQ24>1, C24<B24), "Invalid", IF( OR(G24="Unknown", M24="Unknown"), "Warning", "Clean" ) ) -> Clean | AB24: =IF( OR( B24="", C24="", NOT(ISNUMBER(B24)), NOT(ISNUMBER(C24)), C24<B24 ), "Invalid", "Valid" ) -> Valid | AC24: 2 | AD24: =IF(C24<B24,"Invalid Shipping Date","Valid") -> Valid | AE24: =IF(AND(B24<>"",NOT(ISNUMBER(B24))),"Text Not Date","Valid") -> Valid | AF24: =IF(ISNUMBER(B24),"Valid","Invalid") -> Valid | AG24: =IF(ISNUMBER(C24),"Valid","Invalid") -> Valid | AH24: =IF(OR(B24="",ISBLANK(B24)),"Missing","Valid") -> Valid | AI24: =IF(OR(C24="",ISBLANK(C24)),"Missing","Valid") -> Valid | AJ24: FALSE | AK24: FALSE | AL24: FALSE | AM24: FALSE | AN24: FALSE | AO24: FALSE | AP24: FALSE | AQ24: =IF(OR(P24="",ISBLANK(P24)),0,P24) -> 0.15 | AR24: =N24*O24*(1-AQ24) -> 8291.512 | AS24: =Q24-AR24 -> -0.002 | AT24: =AR24-R24 -> 1606.482 | AU24: =S24-AT24 -> -0.002 | AV24: =AT24/AR24 -> 0.19375019 | AW24: =TEXT(B24,"mmmm") -> January | AX24: =YEAR(B24) -> 2025
A25: ORD-2025-10024 | B25: 45898 | C25: 45900 | D25: CUST-7098 | E25: Rahul Verma | F25: Home Office | G25: East | H25: Bihar | I25: Patna | J25: Furniture | K25: Bookcases | L25: Pro Bookcases 394 | M25: First Class | N25: 4 | O25: 1958.01 | P25: 0.2 | Q25: 6265.63 | R25: 4321.86 | S25: 1943.77 | T25: Paid | U25: Completed | V25: =TEXTJOIN("|",TRUE,A25:U25) -> #NAME? | W25: =IFERROR(__xludf.DUMMYFUNCTION("IF(COUNTIF($A:$A,A19)=1, ""Unique"", IF(COUNTUNIQUE(FILTER($V$2:$V$934,$A$2:$A$934=A19))>1, ""Conflicting Duplicate"", ""Exact Duplicate""))"),"Unique") -> Unique | X25: =COUNTIF(V:V,V25)>1 -> TRUE | Y25: =IF(COUNTIF($A:$A,A25)>1,"Duplicate Order ID","Unique") -> Unique | AA25: =IF( OR(AQ25<0, AQ25>1, C25<B25), "Invalid", IF( OR(G25="Unknown", M25="Unknown"), "Warning", "Clean" ) ) -> Clean | AB25: =IF( OR( B25="", C25="", NOT(ISNUMBER(B25)), NOT(ISNUMBER(C25)), C25<B25 ), "Invalid", "Valid" ) -> Valid | AC25: 2 | AD25: =IF(C25<B25,"Invalid Shipping Date","Valid") -> Valid | AE25: =IF(AND(B25<>"",NOT(ISNUMBER(B25))),"Text Not Date","Valid") -> Valid | AF25: =IF(ISNUMBER(B25),"Valid","Invalid") -> Valid | AG25: =IF(ISNUMBER(C25),"Valid","Invalid") -> Valid | AH25: =IF(OR(B25="",ISBLANK(B25)),"Missing","Valid") -> Valid | AI25: =IF(OR(C25="",ISBLANK(C25)),"Missing","Valid") -> Valid | AJ25: FALSE | AK25: FALSE | AL25: FALSE | AM25: FALSE | AN25: FALSE | AO25: FALSE | AP25: FALSE | AQ25: =IF(OR(P25="",ISBLANK(P25)),0,P25) -> 0.2 | AR25: =N25*O25*(1-AQ25) -> 6265.632 | AS25: =Q25-AR25 -> -0.002 | AT25: =AR25-R25 -> 1943.772 | AU25: =S25-AT25 -> -0.002 | AV25: =AT25/AR25 -> 0.3102276 | AW25: =TEXT(B25,"mmmm") -> August | AX25: =YEAR(B25) -> 2025
A26: ORD-2024-10025 | B26: 45355 | C26: 45352 | D26: CUST-1747 | E26: Diya Patel | F26: Consumer | G26: North | H26: Punjab | I26: Ludhiana | J26: Office Supplies | K26: Art | L26: Max Art 215 | M26: Standard Class | N26: 4 | O26: 4492.94 | P26: 0.25 | Q26: 13478.82 | R26: 10937.35 | S26: 2541.47 | T26: Pending | U26: Cancelled | V26: =TEXTJOIN("|",TRUE,A26:U26) -> #NAME? | W26: =IFERROR(__xludf.DUMMYFUNCTION("IF(COUNTIF($A:$A,A20)=1, ""Unique"", IF(COUNTUNIQUE(FILTER($V$2:$V$934,$A$2:$A$934=A20))>1, ""Conflicting Duplicate"", ""Exact Duplicate""))"),"Unique") -> Unique | X26: =COUNTIF(V:V,V26)>1 -> TRUE | Y26: =IF(COUNTIF($A:$A,A26)>1,"Duplicate Order ID","Unique") -> Unique | AA26: =IF( OR(AQ26<0, AQ26>1, C26<B26), "Invalid", IF( OR(G26="Unknown", M26="Unknown"), "Warning", "Clean" ) ) -> Invalid | AB26: =IF( OR( B26="", C26="", NOT(ISNUMBER(B26)), NOT(ISNUMBER(C26)), C26<B26 ), "Invalid", "Valid" ) -> Invalid | AC26: -3 | AD26: =IF(C26<B26,"Invalid Shipping Date","Valid") -> Invalid Shipping Date | AE26: =IF(AND(B26<>"",NOT(ISNUMBER(B26))),"Text Not Date","Valid") -> Valid | AF26: =IF(ISNUMBER(B26),"Valid","Invalid") -> Valid | AG26: =IF(ISNUMBER(C26),"Valid","Invalid") -> Valid | AH26: =IF(OR(B26="",ISBLANK(B26)),"Missing","Valid") -> Valid | AI26: =IF(OR(C26="",ISBLANK(C26)),"Missing","Valid") -> Valid | AJ26: FALSE | AK26: FALSE | AL26: FALSE | AM26: FALSE | AN26: FALSE | AO26: TRUE | AP26: TRUE | AQ26: =IF(OR(P26="",ISBLANK(P26)),0,P26) -> 0.25 | AR26: =N26*O26*(1-AQ26) -> 13478.82 | AS26: =Q26-AR26 -> 0 | AT26: =AR26-R26 -> 2541.47 | AU26: =S26-AT26 -> 0 | AV26: =AT26/AR26 -> 0.18855286 | AW26: =TEXT(B26,"mmmm") -> March | AX26: =YEAR(B26) -> 2024
A27: ORD-2024-10026 | B27: 45576 | C27: 45584 | D27: CUST-1731 | E27: Arjun Bose | F27: Corporate | G27: East | H27: Assam | I27: Guwahati | J27: Technology | K27: Accessories | L27: Classic Accessories 478 | M27: First Class | N27: 2 | O27: 4315.2 | P27: 0.15 | Q27: 7335.84 | R27: 4968.41 | S27: 2367.43 | T27: Paid | U27: Completed | V27: =TEXTJOIN("|",TRUE,A27:U27) -> #NAME? | W27: =IFERROR(__xludf.DUMMYFUNCTION("IF(COUNTIF($A:$A,A21)=1, ""Unique"", IF(COUNTUNIQUE(FILTER($V$2:$V$934,$A$2:$A$934=A21))>1, ""Conflicting Duplicate"", ""Exact Duplicate""))"),"Unique") -> Unique | X27: =COUNTIF(V:V,V27)>1 -> TRUE | Y27: =IF(COUNTIF($A:$A,A27)>1,"Duplicate Order ID","Unique") -> Unique | AA27: =IF( OR(AQ27<0, AQ27>1, C27<B27), "Invalid", IF( OR(G27="Unknown", M27="Unknown"), "Warning", "Clean" ) ) -> Clean | AB27: =IF( OR( B27="", C27="", NOT(ISNUMBER(B27)), NOT(ISNUMBER(C27)), C27<B27 ), "Invalid", "Valid" ) -> Valid | AC27: 8 | AD27: =IF(C27<B27,"Invalid Shipping Date","Valid") -> Valid | AE27: =IF(AND(B27<>"",NOT(ISNUMBER(B27))),"Text Not Date","Valid") -> Valid | AF27: =IF(ISNUMBER(B27),"Valid","Invalid") -> Valid | AG27: =IF(ISNUMBER(C27),"Valid","Invalid") -> Valid | AH27: =IF(OR(B27="",ISBLANK(B27)),"Missing","Valid") -> Valid | AI27: =IF(OR(C27="",ISBLANK(C27)),"Missing","Valid") -> Valid | AJ27: FALSE | AK27: FALSE | AL27: FALSE | AM27: FALSE | AN27: FALSE | AO27: FALSE | AP27: FALSE | AQ27: =IF(OR(P27="",ISBLANK(P27)),0,P27) -> 0.15 | AR27: =N27*O27*(1-AQ27) -> 7335.84 | AS27: =Q27-AR27 -> 0 | AT27: =AR27-R27 -> 2367.43 | AU27: =S27-AT27 -> 0 | AV27: =AT27/AR27 -> 0.32272105 | AW27: =TEXT(B27,"mmmm") -> October | AX27: =YEAR(B27) -> 2024
A28: ORD-2024-10027 | B28: 45619 | C28: 45619 | D28: CUST-4401 | E28: Diya Patel | F28: Corporate | G28: North | H28: Uttar Pradesh | I28: Noida | J28: Technology | K28: Phones | L28: Pro Phones 243 | M28: Standard Class | N28: 4 | O28: 716.13 | P28: 0.1 | Q28: 2578.07 | R28: 1527.55 | S28: 1050.52 | T28: Paid | U28: Returned | V28: =TEXTJOIN("|",TRUE,A28:U28) -> #NAME? | W28: =IFERROR(__xludf.DUMMYFUNCTION("IF(COUNTIF($A:$A,A22)=1, ""Unique"", IF(COUNTUNIQUE(FILTER($V$2:$V$934,$A$2:$A$934=A22))>1, ""Conflicting Duplicate"", ""Exact Duplicate""))"),"Unique") -> Unique | X28: =COUNTIF(V:V,V28)>1 -> TRUE | Y28: =IF(COUNTIF($A:$A,A28)>1,"Duplicate Order ID","Unique") -> Unique | AA28: =IF( OR(AQ28<0, AQ28>1, C28<B28), "Invalid", IF( OR(G28="Unknown", M28="Unknown"), "Warning", "Clean" ) ) -> Clean | AB28: =IF( OR( B28="", C28="", NOT(ISNUMBER(B28)), NOT(ISNUMBER(C28)), C28<B28 ), "Invalid", "Valid" ) -> Valid | AC28: 0 | AD28: =IF(C28<B28,"Invalid Shipping Date","Valid") -> Valid | AE28: =IF(AND(B28<>"",NOT(ISNUMBER(B28))),"Text Not Date","Valid") -> Valid | AF28: =IF(ISNUMBER(B28),"Valid","Invalid") -> Valid | AG28: =IF(ISNUMBER(C28),"Valid","Invalid") -> Valid | AH28: =IF(OR(B28="",ISBLANK(B28)),"Missing","Valid") -> Valid | AI28: =IF(OR(C28="",ISBLANK(C28)),"Missing","Valid") -> Valid | AJ28: FALSE | AK28: FALSE | AL28: FALSE | AM28: FALSE | AN28: FALSE | AO28: FALSE | AP28: FALSE | AQ28: =IF(OR(P28="",ISBLANK(P28)),0,P28) -> 0.1 | AR28: =N28*O28*(1-AQ28) -> 2578.068 | AS28: =Q28-AR28 -> 0.002 | AT28: =AR28-R28 -> 1050.518 | AU28: =S28-AT28 -> 0.002 | AV28: =AT28/AR28 -> 0.40748266 | AW28: =TEXT(B28,"mmmm") -> November | AX28: =YEAR(B28) -> 2024
A29: ORD-2025-10028 | B29: 45929 | C29: 45935 | D29: CUST-9875 | E29: Arjun Bose | F29: Small Business | G29: South | H29: Karnataka | I29: Bengaluru | J29: Office Supplies | K29: Paper | L29: Basic Paper 613 | M29: Second Class | N29: 5 | O29: 1806.51 | P29: 0.25 | Q29: 6774.41 | R29: 4710.36 | S29: 2064.05 | T29: Failed | U29: Returned | V29: =TEXTJOIN("|",TRUE,A29:U29) -> #NAME? | W29: =IFERROR(__xludf.DUMMYFUNCTION("IF(COUNTIF($A:$A,A23)=1, ""Unique"", IF(COUNTUNIQUE(FILTER($V$2:$V$934,$A$2:$A$934=A23))>1, ""Conflicting Duplicate"", ""Exact Duplicate""))"),"Unique") -> Unique | X29: =COUNTIF(V:V,V29)>1 -> TRUE | Y29: =IF(COUNTIF($A:$A,A29)>1,"Duplicate Order ID","Unique") -> Unique | AA29: =IF( OR(AQ29<0, AQ29>1, C29<B29), "Invalid", IF( OR(G29="Unknown", M29="Unknown"), "Warning", "Clean" ) ) -> Clean | AB29: =IF( OR( B29="", C29="", NOT(ISNUMBER(B29)), NOT(ISNUMBER(C29)), C29<B29 ), "Invalid", "Valid" ) -> Valid | AC29: 6 | AD29: =IF(C29<B29,"Invalid Shipping Date","Valid") -> Valid | AE29: =IF(AND(B29<>"",NOT(ISNUMBER(B29))),"Text Not Date","Valid") -> Valid | AF29: =IF(ISNUMBER(B29),"Valid","Invalid") -> Valid | AG29: =IF(ISNUMBER(C29),"Valid","Invalid") -> Valid | AH29: =IF(OR(B29="",ISBLANK(B29)),"Missing","Valid") -> Valid | AI29: =IF(OR(C29="",ISBLANK(C29)),"Missing","Valid") -> Valid | AJ29: FALSE | AK29: FALSE | AL29: FALSE | AM29: FALSE | AN29: FALSE | AO29: FALSE | AP29: FALSE | AQ29: =IF(OR(P29="",ISBLANK(P29)),0,P29) -> 0.25 | AR29: =N29*O29*(1-AQ29) -> 6774.4125 | AS29: =Q29-AR29 -> -0.0025 | AT29: =AR29-R29 -> 2064.0525 | AU29: =S29-AT29 -> -0.0025 | AV29: =AT29/AR29 -> 0.30468362 | AW29: =TEXT(B29,"mmmm") -> September | AX29: =YEAR(B29) -> 2025
A30: ORD-2024-10029 | B30: 45576 | C30: 45583 | D30: CUST-1569 | E30: Ananya Rao | F30: Home Office | G30: West | H30: Gujarat | I30: Ahmedabad | J30: Technology | K30: Phones | L30: Prime Phones 698 | M30: Second Class | N30: 2 | O30: 1942.22 | P30: 0.25 | Q30: 2913.33 | R30: 2122.33 | S30: 791 | T30: Refunded | U30: Cancelled | V30: =TEXTJOIN("|",TRUE,A30:U30) -> #NAME? | W30: =IFERROR(__xludf.DUMMYFUNCTION("IF(COUNTIF($A:$A,A24)=1, ""Unique"", IF(COUNTUNIQUE(FILTER($V$2:$V$934,$A$2:$A$934=A24))>1, ""Conflicting Duplicate"", ""Exact Duplicate""))"),"Unique") -> Unique | X30: =COUNTIF(V:V,V30)>1 -> TRUE | Y30: =IF(COUNTIF($A:$A,A30)>1,"Duplicate Order ID","Unique") -> Unique | AA30: =IF( OR(AQ30<0, AQ30>1, C30<B30), "Invalid", IF( OR(G30="Unknown", M30="Unknown"), "Warning", "Clean" ) ) -> Clean | AB30: =IF( OR( B30="", C30="", NOT(ISNUMBER(B30)), NOT(ISNUMBER(C30)), C30<B30 ), "Invalid", "Valid" ) -> Valid | AC30: 7 | AD30: =IF(C30<B30,"Invalid Shipping Date","Valid") -> Valid | AE30: =IF(AND(B30<>"",NOT(ISNUMBER(B30))),"Text Not Date","Valid") -> Valid | AF30: =IF(ISNUMBER(B30),"Valid","Invalid") -> Valid | AG30: =IF(ISNUMBER(C30),"Valid","Invalid") -> Valid | AH30: =IF(OR(B30="",ISBLANK(B30)),"Missing","Valid") -> Valid | AI30: =IF(OR(C30="",ISBLANK(C30)),"Missing","Valid") -> Valid | AJ30: FALSE | AK30: FALSE | AL30: FALSE | AM30: FALSE | AN30: FALSE | AO30: FALSE | AP30: FALSE | AQ30: =IF(OR(P30="",ISBLANK(P30)),0,P30) -> 0.25 | AR30: =N30*O30*(1-AQ30) -> 2913.33 | AS30: =Q30-AR30 -> 0 | AT30: =AR30-R30 -> 791 | AU30: =S30-AT30 -> 0 | AV30: =AT30/AR30 -> 0.27151061 | AW30: =TEXT(B30,"mmmm") -> October | AX30: =YEAR(B30) -> 2024
A31: ORD-2025-10030 | B31: 45882 | C31: 45882 | D31: CUST-5936 | E31: Rohan Mehta | F31: Home Office | G31: South | H31: Kerala | I31: Kochi | J31: Technology | K31: Phones | L31: Pro Phones 442 | M31: Standard Class | N31: 1 | O31: 256.01 | P31: 0.15 | Q31: 217.61 | R31: 119.77 | S31: 97.84 | T31: Paid | U31: Completed | V31: =TEXTJOIN("|",TRUE,A31:U31) -> #NAME? | W31: =IFERROR(__xludf.DUMMYFUNCTION("IF(COUNTIF($A:$A,A25)=1, ""Unique"", IF(COUNTUNIQUE(FILTER($V$2:$V$934,$A$2:$A$934=A25))>1, ""Conflicting Duplicate"", ""Exact Duplicate""))"),"Unique") -> Unique | X31: =COUNTIF(V:V,V31)>1 -> TRUE | Y31: =IF(COUNTIF($A:$A,A31)>1,"Duplicate Order ID","Unique") -> Unique | AA31: =IF( OR(AQ31<0, AQ31>1, C31<B31), "Invalid", IF( OR(G31="Unknown", M31="Unknown"), "Warning", "Clean" ) ) -> Clean | AB31: =IF( OR( B31="", C31="", NOT(ISNUMBER(B31)), NOT(ISNUMBER(C31)), C31<B31 ), "Invalid", "Valid" ) -> Valid | AC31: 0 | AD31: =IF(C31<B31,"Invalid Shipping Date","Valid") -> Valid | AE31: =IF(AND(B31<>"",NOT(ISNUMBER(B31))),"Text Not Date","Valid") -> Valid | AF31: =IF(ISNUMBER(B31),"Valid","Invalid") -> Valid | AG31: =IF(ISNUMBER(C31),"Valid","Invalid") -> Valid | AH31: =IF(OR(B31="",ISBLANK(B31)),"Missing","Valid") -> Valid | AI31: =IF(OR(C31="",ISBLANK(C31)),"Missing","Valid") -> Valid | AJ31: FALSE | AK31: FALSE | AL31: FALSE | AM31: FALSE | AN31: FALSE | AO31: FALSE | AP31: FALSE | AQ31: =IF(OR(P31="",ISBLANK(P31)),0,P31) -> 0.15 | AR31: =N31*O31*(1-AQ31) -> 217.6085 | AS31: =Q31-AR31 -> 0.0015 | AT31: =AR31-R31 -> 97.8385 | AU31: =S31-AT31 -> 0.0015 | AV31: =AT31/AR31 -> 0.4496079 | AW31: =TEXT(B31,"mmmm") -> August | AX31: =YEAR(B31) -> 2025
A32: ORD-2024-10031 | B32: 45331 | C32: 45334 | D32: CUST-8759 | E32: Ananya Rao | F32: Corporate | G32: West | H32: Goa | I32: Panaji | J32: Office Supplies | K32: Labels | L32: Pro Labels 355 | M32: First Class | N32: 1 | O32: 3421.77 | P32: 0.1 | Q32: 3079.59 | R32: 2001.89 | S32: 1077.7 | T32: Paid | U32: Completed | V32: =TEXTJOIN("|",TRUE,A32:U32) -> #NAME? | W32: =IFERROR(__xludf.DUMMYFUNCTION("IF(COUNTIF($A:$A,A26)=1, ""Unique"", IF(COUNTUNIQUE(FILTER($V$2:$V$934,$A$2:$A$934=A26))>1, ""Conflicting Duplicate"", ""Exact Duplicate""))"),"Unique") -> Unique | X32: =COUNTIF(V:V,V32)>1 -> TRUE | Y32: =IF(COUNTIF($A:$A,A32)>1,"Duplicate Order ID","Unique") -> Unique | AA32: =IF( OR(AQ32<0, AQ32>1, C32<B32), "Invalid", IF( OR(G32="Unknown", M32="Unknown"), "Warning", "Clean" ) ) -> Clean | AB32: =IF( OR( B32="", C32="", NOT(ISNUMBER(B32)), NOT(ISNUMBER(C32)), C32<B32 ), "Invalid", "Valid" ) -> Valid | AC32: 3 | AD32: =IF(C32<B32,"Invalid Shipping Date","Valid") -> Valid | AE32: =IF(AND(B32<>"",NOT(ISNUMBER(B32))),"Text Not Date","Valid") -> Valid | AF32: =IF(ISNUMBER(B32),"Valid","Invalid") -> Valid | AG32: =IF(ISNUMBER(C32),"Valid","Invalid") -> Valid | AH32: =IF(OR(B32="",ISBLANK(B32)),"Missing","Valid") -> Valid | AI32: =IF(OR(C32="",ISBLANK(C32)),"Missing","Valid") -> Valid | AJ32: FALSE | AK32: FALSE | AL32: FALSE | AM32: FALSE | AN32: FALSE | AO32: FALSE | AP32: FALSE | AQ32: =IF(OR(P32="",ISBLANK(P32)),0,P32) -> 0.1 | AR32: =N32*O32*(1-AQ32) -> 3079.593 | AS32: =Q32-AR32 -> -0.003 | AT32: =AR32-R32 -> 1077.703 | AU32: =S32-AT32 -> -0.003 | AV32: =AT32/AR32 -> 0.34994981 | AW32: =TEXT(B32,"mmmm") -> February | AX32: =YEAR(B32) -> 2024
A33: ORD-2025-10032 | B33: 45823 | C33: 45827 | D33: CUST-7867 | E33: Karan Malhotra | F33: Small Business | G33: West | H33: Madhya Pradesh | I33: Indore | J33: Office Supplies | K33: Paper | L33: Pro Paper 959 | M33: Second Class | N33: 9 | O33: 3092.55 | P33: 0 | Q33: 27832.95 | R33: 17769.75 | S33: 10063.2 | T33: Failed | U33: Returned | V33: =TEXTJOIN("|",TRUE,A33:U33) -> #NAME? | W33: =IFERROR(__xludf.DUMMYFUNCTION("IF(COUNTIF($A:$A,A27)=1, ""Unique"", IF(COUNTUNIQUE(FILTER($V$2:$V$934,$A$2:$A$934=A27))>1, ""Conflicting Duplicate"", ""Exact Duplicate""))"),"Unique") -> Unique | X33: =COUNTIF(V:V,V33)>1 -> TRUE | Y33: =IF(COUNTIF($A:$A,A33)>1,"Duplicate Order ID","Unique") -> Unique | AA33: =IF( OR(AQ33<0, AQ33>1, C33<B33), "Invalid", IF( OR(G33="Unknown", M33="Unknown"), "Warning", "Clean" ) ) -> Clean | AB33: =IF( OR( B33="", C33="", NOT(ISNUMBER(B33)), NOT(ISNUMBER(C33)), C33<B33 ), "Invalid", "Valid" ) -> Valid | AC33: 4 | AD33: =IF(C33<B33,"Invalid Shipping Date","Valid") -> Valid | AE33: =IF(AND(B33<>"",NOT(ISNUMBER(B33))),"Text Not Date","Valid") -> Valid | AF33: =IF(ISNUMBER(B33),"Valid","Invalid") -> Valid | AG33: =IF(ISNUMBER(C33),"Valid","Invalid") -> Valid | AH33: =IF(OR(B33="",ISBLANK(B33)),"Missing","Valid") -> Valid | AI33: =IF(OR(C33="",ISBLANK(C33)),"Missing","Valid") -> Valid | AJ33: FALSE | AK33: FALSE | AL33: FALSE | AM33: FALSE | AN33: FALSE | AO33: FALSE | AP33: FALSE | AQ33: =IF(OR(P33="",ISBLANK(P33)),0,P33) -> 0 | AR33: =N33*O33*(1-AQ33) -> 27832.95 | AS33: =Q33-AR33 -> 0 | AT33: =AR33-R33 -> 10063.2 | AU33: =S33-AT33 -> 0 | AV33: =AT33/AR33 -> 0.36155708 | AW33: =TEXT(B33,"mmmm") -> June | AX33: =YEAR(B33) -> 2025
A34: ORD-2024-10033 | B34: 45618 | C34: 45622 | D34: CUST-6509 | E34: Aarav Sharma | F34: Corporate | G34: South | H34: Andhra Pradesh | I34: Vijayawada | J34: Technology | K34: Phones | L34: Basic Phones 242 | M34: Second Class | N34: 3 | O34: 4001.25 | P34: 0 | Q34: 9002.81 | R34: 7529.92 | S34: 1472.89 | T34: Paid | U34: Completed | V34: =TEXTJOIN("|",TRUE,A34:U34) -> #NAME? | W34: =IFERROR(__xludf.DUMMYFUNCTION("IF(COUNTIF($A:$A,A28)=1, ""Unique"", IF(COUNTUNIQUE(FILTER($V$2:$V$934,$A$2:$A$934=A28))>1, ""Conflicting Duplicate"", ""Exact Duplicate""))"),"Unique") -> Unique | X34: =COUNTIF(V:V,V34)>1 -> TRUE | Y34: =IF(COUNTIF($A:$A,A34)>1,"Duplicate Order ID","Unique") -> Unique | AA34: =IF( OR(AQ34<0, AQ34>1, C34<B34), "Invalid", IF( OR(G34="Unknown", M34="Unknown"), "Warning", "Clean" ) ) -> Clean | AB34: =IF( OR( B34="", C34="", NOT(ISNUMBER(B34)), NOT(ISNUMBER(C34)), C34<B34 ), "Invalid", "Valid" ) -> Valid | AC34: 4 | AD34: =IF(C34<B34,"Invalid Shipping Date","Valid") -> Valid | AE34: =IF(AND(B34<>"",NOT(ISNUMBER(B34))),"Text Not Date","Valid") -> Valid | AF34: =IF(ISNUMBER(B34),"Valid","Invalid") -> Valid | AG34: =IF(ISNUMBER(C34),"Valid","Invalid") -> Valid | AH34: =IF(OR(B34="",ISBLANK(B34)),"Missing","Valid") -> Valid | AI34: =IF(OR(C34="",ISBLANK(C34)),"Missing","Valid") -> Valid | AJ34: FALSE | AK34: FALSE | AL34: TRUE | AM34: FALSE | AN34: FALSE | AO34: FALSE | AP34: TRUE | AQ34: =IF(OR(P34="",ISBLANK(P34)),0,P34) -> 0 | AR34: =N34*O34*(1-AQ34) -> 12003.75 | AS34: =Q34-AR34 -> -3000.94 | AT34: =AR34-R34 -> 4473.83 | AU34: =S34-AT34 -> -3000.94 | AV34: =AT34/AR34 -> 0.3727027 | AW34: =TEXT(B34,"mmmm") -> November | AX34: =YEAR(B34) -> 2024
A35: ORD-2024-10034 | B35: 45495 | C35: 45500 | D35: CUST-6660 | E35: Priya Menon | F35: Home Office | G35: West | H35: Goa | I35: Panaji | J35: Furniture | K35: Tables | L35: Max Tables 836 | M35: Same Day | N35: 7 | O35: 492.41 | P35: 0.25 | Q35: 2585.15 | R35: 2070.73 | S35: 514.42 | T35: Paid | U35: Completed | V35: =TEXTJOIN("|",TRUE,A35:U35) -> #NAME? | W35: =IFERROR(__xludf.DUMMYFUNCTION("IF(COUNTIF($A:$A,A29)=1, ""Unique"", IF(COUNTUNIQUE(FILTER($V$2:$V$934,$A$2:$A$934=A29))>1, ""Conflicting Duplicate"", ""Exact Duplicate""))"),"Unique") -> Unique | X35: =COUNTIF(V:V,V35)>1 -> TRUE | Y35: =IF(COUNTIF($A:$A,A35)>1,"Duplicate Order ID","Unique") -> Unique | AA35: =IF( OR(AQ35<0, AQ35>1, C35<B35), "Invalid", IF( OR(G35="Unknown", M35="Unknown"), "Warning", "Clean" ) ) -> Clean | AB35: =IF( OR( B35="", C35="", NOT(ISNUMBER(B35)), NOT(ISNUMBER(C35)), C35<B35 ), "Invalid", "Valid" ) -> Valid | AC35: 5 | AD35: =IF(C35<B35,"Invalid Shipping Date","Valid") -> Valid | AE35: =IF(AND(B35<>"",NOT(ISNUMBER(B35))),"Text Not Date","Valid") -> Valid | AF35: =IF(ISNUMBER(B35),"Valid","Invalid") -> Valid | AG35: =IF(ISNUMBER(C35),"Valid","Invalid") -> Valid | AH35: =IF(OR(B35="",ISBLANK(B35)),"Missing","Valid") -> Valid | AI35: =IF(OR(C35="",ISBLANK(C35)),"Missing","Valid") -> Valid | AJ35: FALSE | AK35: FALSE | AL35: FALSE | AM35: FALSE | AN35: FALSE | AO35: FALSE | AP35: FALSE | AQ35: =IF(OR(P35="",ISBLANK(P35)),0,P35) -> 0.25 | AR35: =N35*O35*(1-AQ35) -> 2585.1525 | AS35: =Q35-AR35 -> -0.0025 | AT35: =AR35-R35 -> 514.4225 | AU35: =S35-AT35 -> -0.0025 | AV35: =AT35/AR35 -> 0.19899116 | AW35: =TEXT(B35,"mmmm") -> July | AX35: =YEAR(B35) -> 2024
A36: ORD-2025-10035 | B36: 45688 | C36: 45693 | D36: CUST-2392 | E36: Priya Menon | F36: Home Office | G36: East | H36: West Bengal | I36: Kolkata | J36: Furniture | K36: Chairs | L36: Elite Chairs 862 | M36: Unknown | N36: 2 | O36: 4159.69 | P36: 0.2 | Q36: 6655.5 | R36: 4340.21 | S36: 2607.32 | T36: Paid | U36: Completed | V36: =TEXTJOIN("|",TRUE,A36:U36) -> #NAME? | W36: =IFERROR(__xludf.DUMMYFUNCTION("IF(COUNTIF($A:$A,A30)=1, ""Unique"", IF(COUNTUNIQUE(FILTER($V$2:$V$934,$A$2:$A$934=A30))>1, ""Conflicting Duplicate"", ""Exact Duplicate""))"),"Unique") -> Unique | X36: =COUNTIF(V:V,V36)>1 -> TRUE | Y36: =IF(COUNTIF($A:$A,A36)>1,"Duplicate Order ID","Unique") -> Unique | AA36: =IF( OR(AQ36<0, AQ36>1, C36<B36), "Invalid", IF( OR(G36="Unknown", M36="Unknown"), "Warning", "Clean" ) ) -> Warning | AB36: =IF( OR( B36="", C36="", NOT(ISNUMBER(B36)), NOT(ISNUMBER(C36)), C36<B36 ), "Invalid", "Valid" ) -> Valid | AC36: 5 | AD36: =IF(C36<B36,"Invalid Shipping Date","Valid") -> Valid | AE36: =IF(AND(B36<>"",NOT(ISNUMBER(B36))),"Text Not Date","Valid") -> Valid | AF36: =IF(ISNUMBER(B36),"Valid","Invalid") -> Valid | AG36: =IF(ISNUMBER(C36),"Valid","Invalid") -> Valid | AH36: =IF(OR(B36="",ISBLANK(B36)),"Missing","Valid") -> Valid | AI36: =IF(OR(C36="",ISBLANK(C36)),"Missing","Valid") -> Valid | AJ36: FALSE | AK36: TRUE | AL36: FALSE | AM36: FALSE | AN36: FALSE | AO36: FALSE | AP36: TRUE | AQ36: =IF(OR(P36="",ISBLANK(P36)),0,P36) -> 0.2 | AR36: =N36*O36*(1-AQ36) -> 6655.504 | AS36: =Q36-AR36 -> -0.004 | AT36: =AR36-R36 -> 2315.294 | AU36: =S36-AT36 -> 292.026 | AV36: =AT36/AR36 -> 0.34787658 | AW36: =TEXT(B36,"mmmm") -> January | AX36: =YEAR(B36) -> 2025
A37: ORD-2024-10036 | B37: 45441 | C37: 45441 | D37: CUST-1611 | E37: Sneha Kapoor | F37: Small Business | G37: West | H37: Gujarat | I37: Ahmedabad | J37: Furniture | K37: Bookcases | L37: Prime Bookcases 414 | M37: Second Class | N37: 8 | O37: 2507.12 | P37: 0.05 | Q37: 19054.11 | R37: 15313.83 | S37: 3740.28 | T37: Pending | U37: Returned | V37: =TEXTJOIN("|",TRUE,A37:U37) -> #NAME? | W37: =IFERROR(__xludf.DUMMYFUNCTION("IF(COUNTIF($A:$A,A31)=1, ""Unique"", IF(COUNTUNIQUE(FILTER($V$2:$V$934,$A$2:$A$934=A31))>1, ""Conflicting Duplicate"", ""Exact Duplicate""))"),"Unique") -> Unique | X37: =COUNTIF(V:V,V37)>1 -> TRUE | Y37: =IF(COUNTIF($A:$A,A37)>1,"Duplicate Order ID","Unique") -> Unique | AA37: =IF( OR(AQ37<0, AQ37>1, C37<B37), "Invalid", IF( OR(G37="Unknown", M37="Unknown"), "Warning", "Clean" ) ) -> Clean | AB37: =IF( OR( B37="", C37="", NOT(ISNUMBER(B37)), NOT(ISNUMBER(C37)), C37<B37 ), "Invalid", "Valid" ) -> Valid | AC37: 0 | AD37: =IF(C37<B37,"Invalid Shipping Date","Valid") -> Valid | AE37: =IF(AND(B37<>"",NOT(ISNUMBER(B37))),"Text Not Date","Valid") -> Valid | AF37: =IF(ISNUMBER(B37),"Valid","Invalid") -> Valid | AG37: =IF(ISNUMBER(C37),"Valid","Invalid") -> Valid | AH37: =IF(OR(B37="",ISBLANK(B37)),"Missing","Valid") -> Valid | AI37: =IF(OR(C37="",ISBLANK(C37)),"Missing","Valid") -> Valid | AJ37: FALSE | AK37: FALSE | AL37: FALSE | AM37: FALSE | AN37: FALSE | AO37: FALSE | AP37: FALSE | AQ37: =IF(OR(P37="",ISBLANK(P37)),0,P37) -> 0.05 | AR37: =N37*O37*(1-AQ37) -> 19054.112 | AS37: =Q37-AR37 -> -0.002 | AT37: =AR37-R37 -> 3740.282 | AU37: =S37-AT37 -> -0.002 | AV37: =AT37/AR37 -> 0.19629789 | AW37: =TEXT(B37,"mmmm") -> May | AX37: =YEAR(B37) -> 2024
A38: ORD-2024-10037 | B38: 45590 | C38: 45593 | D38: CUST-8296 | E38: Rohan Mehta | F38: Corporate | G38: West | H38: Maharashtra | I38: Mumbai | J38: Furniture | K38: Bookcases | L38: Eco Bookcases 220 | M38: Second Class | N38: 3 | O38: 3126.47 | P38: 0 | Q38: 9379.41 | R38: 6670.85 | S38: 2708.56 | T38: Paid | U38: Returned | V38: =TEXTJOIN("|",TRUE,A38:U38) -> #NAME? | W38: =IFERROR(__xludf.DUMMYFUNCTION("IF(COUNTIF($A:$A,A32)=1, ""Unique"", IF(COUNTUNIQUE(FILTER($V$2:$V$934,$A$2:$A$934=A32))>1, ""Conflicting Duplicate"", ""Exact Duplicate""))"),"Unique") -> Unique | X38: =COUNTIF(V:V,V38)>1 -> TRUE | Y38: =IF(COUNTIF($A:$A,A38)>1,"Duplicate Order ID","Unique") -> Unique | AA38: =IF( OR(AQ38<0, AQ38>1, C38<B38), "Invalid", IF( OR(G38="Unknown", M38="Unknown"), "Warning", "Clean" ) ) -> Clean | AB38: =IF( OR( B38="", C38="", NOT(ISNUMBER(B38)), NOT(ISNUMBER(C38)), C38<B38 ), "Invalid", "Valid" ) -> Valid | AC38: 3 | AD38: =IF(C38<B38,"Invalid Shipping Date","Valid") -> Valid | AE38: =IF(AND(B38<>"",NOT(ISNUMBER(B38))),"Text Not Date","Valid") -> Valid | AF38: =IF(ISNUMBER(B38),"Valid","Invalid") -> Valid | AG38: =IF(ISNUMBER(C38),"Valid","Invalid") -> Valid | AH38: =IF(OR(B38="",ISBLANK(B38)),"Missing","Valid") -> Valid | AI38: =IF(OR(C38="",ISBLANK(C38)),"Missing","Valid") -> Valid | AJ38: FALSE | AK38: FALSE | AL38: FALSE | AM38: FALSE | AN38: FALSE | AO38: FALSE | AP38: FALSE | AQ38: =IF(OR(P38="",ISBLANK(P38)),0,P38) -> 0 | AR38: =N38*O38*(1-AQ38) -> 9379.41 | AS38: =Q38-AR38 -> 0 | AT38: =AR38-R38 -> 2708.56 | AU38: =S38-AT38 -> 0 | AV38: =AT38/AR38 -> 0.28877723 | AW38: =TEXT(B38,"mmmm") -> October | AX38: =YEAR(B38) -> 2024
A39: ORD-2025-10038 | B39: 45867 | C39: 45867 | D39: CUST-4646 | E39: Diya Patel | F39: Consumer | G39: West | H39: Maharashtra | I39: Mumbai | J39: Technology | K39: Copiers | L39: Pro Copiers 830 | M39: Standard Class | N39: 4 | O39: 1327.54 | P39: 0.2 | Q39: 4248.13 | R39: 3321.09 | S39: 927.04 | T39: Paid | U39: Completed | V39: =TEXTJOIN("|",TRUE,A39:U39) -> #NAME? | W39: =IFERROR(__xludf.DUMMYFUNCTION("IF(COUNTIF($A:$A,A33)=1, ""Unique"", IF(COUNTUNIQUE(FILTER($V$2:$V$934,$A$2:$A$934=A33))>1, ""Conflicting Duplicate"", ""Exact Duplicate""))"),"Unique") -> Unique | X39: =COUNTIF(V:V,V39)>1 -> TRUE | Y39: =IF(COUNTIF($A:$A,A39)>1,"Duplicate Order ID","Unique") -> Unique | AA39: =IF( OR(AQ39<0, AQ39>1, C39<B39), "Invalid", IF( OR(G39="Unknown", M39="Unknown"), "Warning", "Clean" ) ) -> Clean | AB39: =IF( OR( B39="", C39="", NOT(ISNUMBER(B39)), NOT(ISNUMBER(C39)), C39<B39 ), "Invalid", "Valid" ) -> Valid | AC39: 0 | AD39: =IF(C39<B39,"Invalid Shipping Date","Valid") -> Valid | AE39: =IF(AND(B39<>"",NOT(ISNUMBER(B39))),"Text Not Date","Valid") -> Valid | AF39: =IF(ISNUMBER(B39),"Valid","Invalid") -> Valid | AG39: =IF(ISNUMBER(C39),"Valid","Invalid") -> Valid | AH39: =IF(OR(B39="",ISBLANK(B39)),"Missing","Valid") -> Valid | AI39: =IF(OR(C39="",ISBLANK(C39)),"Missing","Valid") -> Valid | AJ39: FALSE | AK39: FALSE | AL39: FALSE | AM39: FALSE | AN39: FALSE | AO39: FALSE | AP39: FALSE | AQ39: =IF(OR(P39="",ISBLANK(P39)),0,P39) -> 0.2 | AR39: =N39*O39*(1-AQ39) -> 4248.128 | AS39: =Q39-AR39 -> 0.002 | AT39: =AR39-R39 -> 927.038 | AU39: =S39-AT39 -> 0.002 | AV39: =AT39/AR39 -> 0.21822271 | AW39: =TEXT(B39,"mmmm") -> July | AX39: =YEAR(B39) -> 2025
A40: ORD-2024-10039 | B40: 45460 | C40: 45465 | D40: CUST-8235 | E40: Aarav Sharma | F40: Corporate | G40: West | H40: Gujarat | I40: Ahmedabad | J40: Technology | K40: Phones | L40: Prime Phones 507 | M40: First Class | N40: 7 | O40: 2210.68 | P40: 0.1 | Q40: 13927.28 | R40: 10504.87 | S40: 3422.41 | T40: Paid | U40: Completed | V40: =TEXTJOIN("|",TRUE,A40:U40) -> #NAME? | W40: =IFERROR(__xludf.DUMMYFUNCTION("IF(COUNTIF($A:$A,A34)=1, ""Unique"", IF(COUNTUNIQUE(FILTER($V$2:$V$934,$A$2:$A$934=A34))>1, ""Conflicting Duplicate"", ""Exact Duplicate""))"),"Unique") -> Unique | X40: =COUNTIF(V:V,V40)>1 -> TRUE | Y40: =IF(COUNTIF($A:$A,A40)>1,"Duplicate Order ID","Unique") -> Unique | AA40: =IF( OR(AQ40<0, AQ40>1, C40<B40), "Invalid", IF( OR(G40="Unknown", M40="Unknown"), "Warning", "Clean" ) ) -> Clean | AB40: =IF( OR( B40="", C40="", NOT(ISNUMBER(B40)), NOT(ISNUMBER(C40)), C40<B40 ), "Invalid", "Valid" ) -> Valid | AC40: 5 | AD40: =IF(C40<B40,"Invalid Shipping Date","Valid") -> Valid | AE40: =IF(AND(B40<>"",NOT(ISNUMBER(B40))),"Text Not Date","Valid") -> Valid | AF40: =IF(ISNUMBER(B40),"Valid","Invalid") -> Valid | AG40: =IF(ISNUMBER(C40),"Valid","Invalid") -> Valid | AH40: =IF(OR(B40="",ISBLANK(B40)),"Missing","Valid") -> Valid | AI40: =IF(OR(C40="",ISBLANK(C40)),"Missing","Valid") -> Valid | AJ40: FALSE | AK40: FALSE | AL40: FALSE | AM40: FALSE | AN40: FALSE | AO40: FALSE | AP40: FALSE | AQ40: =IF(OR(P40="",ISBLANK(P40)),0,P40) -> 0.1 | AR40: =N40*O40*(1-AQ40) -> 13927.284 | AS40: =Q40-AR40 -> -0.004 | AT40: =AR40-R40 -> 3422.414 | AU40: =S40-AT40 -> -0.004 | AV40: =AT40/AR40 -> 0.24573449 | AW40: =TEXT(B40,"mmmm") -> June | AX40: =YEAR(B40) -> 2024
A41: ORD-2024-10040 | B41: 45637 | C41: 45637 | D41: CUST-5830 | E41: Mira Das | F41: Small Business | G41: West | H41: Madhya Pradesh | I41: Indore | J41: Technology | K41: Copiers | L41: Classic Copiers 590 | M41: First Class | N41: 4 | O41: 1370.92 | P41: 0.1 | Q41: 4935.31 | R41: 3374.77 | S41: 1560.54 | T41: Pending | U41: Returned | V41: =TEXTJOIN("|",TRUE,A41:U41) -> #NAME? | W41: =IFERROR(__xludf.DUMMYFUNCTION("IF(COUNTIF($A:$A,A35)=1, ""Unique"", IF(COUNTUNIQUE(FILTER($V$2:$V$934,$A$2:$A$934=A35))>1, ""Conflicting Duplicate"", ""Exact Duplicate""))"),"Unique") -> Unique | X41: =COUNTIF(V:V,V41)>1 -> TRUE | Y41: =IF(COUNTIF($A:$A,A41)>1,"Duplicate Order ID","Unique") -> Unique | AA41: =IF( OR(AQ41<0, AQ41>1, C41<B41), "Invalid", IF( OR(G41="Unknown", M41="Unknown"), "Warning", "Clean" ) ) -> Clean | AB41: =IF( OR( B41="", C41="", NOT(ISNUMBER(B41)), NOT(ISNUMBER(C41)), C41<B41 ), "Invalid", "Valid" ) -> Valid | AC41: 0 | AD41: =IF(C41<B41,"Invalid Shipping Date","Valid") -> Valid | AE41: =IF(AND(B41<>"",NOT(ISNUMBER(B41))),"Text Not Date","Valid") -> Valid | AF41: =IF(ISNUMBER(B41),"Valid","Invalid") -> Valid | AG41: =IF(ISNUMBER(C41),"Valid","Invalid") -> Valid | AH41: =IF(OR(B41="",ISBLANK(B41)),"Missing","Valid") -> Valid | AI41: =IF(OR(C41="",ISBLANK(C41)),"Missing","Valid") -> Valid | AJ41: FALSE | AK41: FALSE | AL41: FALSE | AM41: FALSE | AN41: FALSE | AO41: FALSE | AP41: FALSE | AQ41: =IF(OR(P41="",ISBLANK(P41)),0,P41) -> 0.1 | AR41: =N41*O41*(1-AQ41) -> 4935.312 | AS41: =Q41-AR41 -> -0.002 | AT41: =AR41-R41 -> 1560.542 | AU41: =S41-AT41 -> -0.002 | AV41: =AT41/AR41 -> 0.31619926 | AW41: =TEXT(B41,"mmmm") -> December | AX41: =YEAR(B41) -> 2024
A42: ORD-2024-10041 | B42: 45575 | C42: 45581 | D42: CUST-7178 | E42: Isha Nair | F42: Home Office | G42: West | H42: Rajasthan | I42: Udaipur | J42: Technology | K42: Copiers | L42: Eco Copiers 865 | M42: Standard Class | N42: 7 | O42: 2509.27 | P42: 0.2 | Q42: 14051.91 | R42: 11990.37 | S42: 2061.54 | T42: Paid | U42: Completed | V42: =TEXTJOIN("|",TRUE,A42:U42) -> #NAME? | W42: =IFERROR(__xludf.DUMMYFUNCTION("IF(COUNTIF($A:$A,A36)=1, ""Unique"", IF(COUNTUNIQUE(FILTER($V$2:$V$934,$A$2:$A$934=A36))>1, ""Conflicting Duplicate"", ""Exact Duplicate""))"),"Unique") -> Unique | X42: =COUNTIF(V:V,V42)>1 -> TRUE | Y42: =IF(COUNTIF($A:$A,A42)>1,"Duplicate Order ID","Unique") -> Unique | AA42: =IF( OR(AQ42<0, AQ42>1, C42<B42), "Invalid", IF( OR(G42="Unknown", M42="Unknown"), "Warning", "Clean" ) ) -> Clean | AB42: =IF( OR( B42="", C42="", NOT(ISNUMBER(B42)), NOT(ISNUMBER(C42)), C42<B42 ), "Invalid", "Valid" ) -> Valid | AC42: 6 | AD42: =IF(C42<B42,"Invalid Shipping Date","Valid") -> Valid | AE42: =IF(AND(B42<>"",NOT(ISNUMBER(B42))),"Text Not Date","Valid") -> Valid | AF42: =IF(ISNUMBER(B42),"Valid","Invalid") -> Valid | AG42: =IF(ISNUMBER(C42),"Valid","Invalid") -> Valid | AH42: =IF(OR(B42="",ISBLANK(B42)),"Missing","Valid") -> Valid | AI42: =IF(OR(C42="",ISBLANK(C42)),"Missing","Valid") -> Valid | AJ42: FALSE | AK42: FALSE | AL42: FALSE | AM42: FALSE | AN42: FALSE | AO42: FALSE | AP42: FALSE | AQ42: =IF(OR(P42="",ISBLANK(P42)),0,P42) -> 0.2 | AR42: =N42*O42*(1-AQ42) -> 14051.912 | AS42: =Q42-AR42 -> -0.002 | AT42: =AR42-R42 -> 2061.542 | AU42: =S42-AT42 -> -0.002 | AV42: =AT42/AR42 -> 0.146709 | AW42: =TEXT(B42,"mmmm") -> October | AX42: =YEAR(B42) -> 2024
A43: ORD-2024-10042 | B43: 45363 | C43: 45368 | D43: CUST-3829 | E43: Aarav Sharma | F43: Small Business | G43: East | H43: Odisha | I43: Bhubaneswar | J43: Furniture | K43: Bookcases | L43: Classic Bookcases 835 | M43: Same Day | N43: 8 | O43: 855.81 | P43: 0 | Q43: 6846.48 | R43: 4239.89 | S43: 2606.59 | T43: Pending | U43: Cancelled | V43: =TEXTJOIN("|",TRUE,A43:U43) -> #NAME? | W43: =IFERROR(__xludf.DUMMYFUNCTION("IF(COUNTIF($A:$A,A37)=1, ""Unique"", IF(COUNTUNIQUE(FILTER($V$2:$V$934,$A$2:$A$934=A37))>1, ""Conflicting Duplicate"", ""Exact Duplicate""))"),"Unique") -> Unique | X43: =COUNTIF(V:V,V43)>1 -> TRUE | Y43: =IF(COUNTIF($A:$A,A43)>1,"Duplicate Order ID","Unique") -> Unique | AA43: =IF( OR(AQ43<0, AQ43>1, C43<B43), "Invalid", IF( OR(G43="Unknown", M43="Unknown"), "Warning", "Clean" ) ) -> Clean | AB43: =IF( OR( B43="", C43="", NOT(ISNUMBER(B43)), NOT(ISNUMBER(C43)), C43<B43 ), "Invalid", "Valid" ) -> Valid | AC43: 5 | AD43: =IF(C43<B43,"Invalid Shipping Date","Valid") -> Valid | AE43: =IF(AND(B43<>"",NOT(ISNUMBER(B43))),"Text Not Date","Valid") -> Valid | AF43: =IF(ISNUMBER(B43),"Valid","Invalid") -> Valid | AG43: =IF(ISNUMBER(C43),"Valid","Invalid") -> Valid | AH43: =IF(OR(B43="",ISBLANK(B43)),"Missing","Valid") -> Valid | AI43: =IF(OR(C43="",ISBLANK(C43)),"Missing","Valid") -> Valid | AJ43: FALSE | AK43: FALSE | AL43: FALSE | AM43: FALSE | AN43: FALSE | AO43: FALSE | AP43: FALSE | AQ43: =IF(OR(P43="",ISBLANK(P43)),0,P43) -> 0 | AR43: =N43*O43*(1-AQ43) -> 6846.48 | AS43: =Q43-AR43 -> 0 | AT43: =AR43-R43 -> 2606.59 | AU43: =S43-AT43 -> 0 | AV43: =AT43/AR43 -> 0.38071973 | AW43: =TEXT(B43,"mmmm") -> March | AX43: =YEAR(B43) -> 2024
A44: ORD-2025-10043 | B44: 45940 | C44: 45945 | D44: CUST-6708 | E44: Arjun Bose | F44: Corporate | G44: East | H44: Jharkhand | I44: Ranchi | J44: Technology | K44: Phones | L44: Eco Phones 702 | M44: Standard Class | N44: 8 | O44: 979.87 | P44: 0.05 | Q44: 7447.01 | R44: 4496.22 | S44: 2950.79 | T44: Paid | U44: Completed | V44: =TEXTJOIN("|",TRUE,A44:U44) -> #NAME? | W44: =IFERROR(__xludf.DUMMYFUNCTION("IF(COUNTIF($A:$A,A38)=1, ""Unique"", IF(COUNTUNIQUE(FILTER($V$2:$V$934,$A$2:$A$934=A38))>1, ""Conflicting Duplicate"", ""Exact Duplicate""))"),"Unique") -> Unique | X44: =COUNTIF(V:V,V44)>1 -> TRUE | Y44: =IF(COUNTIF($A:$A,A44)>1,"Duplicate Order ID","Unique") -> Unique | AA44: =IF( OR(AQ44<0, AQ44>1, C44<B44), "Invalid", IF( OR(G44="Unknown", M44="Unknown"), "Warning", "Clean" ) ) -> Clean | AB44: =IF( OR( B44="", C44="", NOT(ISNUMBER(B44)), NOT(ISNUMBER(C44)), C44<B44 ), "Invalid", "Valid" ) -> Valid | AC44: 5 | AD44: =IF(C44<B44,"Invalid Shipping Date","Valid") -> Valid | AE44: =IF(AND(B44<>"",NOT(ISNUMBER(B44))),"Text Not Date","Valid") -> Valid | AF44: =IF(ISNUMBER(B44),"Valid","Invalid") -> Valid | AG44: =IF(ISNUMBER(C44),"Valid","Invalid") -> Valid | AH44: =IF(OR(B44="",ISBLANK(B44)),"Missing","Valid") -> Valid | AI44: =IF(OR(C44="",ISBLANK(C44)),"Missing","Valid") -> Valid | AJ44: FALSE | AK44: FALSE | AL44: FALSE | AM44: FALSE | AN44: FALSE | AO44: FALSE | AP44: FALSE | AQ44: =IF(OR(P44="",ISBLANK(P44)),0,P44) -> 0.05 | AR44: =N44*O44*(1-AQ44) -> 7447.012 | AS44: =Q44-AR44 -> -0.002 | AT44: =AR44-R44 -> 2950.792 | AU44: =S44-AT44 -> -0.002 | AV44: =AT44/AR44 -> 0.39623838 | AW44: =TEXT(B44,"mmmm") -> October | AX44: =YEAR(B44) -> 2025
A45: ORD-2024-10044 | B45: 45481 | C45: 45487 | D45: CUST-7119 | E45: Priya Menon | F45: Small Business | G45: East | H45: Odisha | I45: Bhubaneswar | J45: Furniture | K45: Furnishings | L45: Smart Furnishings 956 | M45: Same Day | N45: 3 | O45: 1010.23 | P45: 0 | Q45: 3030.69 | R45: 1721.08 | S45: 1309.61 | T45: Paid | U45: Completed | V45: =TEXTJOIN("|",TRUE,A45:U45) -> #NAME? | W45: =IFERROR(__xludf.DUMMYFUNCTION("IF(COUNTIF($A:$A,A39)=1, ""Unique"", IF(COUNTUNIQUE(FILTER($V$2:$V$934,$A$2:$A$934=A39))>1, ""Conflicting Duplicate"", ""Exact Duplicate""))"),"Unique") -> Unique | X45: =COUNTIF(V:V,V45)>1 -> TRUE | Y45: =IF(COUNTIF($A:$A,A45)>1,"Duplicate Order ID","Unique") -> Unique | AA45: =IF( OR(AQ45<0, AQ45>1, C45<B45), "Invalid", IF( OR(G45="Unknown", M45="Unknown"), "Warning", "Clean" ) ) -> Clean | AB45: =IF( OR( B45="", C45="", NOT(ISNUMBER(B45)), NOT(ISNUMBER(C45)), C45<B45 ), "Invalid", "Valid" ) -> Valid | AC45: 6 | AD45: =IF(C45<B45,"Invalid Shipping Date","Valid") -> Valid | AE45: =IF(AND(B45<>"",NOT(ISNUMBER(B45))),"Text Not Date","Valid") -> Valid | AF45: =IF(ISNUMBER(B45),"Valid","Invalid") -> Valid | AG45: =IF(ISNUMBER(C45),"Valid","Invalid") -> Valid | AH45: =IF(OR(B45="",ISBLANK(B45)),"Missing","Valid") -> Valid | AI45: =IF(OR(C45="",ISBLANK(C45)),"Missing","Valid") -> Valid | AJ45: FALSE | AK45: FALSE | AL45: FALSE | AM45: FALSE | AN45: FALSE | AO45: FALSE | AP45: FALSE | AQ45: =IF(OR(P45="",ISBLANK(P45)),0,P45) -> 0 | AR45: =N45*O45*(1-AQ45) -> 3030.69 | AS45: =Q45-AR45 -> 0 | AT45: =AR45-R45 -> 1309.61 | AU45: =S45-AT45 -> 0 | AV45: =AT45/AR45 -> 0.43211612 | AW45: =TEXT(B45,"mmmm") -> July | AX45: =YEAR(B45) -> 2024
A46: ORD-2024-10045 | B46: 45465 | C46: 45468 | D46: CUST-3373 | E46: Rohan Mehta | F46: Small Business | G46: North | H46: Haryana | I46: Gurugram | J46: Furniture | K46: Chairs | L46: Max Chairs 393 | M46: Standard Class | N46: 9 | O46: 3329.77 | P46: 0.1 | Q46: 26971.14 | R46: 17376.2 | S46: 9594.94 | T46: Paid | U46: Completed | V46: =TEXTJOIN("|",TRUE,A46:U46) -> #NAME? | W46: =IFERROR(__xludf.DUMMYFUNCTION("IF(COUNTIF($A:$A,A40)=1, ""Unique"", IF(COUNTUNIQUE(FILTER($V$2:$V$934,$A$2:$A$934=A40))>1, ""Conflicting Duplicate"", ""Exact Duplicate""))"),"Unique") -> Unique | X46: =COUNTIF(V:V,V46)>1 -> TRUE | Y46: =IF(COUNTIF($A:$A,A46)>1,"Duplicate Order ID","Unique") -> Unique | AA46: =IF( OR(AQ46<0, AQ46>1, C46<B46), "Invalid", IF( OR(G46="Unknown", M46="Unknown"), "Warning", "Clean" ) ) -> Clean | AB46: =IF( OR( B46="", C46="", NOT(ISNUMBER(B46)), NOT(ISNUMBER(C46)), C46<B46 ), "Invalid", "Valid" ) -> Valid | AC46: 3 | AD46: =IF(C46<B46,"Invalid Shipping Date","Valid") -> Valid | AE46: =IF(AND(B46<>"",NOT(ISNUMBER(B46))),"Text Not Date","Valid") -> Valid | AF46: =IF(ISNUMBER(B46),"Valid","Invalid") -> Valid | AG46: =IF(ISNUMBER(C46),"Valid","Invalid") -> Valid | AH46: =IF(OR(B46="",ISBLANK(B46)),"Missing","Valid") -> Valid | AI46: =IF(OR(C46="",ISBLANK(C46)),"Missing","Valid") -> Valid | AJ46: FALSE | AK46: FALSE | AL46: FALSE | AM46: FALSE | AN46: FALSE | AO46: FALSE | AP46: FALSE | AQ46: =IF(OR(P46="",ISBLANK(P46)),0,P46) -> 0.1 | AR46: =N46*O46*(1-AQ46) -> 26971.137 | AS46: =Q46-AR46 -> 0.003 | AT46: =AR46-R46 -> 9594.937 | AU46: =S46-AT46 -> 0.003 | AV46: =AT46/AR46 -> 0.35574833 | AW46: =TEXT(B46,"mmmm") -> June | AX46: =YEAR(B46) -> 2024
A47: ORD-2024-10046 | B47: 45309 | C47: 45315 | D47: CUST-8896 | E47: Isha Nair | F47: Home Office | G47: East | H47: Bihar | I47: Patna | J47: Office Supplies | K47: Art | L47: Prime Art 221 | M47: Second Class | N47: 8 | O47: 3927.82 | P47: 0.05 | Q47: 29851.43 | R47: 17487.48 | S47: 12363.95 | T47: Pending | U47: Returned | V47: =TEXTJOIN("|",TRUE,A47:U47) -> #NAME? | W47: =IFERROR(__xludf.DUMMYFUNCTION("IF(COUNTIF($A:$A,A41)=1, ""Unique"", IF(COUNTUNIQUE(FILTER($V$2:$V$934,$A$2:$A$934=A41))>1, ""Conflicting Duplicate"", ""Exact Duplicate""))"),"Unique") -> Unique | X47: =COUNTIF(V:V,V47)>1 -> TRUE | Y47: =IF(COUNTIF($A:$A,A47)>1,"Duplicate Order ID","Unique") -> Unique | AA47: =IF( OR(AQ47<0, AQ47>1, C47<B47), "Invalid", IF( OR(G47="Unknown", M47="Unknown"), "Warning", "Clean" ) ) -> Clean | AB47: =IF( OR( B47="", C47="", NOT(ISNUMBER(B47)), NOT(ISNUMBER(C47)), C47<B47 ), "Invalid", "Valid" ) -> Valid | AC47: 6 | AD47: =IF(C47<B47,"Invalid Shipping Date","Valid") -> Valid | AE47: =IF(AND(B47<>"",NOT(ISNUMBER(B47))),"Text Not Date","Valid") -> Valid | AF47: =IF(ISNUMBER(B47),"Valid","Invalid") -> Valid | AG47: =IF(ISNUMBER(C47),"Valid","Invalid") -> Valid | AH47: =IF(OR(B47="",ISBLANK(B47)),"Missing","Valid") -> Valid | AI47: =IF(OR(C47="",ISBLANK(C47)),"Missing","Valid") -> Valid | AJ47: FALSE | AK47: FALSE | AL47: FALSE | AM47: FALSE | AN47: FALSE | AO47: FALSE | AP47: FALSE | AQ47: =IF(OR(P47="",ISBLANK(P47)),0,P47) -> 0.05 | AR47: =N47*O47*(1-AQ47) -> 29851.432 | AS47: =Q47-AR47 -> -0.002 | AT47: =AR47-R47 -> 12363.952 | AU47: =S47-AT47 -> -0.002 | AV47: =AT47/AR47 -> 0.41418288 | AW47: =TEXT(B47,"mmmm") -> January | AX47: =YEAR(B47) -> 2024
A48: ORD-2024-10047 | B48: 45492 | C48: 45492 | D48: CUST-8517 | E48: Ananya Rao | F48: Small Business | G48: South | H48: Kerala | I48: Kochi | J48: Furniture | K48: Bookcases | L48: Elite Bookcases 671 | M48: Standard Class | N48: 9 | O48: 2386.79 | P48: 0.25 | Q48: 16110.83 | R48: 10680.03 | S48: 5430.8 | T48: Refunded | U48: Returned | V48: =TEXTJOIN("|",TRUE,A48:U48) -> #NAME? | W48: =IFERROR(__xludf.DUMMYFUNCTION("IF(COUNTIF($A:$A,A42)=1, ""Unique"", IF(COUNTUNIQUE(FILTER($V$2:$V$934,$A$2:$A$934=A42))>1, ""Conflicting Duplicate"", ""Exact Duplicate""))"),"Unique") -> Unique | X48: =COUNTIF(V:V,V48)>1 -> TRUE | Y48: =IF(COUNTIF($A:$A,A48)>1,"Duplicate Order ID","Unique") -> Unique | AA48: =IF( OR(AQ48<0, AQ48>1, C48<B48), "Invalid", IF( OR(G48="Unknown", M48="Unknown"), "Warning", "Clean" ) ) -> Clean | AB48: =IF( OR( B48="", C48="", NOT(ISNUMBER(B48)), NOT(ISNUMBER(C48)), C48<B48 ), "Invalid", "Valid" ) -> Valid | AC48: 0 | AD48: =IF(C48<B48,"Invalid Shipping Date","Valid") -> Valid | AE48: =IF(AND(B48<>"",NOT(ISNUMBER(B48))),"Text Not Date","Valid") -> Valid | AF48: =IF(ISNUMBER(B48),"Valid","Invalid") -> Valid | AG48: =IF(ISNUMBER(C48),"Valid","Invalid") -> Valid | AH48: =IF(OR(B48="",ISBLANK(B48)),"Missing","Valid") -> Valid | AI48: =IF(OR(C48="",ISBLANK(C48)),"Missing","Valid") -> Valid | AJ48: FALSE | AK48: FALSE | AL48: FALSE | AM48: FALSE | AN48: FALSE | AO48: FALSE | AP48: FALSE | AQ48: =IF(OR(P48="",ISBLANK(P48)),0,P48) -> 0.25 | AR48: =N48*O48*(1-AQ48) -> 16110.833 | AS48: =Q48-AR48 -> -0.0025 | AT48: =AR48-R48 -> 5430.8025 | AU48: =S48-AT48 -> -0.0025 | AV48: =AT48/AR48 -> 0.33709012 | AW48: =TEXT(B48,"mmmm") -> July | AX48: =YEAR(B48) -> 2024
A49: ORD-2024-10048 | B49: 45516 | C49: 45516 | D49: CUST-1987 | E49: Rahul Verma | F49: Corporate | G49: South | H49: Tamil Nadu | I49: Chennai | J49: Office Supplies | K49: Storage | L49: Max Storage 432 | M49: Standard Class | N49: 8 | O49: 2445.31 | P49: 0.1 | Q49: 17606.23 | R49: 12438.96 | S49: 5167.27 | T49: Paid | U49: Completed | V49: =TEXTJOIN("|",TRUE,A49:U49) -> #NAME? | W49: =IFERROR(__xludf.DUMMYFUNCTION("IF(COUNTIF($A:$A,A43)=1, ""Unique"", IF(COUNTUNIQUE(FILTER($V$2:$V$934,$A$2:$A$934=A43))>1, ""Conflicting Duplicate"", ""Exact Duplicate""))"),"Unique") -> Unique | X49: =COUNTIF(V:V,V49)>1 -> TRUE | Y49: =IF(COUNTIF($A:$A,A49)>1,"Duplicate Order ID","Unique") -> Unique | AA49: =IF( OR(AQ49<0, AQ49>1, C49<B49), "Invalid", IF( OR(G49="Unknown", M49="Unknown"), "Warning", "Clean" ) ) -> Clean | AB49: =IF( OR( B49="", C49="", NOT(ISNUMBER(B49)), NOT(ISNUMBER(C49)), C49<B49 ), "Invalid", "Valid" ) -> Valid | AC49: 0 | AD49: =IF(C49<B49,"Invalid Shipping Date","Valid") -> Valid | AE49: =IF(AND(B49<>"",NOT(ISNUMBER(B49))),"Text Not Date","Valid") -> Valid | AF49: =IF(ISNUMBER(B49),"Valid","Invalid") -> Valid | AG49: =IF(ISNUMBER(C49),"Valid","Invalid") -> Valid | AH49: =IF(OR(B49="",ISBLANK(B49)),"Missing","Valid") -> Valid | AI49: =IF(OR(C49="",ISBLANK(C49)),"Missing","Valid") -> Valid | AJ49: FALSE | AK49: FALSE | AL49: FALSE | AM49: FALSE | AN49: FALSE | AO49: FALSE | AP49: FALSE | AQ49: =IF(OR(P49="",ISBLANK(P49)),0,P49) -> 0.1 | AR49: =N49*O49*(1-AQ49) -> 17606.232 | AS49: =Q49-AR49 -> -0.002 | AT49: =AR49-R49 -> 5167.272 | AU49: =S49-AT49 -> -0.002 | AV49: =AT49/AR49 -> 0.29349108 | AW49: =TEXT(B49,"mmmm") -> August | AX49: =YEAR(B49) -> 2024
A50: ORD-2025-10049 | B50: 45687 | C50: 45693 | D50: CUST-8183 | E50: Neha Gupta | F50: Corporate | G50: West | H50: Maharashtra | I50: Mumbai | J50: Furniture | K50: Chairs | L50: Basic Chairs 837 | M50: Second Class | N50: 7 | O50: 4063.66 | P50: 0 | Q50: 28445.62 | R50: 20938.59 | S50: 7507.03 | T50: Paid | U50: Completed | V50: =TEXTJOIN("|",TRUE,A50:U50) -> #NAME? | W50: =IFERROR(__xludf.DUMMYFUNCTION("IF(COUNTIF($A:$A,A44)=1, ""Unique"", IF(COUNTUNIQUE(FILTER($V$2:$V$934,$A$2:$A$934=A44))>1, ""Conflicting Duplicate"", ""Exact Duplicate""))"),"Unique") -> Unique | X50: =COUNTIF(V:V,V50)>1 -> TRUE | Y50: =IF(COUNTIF($A:$A,A50)>1,"Duplicate Order ID","Unique") -> Unique | AA50: =IF( OR(AQ50<0, AQ50>1, C50<B50), "Invalid", IF( OR(G50="Unknown", M50="Unknown"), "Warning", "Clean" ) ) -> Clean | AB50: =IF( OR( B50="", C50="", NOT(ISNUMBER(B50)), NOT(ISNUMBER(C50)), C50<B50 ), "Invalid", "Valid" ) -> Valid | AC50: 6 | AD50: =IF(C50<B50,"Invalid Shipping Date","Valid") -> Valid | AE50: =IF(AND(B50<>"",NOT(ISNUMBER(B50))),"Text Not Date","Valid") -> Valid | AF50: =IF(ISNUMBER(B50),"Valid","Invalid") -> Valid | AG50: =IF(ISNUMBER(C50),"Valid","Invalid") -> Valid | AH50: =IF(OR(B50="",ISBLANK(B50)),"Missing","Valid") -> Valid | AI50: =IF(OR(C50="",ISBLANK(C50)),"Missing","Valid") -> Valid | AJ50: FALSE | AK50: FALSE | AL50: FALSE | AM50: FALSE | AN50: FALSE | AO50: FALSE | AP50: FALSE | AQ50: =IF(OR(P50="",ISBLANK(P50)),0,P50) -> 0 | AR50: =N50*O50*(1-AQ50) -> 28445.62 | AS50: =Q50-AR50 -> 0 | AT50: =AR50-R50 -> 7507.03 | AU50: =S50-AT50 -> 0 | AV50: =AT50/AR50 -> 0.26390812 | AW50: =TEXT(B50,"mmmm") -> January | AX50: =YEAR(B50) -> 2025
A51: ORD-2024-10050 | B51: 45388 | C51: 45395 | D51: CUST-2380 | E51: Aarav Sharma | F51: Home Office | G51: North | H51: Uttar Pradesh | I51: Noida | J51: Technology | K51: Copiers | L51: Classic Copiers 295 | M51: Second Class | N51: 9 | O51: 792.11 | P51: 0.05 | Q51: 6772.54 | R51: 5755.46 | S51: 1017.08 | T51: Paid | U51: Completed | V51: =TEXTJOIN("|",TRUE,A51:U51) -> #NAME? | W51: =IFERROR(__xludf.DUMMYFUNCTION("IF(COUNTIF($A:$A,A45)=1, ""Unique"", IF(COUNTUNIQUE(FILTER($V$2:$V$934,$A$2:$A$934=A45))>1, ""Conflicting Duplicate"", ""Exact Duplicate""))"),"Unique") -> Unique | X51: =COUNTIF(V:V,V51)>1 -> TRUE | Y51: =IF(COUNTIF($A:$A,A51)>1,"Duplicate Order ID","Unique") -> Unique | AA51: =IF( OR(AQ51<0, AQ51>1, C51<B51), "Invalid", IF( OR(G51="Unknown", M51="Unknown"), "Warning", "Clean" ) ) -> Clean | AB51: =IF( OR( B51="", C51="", NOT(ISNUMBER(B51)), NOT(ISNUMBER(C51)), C51<B51 ), "Invalid", "Valid" ) -> Valid | AC51: 7 | AD51: =IF(C51<B51,"Invalid Shipping Date","Valid") -> Valid | AE51: =IF(AND(B51<>"",NOT(ISNUMBER(B51))),"Text Not Date","Valid") -> Valid | AF51: =IF(ISNUMBER(B51),"Valid","Invalid") -> Valid | AG51: =IF(ISNUMBER(C51),"Valid","Invalid") -> Valid | AH51: =IF(OR(B51="",ISBLANK(B51)),"Missing","Valid") -> Valid | AI51: =IF(OR(C51="",ISBLANK(C51)),"Missing","Valid") -> Valid | AJ51: FALSE | AK51: FALSE | AL51: FALSE | AM51: FALSE | AN51: FALSE | AO51: FALSE | AP51: FALSE | AQ51: =IF(OR(P51="",ISBLANK(P51)),0,P51) -> 0.05 | AR51: =N51*O51*(1-AQ51) -> 6772.5405 | AS51: =Q51-AR51 -> -0.0005 | AT51: =AR51-R51 -> 1017.0805 | AU51: =S51-AT51 -> -0.0005 | AV51: =AT51/AR51 -> 0.1501771 | AW51: =TEXT(B51,"mmmm") -> April | AX51: =YEAR(B51) -> 2024
A52: ORD-2025-10051 | B52: 45788 | C52: 45796 | D52: CUST-8787 | E52: Sneha Kapoor | F52: Consumer | G52: East | H52: West Bengal | I52: Kolkata | J52: Technology | K52: Copiers | L52: Pro Copiers 963 | M52: Standard Class | N52: 1 | O52: 2382.8 | P52: 0.15 | Q52: 2025.38 | R52: 1140.65 | S52: 884.73 | T52: Paid | U52: Completed | V52: =TEXTJOIN("|",TRUE,A52:U52) -> #NAME? | W52: =IFERROR(__xludf.DUMMYFUNCTION("IF(COUNTIF($A:$A,A46)=1, ""Unique"", IF(COUNTUNIQUE(FILTER($V$2:$V$934,$A$2:$A$934=A46))>1, ""Conflicting Duplicate"", ""Exact Duplicate""))"),"Unique") -> Unique | X52: =COUNTIF(V:V,V52)>1 -> TRUE | Y52: =IF(COUNTIF($A:$A,A52)>1,"Duplicate Order ID","Unique") -> Unique | AA52: =IF( OR(AQ52<0, AQ52>1, C52<B52), "Invalid", IF( OR(G52="Unknown", M52="Unknown"), "Warning", "Clean" ) ) -> Clean | AB52: =IF( OR( B52="", C52="", NOT(ISNUMBER(B52)), NOT(ISNUMBER(C52)), C52<B52 ), "Invalid", "Valid" ) -> Valid | AC52: 8 | AD52: =IF(C52<B52,"Invalid Shipping Date","Valid") -> Valid | AE52: =IF(AND(B52<>"",NOT(ISNUMBER(B52))),"Text Not Date","Valid") -> Valid | AF52: =IF(ISNUMBER(B52),"Valid","Invalid") -> Valid | AG52: =IF(ISNUMBER(C52),"Valid","Invalid") -> Valid | AH52: =IF(OR(B52="",ISBLANK(B52)),"Missing","Valid") -> Valid | AI52: =IF(OR(C52="",ISBLANK(C52)),"Missing","Valid") -> Valid | AJ52: FALSE | AK52: FALSE | AL52: FALSE | AM52: FALSE | AN52: FALSE | AO52: FALSE | AP52: FALSE | AQ52: =IF(OR(P52="",ISBLANK(P52)),0,P52) -> 0.15 | AR52: =N52*O52*(1-AQ52) -> 2025.38 | AS52: =Q52-AR52 -> 0 | AT52: =AR52-R52 -> 884.73 | AU52: =S52-AT52 -> 0 | AV52: =AT52/AR52 -> 0.43682173 | AW52: =TEXT(B52,"mmmm") -> May | AX52: =YEAR(B52) -> 2025
A53: ORD-2024-10052 | B53: 45406 | C53: 45411 | D53: CUST-3557 | E53: Ananya Rao | F53: Corporate | G53: South | H53: Telangana | I53: Hyderabad | J53: Office Supplies | K53: Art | L53: Pro Art 907 | M53: Standard Class | N53: 6 | O53: 1528.08 | P53: 0 | Q53: 9168.48 | R53: 7439.77 | S53: 1728.71 | T53: Paid | U53: Completed | V53: =TEXTJOIN("|",TRUE,A53:U53) -> #NAME? | W53: =IFERROR(__xludf.DUMMYFUNCTION("IF(COUNTIF($A:$A,A47)=1, ""Unique"", IF(COUNTUNIQUE(FILTER($V$2:$V$934,$A$2:$A$934=A47))>1, ""Conflicting Duplicate"", ""Exact Duplicate""))"),"Unique") -> Unique | X53: =COUNTIF(V:V,V53)>1 -> TRUE | Y53: =IF(COUNTIF($A:$A,A53)>1,"Duplicate Order ID","Unique") -> Unique | AA53: =IF( OR(AQ53<0, AQ53>1, C53<B53), "Invalid", IF( OR(G53="Unknown", M53="Unknown"), "Warning", "Clean" ) ) -> Clean | AB53: =IF( OR( B53="", C53="", NOT(ISNUMBER(B53)), NOT(ISNUMBER(C53)), C53<B53 ), "Invalid", "Valid" ) -> Valid | AC53: 5 | AD53: =IF(C53<B53,"Invalid Shipping Date","Valid") -> Valid | AE53: =IF(AND(B53<>"",NOT(ISNUMBER(B53))),"Text Not Date","Valid") -> Valid | AF53: =IF(ISNUMBER(B53),"Valid","Invalid") -> Valid | AG53: =IF(ISNUMBER(C53),"Valid","Invalid") -> Valid | AH53: =IF(OR(B53="",ISBLANK(B53)),"Missing","Valid") -> Valid | AI53: =IF(OR(C53="",ISBLANK(C53)),"Missing","Valid") -> Valid | AJ53: FALSE | AK53: FALSE | AL53: FALSE | AM53: FALSE | AN53: FALSE | AO53: FALSE | AP53: FALSE | AQ53: =IF(OR(P53="",ISBLANK(P53)),0,P53) -> 0 | AR53: =N53*O53*(1-AQ53) -> 9168.48 | AS53: =Q53-AR53 -> 0 | AT53: =AR53-R53 -> 1728.71 | AU53: =S53-AT53 -> 0 | AV53: =AT53/AR53 -> 0.18854925 | AW53: =TEXT(B53,"mmmm") -> April | AX53: =YEAR(B53) -> 2024
A54: ORD-2024-10053 | B54: 45591 | C54: 45593 | D54: CUST-2778 | E54: Kabir Singh | F54: Small Business | G54: North | H54: Rajasthan | I54: Jaipur | J54: Furniture | K54: Chairs | L54: Pro Chairs 526 | M54: First Class | N54: 9 | O54: 1399.63 | P54: 0 | Q54: 12596.67 | R54: 10603.29 | S54: 1993.38 | T54: Failed | U54: Cancelled | V54: =TEXTJOIN("|",TRUE,A54:U54) -> #NAME? | W54: =IFERROR(__xludf.DUMMYFUNCTION("IF(COUNTIF($A:$A,A48)=1, ""Unique"", IF(COUNTUNIQUE(FILTER($V$2:$V$934,$A$2:$A$934=A48))>1, ""Conflicting Duplicate"", ""Exact Duplicate""))"),"Unique") -> Unique | X54: =COUNTIF(V:V,V54)>1 -> TRUE | Y54: =IF(COUNTIF($A:$A,A54)>1,"Duplicate Order ID","Unique") -> Unique | AA54: =IF( OR(AQ54<0, AQ54>1, C54<B54), "Invalid", IF( OR(G54="Unknown", M54="Unknown"), "Warning", "Clean" ) ) -> Clean | AB54: =IF( OR( B54="", C54="", NOT(ISNUMBER(B54)), NOT(ISNUMBER(C54)), C54<B54 ), "Invalid", "Valid" ) -> Valid | AC54: 2 | AD54: =IF(C54<B54,"Invalid Shipping Date","Valid") -> Valid | AE54: =IF(AND(B54<>"",NOT(ISNUMBER(B54))),"Text Not Date","Valid") -> Valid | AF54: =IF(ISNUMBER(B54),"Valid","Invalid") -> Valid | AG54: =IF(ISNUMBER(C54),"Valid","Invalid") -> Valid | AH54: =IF(OR(B54="",ISBLANK(B54)),"Missing","Valid") -> Valid | AI54: =IF(OR(C54="",ISBLANK(C54)),"Missing","Valid") -> Valid | AJ54: FALSE | AK54: FALSE | AL54: FALSE | AM54: FALSE | AN54: FALSE | AO54: FALSE | AP54: FALSE | AQ54: =IF(OR(P54="",ISBLANK(P54)),0,P54) -> 0 | AR54: =N54*O54*(1-AQ54) -> 12596.67 | AS54: =Q54-AR54 -> 0 | AT54: =AR54-R54 -> 1993.38 | AU54: =S54-AT54 -> 0 | AV54: =AT54/AR54 -> 0.15824658 | AW54: =TEXT(B54,"mmmm") -> October | AX54: =YEAR(B54) -> 2024
A55: ORD-2025-10054 | B55: 45747 | C55: 45747 | D55: CUST-7195 | E55: Kabir Singh | F55: Home Office | G55: West | H55: Gujarat | I55: Ahmedabad | J55: Office Supplies | K55: Storage | L55: Elite Storage 924 | M55: First Class | N55: 5 | O55: 1207.47 | P55: 0.15 | Q55: 5131.75 | R55: 2838.68 | S55: 2293.07 | T55: Paid | U55: Completed | V55: =TEXTJOIN("|",TRUE,A55:U55) -> #NAME? | W55: =IFERROR(__xludf.DUMMYFUNCTION("IF(COUNTIF($A:$A,A49)=1, ""Unique"", IF(COUNTUNIQUE(FILTER($V$2:$V$934,$A$2:$A$934=A49))>1, ""Conflicting Duplicate"", ""Exact Duplicate""))"),"Unique") -> Unique | X55: =COUNTIF(V:V,V55)>1 -> TRUE | Y55: =IF(COUNTIF($A:$A,A55)>1,"Duplicate Order ID","Unique") -> Unique | AA55: =IF( OR(AQ55<0, AQ55>1, C55<B55), "Invalid", IF( OR(G55="Unknown", M55="Unknown"), "Warning", "Clean" ) ) -> Clean | AB55: =IF( OR( B55="", C55="", NOT(ISNUMBER(B55)), NOT(ISNUMBER(C55)), C55<B55 ), "Invalid", "Valid" ) -> Valid | AC55: 0 | AD55: =IF(C55<B55,"Invalid Shipping Date","Valid") -> Valid | AE55: =IF(AND(B55<>"",NOT(ISNUMBER(B55))),"Text Not Date","Valid") -> Valid | AF55: =IF(ISNUMBER(B55),"Valid","Invalid") -> Valid | AG55: =IF(ISNUMBER(C55),"Valid","Invalid") -> Valid | AH55: =IF(OR(B55="",ISBLANK(B55)),"Missing","Valid") -> Valid | AI55: =IF(OR(C55="",ISBLANK(C55)),"Missing","Valid") -> Valid | AJ55: FALSE | AK55: FALSE | AL55: FALSE | AM55: FALSE | AN55: FALSE | AO55: FALSE | AP55: FALSE | AQ55: =IF(OR(P55="",ISBLANK(P55)),0,P55) -> 0.15 | AR55: =N55*O55*(1-AQ55) -> 5131.7475 | AS55: =Q55-AR55 -> 0.0025 | AT55: =AR55-R55 -> 2293.0675 | AU55: =S55-AT55 -> 0.0025 | AV55: =AT55/AR55 -> 0.4468395 | AW55: =TEXT(B55,"mmmm") -> March | AX55: =YEAR(B55) -> 2025
A56: ORD-2025-10055 | B56: 45807 | C56: 45810 | D56: CUST-9039 | E56: Arjun Bose | F56: Corporate | G56: South | H56: Tamil Nadu | I56: Chennai | J56: Office Supplies | K56: Labels | L56: Pro Labels 957 | M56: Same Day | N56: 8 | O56: 474.37 | P56: 0.1 | Q56: 3415.46 | R56: 1993.23 | S56: 1422.23 | T56: Failed | U56: Cancelled | V56: =TEXTJOIN("|",TRUE,A56:U56) -> #NAME? | W56: =IFERROR(__xludf.DUMMYFUNCTION("IF(COUNTIF($A:$A,A50)=1, ""Unique"", IF(COUNTUNIQUE(FILTER($V$2:$V$934,$A$2:$A$934=A50))>1, ""Conflicting Duplicate"", ""Exact Duplicate""))"),"Unique") -> Unique | X56: =COUNTIF(V:V,V56)>1 -> TRUE | Y56: =IF(COUNTIF($A:$A,A56)>1,"Duplicate Order ID","Unique") -> Unique | AA56: =IF( OR(AQ56<0, AQ56>1, C56<B56), "Invalid", IF( OR(G56="Unknown", M56="Unknown"), "Warning", "Clean" ) ) -> Clean | AB56: =IF( OR( B56="", C56="", NOT(ISNUMBER(B56)), NOT(ISNUMBER(C56)), C56<B56 ), "Invalid", "Valid" ) -> Valid | AC56: 3 | AD56: =IF(C56<B56,"Invalid Shipping Date","Valid") -> Valid | AE56: =IF(AND(B56<>"",NOT(ISNUMBER(B56))),"Text Not Date","Valid") -> Valid | AF56: =IF(ISNUMBER(B56),"Valid","Invalid") -> Valid | AG56: =IF(ISNUMBER(C56),"Valid","Invalid") -> Valid | AH56: =IF(OR(B56="",ISBLANK(B56)),"Missing","Valid") -> Valid | AI56: =IF(OR(C56="",ISBLANK(C56)),"Missing","Valid") -> Valid | AJ56: FALSE | AK56: FALSE | AL56: FALSE | AM56: FALSE | AN56: FALSE | AO56: FALSE | AP56: FALSE | AQ56: =IF(OR(P56="",ISBLANK(P56)),0,P56) -> 0.1 | AR56: =N56*O56*(1-AQ56) -> 3415.464 | AS56: =Q56-AR56 -> -0.004 | AT56: =AR56-R56 -> 1422.234 | AU56: =S56-AT56 -> -0.004 | AV56: =AT56/AR56 -> 0.41641019 | AW56: =TEXT(B56,"mmmm") -> May | AX56: =YEAR(B56) -> 2025
A57: ORD-2025-10056 | B57: 45839 | C57: 45841 | D57: CUST-9821 | E57: Mira Das | F57: Small Business | G57: South | H57: Andhra Pradesh | I57: Vijayawada | J57: Technology | K57: Machines | L57: Classic Machines 310 | M57: Same Day | N57: 3 | O57: 1516.24 | P57: 0.25 | Q57: 3411.54 | R57: 2803.13 | S57: 608.41 | T57: Paid | U57: Completed | V57: =TEXTJOIN("|",TRUE,A57:U57) -> #NAME? | W57: =IFERROR(__xludf.DUMMYFUNCTION("IF(COUNTIF($A:$A,A51)=1, ""Unique"", IF(COUNTUNIQUE(FILTER($V$2:$V$934,$A$2:$A$934=A51))>1, ""Conflicting Duplicate"", ""Exact Duplicate""))"),"Unique") -> Unique | X57: =COUNTIF(V:V,V57)>1 -> TRUE | Y57: =IF(COUNTIF($A:$A,A57)>1,"Duplicate Order ID","Unique") -> Unique | AA57: =IF( OR(AQ57<0, AQ57>1, C57<B57), "Invalid", IF( OR(G57="Unknown", M57="Unknown"), "Warning", "Clean" ) ) -> Clean | AB57: =IF( OR( B57="", C57="", NOT(ISNUMBER(B57)), NOT(ISNUMBER(C57)), C57<B57 ), "Invalid", "Valid" ) -> Valid | AC57: 2 | AD57: =IF(C57<B57,"Invalid Shipping Date","Valid") -> Valid | AE57: =IF(AND(B57<>"",NOT(ISNUMBER(B57))),"Text Not Date","Valid") -> Valid | AF57: =IF(ISNUMBER(B57),"Valid","Invalid") -> Valid | AG57: =IF(ISNUMBER(C57),"Valid","Invalid") -> Valid | AH57: =IF(OR(B57="",ISBLANK(B57)),"Missing","Valid") -> Valid | AI57: =IF(OR(C57="",ISBLANK(C57)),"Missing","Valid") -> Valid | AJ57: FALSE | AK57: FALSE | AL57: FALSE | AM57: FALSE | AN57: FALSE | AO57: FALSE | AP57: FALSE | AQ57: =IF(OR(P57="",ISBLANK(P57)),0,P57) -> 0.25 | AR57: =N57*O57*(1-AQ57) -> 3411.54 | AS57: =Q57-AR57 -> 0 | AT57: =AR57-R57 -> 608.41 | AU57: =S57-AT57 -> 0 | AV57: =AT57/AR57 -> 0.17833881 | AW57: =TEXT(B57,"mmmm") -> July | AX57: =YEAR(B57) -> 2025
A58: ORD-2025-10057 | B58: 45662 | C58: 45663 | D58: CUST-8701 | E58: Karan Malhotra | F58: Consumer | G58: South | H58: Karnataka | I58: Bengaluru | J58: Office Supplies | K58: Binders | L58: Smart Binders 393 | M58: Second Class | N58: 3 | O58: 3155.61 | P58: 0 | Q58: 9466.83 | R58: 6557.83 | S58: 2909 | T58: Refunded | U58: Cancelled | V58: =TEXTJOIN("|",TRUE,A58:U58) -> #NAME? | W58: =IFERROR(__xludf.DUMMYFUNCTION("IF(COUNTIF($A:$A,A52)=1, ""Unique"", IF(COUNTUNIQUE(FILTER($V$2:$V$934,$A$2:$A$934=A52))>1, ""Conflicting Duplicate"", ""Exact Duplicate""))"),"Unique") -> Unique | X58: =COUNTIF(V:V,V58)>1 -> TRUE | Y58: =IF(COUNTIF($A:$A,A58)>1,"Duplicate Order ID","Unique") -> Unique | AA58: =IF( OR(AQ58<0, AQ58>1, C58<B58), "Invalid", IF( OR(G58="Unknown", M58="Unknown"), "Warning", "Clean" ) ) -> Clean | AB58: =IF( OR( B58="", C58="", NOT(ISNUMBER(B58)), NOT(ISNUMBER(C58)), C58<B58 ), "Invalid", "Valid" ) -> Valid | AC58: 1 | AD58: =IF(C58<B58,"Invalid Shipping Date","Valid") -> Valid | AE58: =IF(AND(B58<>"",NOT(ISNUMBER(B58))),"Text Not Date","Valid") -> Valid | AF58: =IF(ISNUMBER(B58),"Valid","Invalid") -> Valid | AG58: =IF(ISNUMBER(C58),"Valid","Invalid") -> Valid | AH58: =IF(OR(B58="",ISBLANK(B58)),"Missing","Valid") -> Valid | AI58: =IF(OR(C58="",ISBLANK(C58)),"Missing","Valid") -> Valid | AJ58: FALSE | AK58: FALSE | AL58: FALSE | AM58: FALSE | AN58: FALSE | AO58: FALSE | AP58: FALSE | AQ58: =IF(OR(P58="",ISBLANK(P58)),0,P58) -> 0 | AR58: =N58*O58*(1-AQ58) -> 9466.83 | AS58: =Q58-AR58 -> 0 | AT58: =AR58-R58 -> 2909 | AU58: =S58-AT58 -> 0 | AV58: =AT58/AR58 -> 0.30728343 | AW58: =TEXT(B58,"mmmm") -> January | AX58: =YEAR(B58) -> 2025
A59: ORD-2024-10058 | B59: 45329 | C59: 45337 | D59: CUST-9941 | E59: Priya Menon | F59: Consumer | G59: West | H59: Goa | I59: Panaji | J59: Furniture | K59: Chairs | L59: Max Chairs 813 | M59: Same Day | N59: 5 | O59: 255.87 | P59: 0 | Q59: 1279.35 | R59: 1091.54 | S59: 187.81 | T59: Paid | U59: Completed | V59: =TEXTJOIN("|",TRUE,A59:U59) -> #NAME? | W59: =IFERROR(__xludf.DUMMYFUNCTION("IF(COUNTIF($A:$A,A53)=1, ""Unique"", IF(COUNTUNIQUE(FILTER($V$2:$V$934,$A$2:$A$934=A53))>1, ""Conflicting Duplicate"", ""Exact Duplicate""))"),"Unique") -> Unique | X59: =COUNTIF(V:V,V59)>1 -> TRUE | Y59: =IF(COUNTIF($A:$A,A59)>1,"Duplicate Order ID","Unique") -> Unique | AA59: =IF( OR(AQ59<0, AQ59>1, C59<B59), "Invalid", IF( OR(G59="Unknown", M59="Unknown"), "Warning", "Clean" ) ) -> Clean | AB59: =IF( OR( B59="", C59="", NOT(ISNUMBER(B59)), NOT(ISNUMBER(C59)), C59<B59 ), "Invalid", "Valid" ) -> Valid | AC59: 8 | AD59: =IF(C59<B59,"Invalid Shipping Date","Valid") -> Valid | AE59: =IF(AND(B59<>"",NOT(ISNUMBER(B59))),"Text Not Date","Valid") -> Valid | AF59: =IF(ISNUMBER(B59),"Valid","Invalid") -> Valid | AG59: =IF(ISNUMBER(C59),"Valid","Invalid") -> Valid | AH59: =IF(OR(B59="",ISBLANK(B59)),"Missing","Valid") -> Valid | AI59: =IF(OR(C59="",ISBLANK(C59)),"Missing","Valid") -> Valid | AJ59: FALSE | AK59: FALSE | AL59: FALSE | AM59: FALSE | AN59: FALSE | AO59: FALSE | AP59: FALSE | AQ59: =IF(OR(P59="",ISBLANK(P59)),0,P59) -> 0 | AR59: =N59*O59*(1-AQ59) -> 1279.35 | AS59: =Q59-AR59 -> 0 | AT59: =AR59-R59 -> 187.81 | AU59: =S59-AT59 -> 0 | AV59: =AT59/AR59 -> 0.14680111 | AW59: =TEXT(B59,"mmmm") -> February | AX59: =YEAR(B59) -> 2024
A60: ORD-2024-10059 | B60: 45536 | C60: 45542 | D60: CUST-3983 | E60: Isha Nair | F60: Home Office | G60: North | H60: Rajasthan | I60: Jaipur | J60: Office Supplies | K60: Storage | L60: Basic Storage 872 | M60: Unknown | N60: 9 | O60: 1389.48 | P60: 0.1 | Q60: 11254.79 | R60: 6578.06 | S60: 4676.73 | T60: Pending | U60: Returned | V60: =TEXTJOIN("|",TRUE,A60:U60) -> #NAME? | W60: =IFERROR(__xludf.DUMMYFUNCTION("IF(COUNTIF($A:$A,A54)=1, ""Unique"", IF(COUNTUNIQUE(FILTER($V$2:$V$934,$A$2:$A$934=A54))>1, ""Conflicting Duplicate"", ""Exact Duplicate""))"),"Unique") -> Unique | X60: =COUNTIF(V:V,V60)>1 -> TRUE | Y60: =IF(COUNTIF($A:$A,A60)>1,"Duplicate Order ID","Unique") -> Unique | AA60: =IF( OR(AQ60<0, AQ60>1, C60<B60), "Invalid", IF( OR(G60="Unknown", M60="Unknown"), "Warning", "Clean" ) ) -> Warning | AB60: =IF( OR( B60="", C60="", NOT(ISNUMBER(B60)), NOT(ISNUMBER(C60)), C60<B60 ), "Invalid", "Valid" ) -> Valid | AC60: 6 | AD60: =IF(C60<B60,"Invalid Shipping Date","Valid") -> Valid | AE60: =IF(AND(B60<>"",NOT(ISNUMBER(B60))),"Text Not Date","Valid") -> Valid | AF60: =IF(ISNUMBER(B60),"Valid","Invalid") -> Valid | AG60: =IF(ISNUMBER(C60),"Valid","Invalid") -> Valid | AH60: =IF(OR(B60="",ISBLANK(B60)),"Missing","Valid") -> Valid | AI60: =IF(OR(C60="",ISBLANK(C60)),"Missing","Valid") -> Valid | AJ60: FALSE | AK60: TRUE | AL60: FALSE | AM60: FALSE | AN60: FALSE | AO60: FALSE | AP60: TRUE | AQ60: =IF(OR(P60="",ISBLANK(P60)),0,P60) -> 0.1 | AR60: =N60*O60*(1-AQ60) -> 11254.788 | AS60: =Q60-AR60 -> 0.002 | AT60: =AR60-R60 -> 4676.728 | AU60: =S60-AT60 -> 0.002 | AV60: =AT60/AR60 -> 0.41553231 | AW60: =TEXT(B60,"mmmm") -> September | AX60: =YEAR(B60) -> 2024
A61: ORD-2024-10060 | B61: 45493 | C61: 45498 | D61: CUST-2418 | E61: Priya Menon | F61: Corporate | G61: East | H61: Assam | I61: Guwahati | J61: Office Supplies | K61: Labels | L61: Smart Labels 655 | M61: Same Day | N61: 5 | O61: 4133.85 | P61: 0.2 | Q61: 16535.4 | R61: 12990.21 | S61: 3545.19 | T61: Paid | U61: Cancelled | V61: =TEXTJOIN("|",TRUE,A61:U61) -> #NAME? | W61: =IFERROR(__xludf.DUMMYFUNCTION("IF(COUNTIF($A:$A,A55)=1, ""Unique"", IF(COUNTUNIQUE(FILTER($V$2:$V$934,$A$2:$A$934=A55))>1, ""Conflicting Duplicate"", ""Exact Duplicate""))"),"Unique") -> Unique | X61: =COUNTIF(V:V,V61)>1 -> TRUE | Y61: =IF(COUNTIF($A:$A,A61)>1,"Duplicate Order ID","Unique") -> Unique | AA61: =IF( OR(AQ61<0, AQ61>1, C61<B61), "Invalid", IF( OR(G61="Unknown", M61="Unknown"), "Warning", "Clean" ) ) -> Clean | AB61: =IF( OR( B61="", C61="", NOT(ISNUMBER(B61)), NOT(ISNUMBER(C61)), C61<B61 ), "Invalid", "Valid" ) -> Valid | AC61: 5 | AD61: =IF(C61<B61,"Invalid Shipping Date","Valid") -> Valid | AE61: =IF(AND(B61<>"",NOT(ISNUMBER(B61))),"Text Not Date","Valid") -> Valid | AF61: =IF(ISNUMBER(B61),"Valid","Invalid") -> Valid | AG61: =IF(ISNUMBER(C61),"Valid","Invalid") -> Valid | AH61: =IF(OR(B61="",ISBLANK(B61)),"Missing","Valid") -> Valid | AI61: =IF(OR(C61="",ISBLANK(C61)),"Missing","Valid") -> Valid | AJ61: FALSE | AK61: FALSE | AL61: FALSE | AM61: FALSE | AN61: FALSE | AO61: FALSE | AP61: FALSE | AQ61: =IF(OR(P61="",ISBLANK(P61)),0,P61) -> 0.2 | AR61: =N61*O61*(1-AQ61) -> 16535.4 | AS61: =Q61-AR61 -> 0 | AT61: =AR61-R61 -> 3545.19 | AU61: =S61-AT61 -> 0 | AV61: =AT61/AR61 -> 0.21440001 | AW61: =TEXT(B61,"mmmm") -> July | AX61: =YEAR(B61) -> 2024
A62: ORD-2024-10061 | B62: 45486 | C62: 45492 | D62: CUST-2892 | E62: Ananya Rao | F62: Corporate | G62: East | H62: Assam | I62: Guwahati | J62: Office Supplies | K62: Labels | L62: Eco Labels 210 | M62: Same Day | N62: 3 | O62: 275.76 | P62: 0.2 | Q62: 661.82 | R62: 481.47 | S62: 180.35 | T62: Refunded | U62: Cancelled | V62: =TEXTJOIN("|",TRUE,A62:U62) -> #NAME? | W62: =IFERROR(__xludf.DUMMYFUNCTION("IF(COUNTIF($A:$A,A56)=1, ""Unique"", IF(COUNTUNIQUE(FILTER($V$2:$V$934,$A$2:$A$934=A56))>1, ""Conflicting Duplicate"", ""Exact Duplicate""))"),"Unique") -> Unique | X62: =COUNTIF(V:V,V62)>1 -> TRUE | Y62: =IF(COUNTIF($A:$A,A62)>1,"Duplicate Order ID","Unique") -> Unique | AA62: =IF( OR(AQ62<0, AQ62>1, C62<B62), "Invalid", IF( OR(G62="Unknown", M62="Unknown"), "Warning", "Clean" ) ) -> Clean | AB62: =IF( OR( B62="", C62="", NOT(ISNUMBER(B62)), NOT(ISNUMBER(C62)), C62<B62 ), "Invalid", "Valid" ) -> Valid | AC62: 6 | AD62: =IF(C62<B62,"Invalid Shipping Date","Valid") -> Valid | AE62: =IF(AND(B62<>"",NOT(ISNUMBER(B62))),"Text Not Date","Valid") -> Valid | AF62: =IF(ISNUMBER(B62),"Valid","Invalid") -> Valid | AG62: =IF(ISNUMBER(C62),"Valid","Invalid") -> Valid | AH62: =IF(OR(B62="",ISBLANK(B62)),"Missing","Valid") -> Valid | AI62: =IF(OR(C62="",ISBLANK(C62)),"Missing","Valid") -> Valid | AJ62: FALSE | AK62: FALSE | AL62: FALSE | AM62: FALSE | AN62: FALSE | AO62: FALSE | AP62: FALSE | AQ62: =IF(OR(P62="",ISBLANK(P62)),0,P62) -> 0.2 | AR62: =N62*O62*(1-AQ62) -> 661.824 | AS62: =Q62-AR62 -> -0.004 | AT62: =AR62-R62 -> 180.354 | AU62: =S62-AT62 -> -0.004 | AV62: =AT62/AR62 -> 0.27251052 | AW62: =TEXT(B62,"mmmm") -> July | AX62: =YEAR(B62) -> 2024
A63: ORD-2024-10062 | B63: 45398 | C63: 45398 | D63: CUST-7008 | E63: Vikram Iyer | F63: Home Office | G63: East | H63: Bihar | I63: Patna | J63: Furniture | K63: Bookcases | L63: Classic Bookcases 296 | M63: Standard Class | N63: 1 | O63: 949.59 | P63: 0 | Q63: 949.59 | R63: 751.25 | S63: 198.34 | T63: Paid | U63: Completed | V63: =TEXTJOIN("|",TRUE,A63:U63) -> #NAME? | W63: =IFERROR(__xludf.DUMMYFUNCTION("IF(COUNTIF($A:$A,A57)=1, ""Unique"", IF(COUNTUNIQUE(FILTER($V$2:$V$934,$A$2:$A$934=A57))>1, ""Conflicting Duplicate"", ""Exact Duplicate""))"),"Unique") -> Unique | X63: =COUNTIF(V:V,V63)>1 -> TRUE | Y63: =IF(COUNTIF($A:$A,A63)>1,"Duplicate Order ID","Unique") -> Unique | AA63: =IF( OR(AQ63<0, AQ63>1, C63<B63), "Invalid", IF( OR(G63="Unknown", M63="Unknown"), "Warning", "Clean" ) ) -> Clean | AB63: =IF( OR( B63="", C63="", NOT(ISNUMBER(B63)), NOT(ISNUMBER(C63)), C63<B63 ), "Invalid", "Valid" ) -> Valid | AC63: 0 | AD63: =IF(C63<B63,"Invalid Shipping Date","Valid") -> Valid | AE63: =IF(AND(B63<>"",NOT(ISNUMBER(B63))),"Text Not Date","Valid") -> Valid | AF63: =IF(ISNUMBER(B63),"Valid","Invalid") -> Valid | AG63: =IF(ISNUMBER(C63),"Valid","Invalid") -> Valid | AH63: =IF(OR(B63="",ISBLANK(B63)),"Missing","Valid") -> Valid | AI63: =IF(OR(C63="",ISBLANK(C63)),"Missing","Valid") -> Valid | AJ63: FALSE | AK63: FALSE | AL63: FALSE | AM63: FALSE | AN63: FALSE | AO63: FALSE | AP63: FALSE | AQ63: =IF(OR(P63="",ISBLANK(P63)),0,P63) -> 0 | AR63: =N63*O63*(1-AQ63) -> 949.59 | AS63: =Q63-AR63 -> 0 | AT63: =AR63-R63 -> 198.34 | AU63: =S63-AT63 -> 0 | AV63: =AT63/AR63 -> 0.20886909 | AW63: =TEXT(B63,"mmmm") -> April | AX63: =YEAR(B63) -> 2024
A64: ORD-2024-10063 | B64: 45595 | C64: 45598 | D64: CUST-4900 | E64: Sneha Kapoor | F64: Home Office | G64: North | H64: Rajasthan | I64: Jaipur | J64: Technology | K64: Phones | L64: Basic Phones 230 | M64: Standard Class | N64: 9 | O64: 3042.29 | P64: 0.2 | Q64: 21904.49 | R64: 13570.55 | S64: 8333.94 | T64: Paid | U64: Completed | V64: =TEXTJOIN("|",TRUE,A64:U64) -> #NAME? | W64: =IFERROR(__xludf.DUMMYFUNCTION("IF(COUNTIF($A:$A,A58)=1, ""Unique"", IF(COUNTUNIQUE(FILTER($V$2:$V$934,$A$2:$A$934=A58))>1, ""Conflicting Duplicate"", ""Exact Duplicate""))"),"Unique") -> Unique | X64: =COUNTIF(V:V,V64)>1 -> TRUE | Y64: =IF(COUNTIF($A:$A,A64)>1,"Duplicate Order ID","Unique") -> Unique | AA64: =IF( OR(AQ64<0, AQ64>1, C64<B64), "Invalid", IF( OR(G64="Unknown", M64="Unknown"), "Warning", "Clean" ) ) -> Clean | AB64: =IF( OR( B64="", C64="", NOT(ISNUMBER(B64)), NOT(ISNUMBER(C64)), C64<B64 ), "Invalid", "Valid" ) -> Valid | AC64: 3 | AD64: =IF(C64<B64,"Invalid Shipping Date","Valid") -> Valid | AE64: =IF(AND(B64<>"",NOT(ISNUMBER(B64))),"Text Not Date","Valid") -> Valid | AF64: =IF(ISNUMBER(B64),"Valid","Invalid") -> Valid | AG64: =IF(ISNUMBER(C64),"Valid","Invalid") -> Valid | AH64: =IF(OR(B64="",ISBLANK(B64)),"Missing","Valid") -> Valid | AI64: =IF(OR(C64="",ISBLANK(C64)),"Missing","Valid") -> Valid | AJ64: FALSE | AK64: FALSE | AL64: FALSE | AM64: FALSE | AN64: FALSE | AO64: FALSE | AP64: FALSE | AQ64: =IF(OR(P64="",ISBLANK(P64)),0,P64) -> 0.2 | AR64: =N64*O64*(1-AQ64) -> 21904.488 | AS64: =Q64-AR64 -> 0.002 | AT64: =AR64-R64 -> 8333.938 | AU64: =S64-AT64 -> 0.002 | AV64: =AT64/AR64 -> 0.38046714 | AW64: =TEXT(B64,"mmmm") -> October | AX64: =YEAR(B64) -> 2024
A65: ORD-2024-10064 | B65: 45316 | C65: 45323 | D65: CUST-5382 | E65: Sneha Kapoor | F65: Home Office | G65: North | H65: Haryana | I65: Gurugram | J65: Office Supplies | K65: Binders | L65: Pro Binders 690 | M65: Same Day | N65: 2 | O65: 2832.77 | P65: 0.15 | Q65: 4815.71 | R65: 3027.75 | S65: 1917.47 | T65: Paid | U65: Completed | V65: =TEXTJOIN("|",TRUE,A65:U65) -> #NAME? | W65: =IFERROR(__xludf.DUMMYFUNCTION("IF(COUNTIF($A:$A,A59)=1, ""Unique"", IF(COUNTUNIQUE(FILTER($V$2:$V$934,$A$2:$A$934=A59))>1, ""Conflicting Duplicate"", ""Exact Duplicate""))"),"Unique") -> Unique | X65: =COUNTIF(V:V,V65)>1 -> TRUE | Y65: =IF(COUNTIF($A:$A,A65)>1,"Duplicate Order ID","Unique") -> Unique | AA65: =IF( OR(AQ65<0, AQ65>1, C65<B65), "Invalid", IF( OR(G65="Unknown", M65="Unknown"), "Warning", "Clean" ) ) -> Clean | AB65: =IF( OR( B65="", C65="", NOT(ISNUMBER(B65)), NOT(ISNUMBER(C65)), C65<B65 ), "Invalid", "Valid" ) -> Valid | AC65: 7 | AD65: =IF(C65<B65,"Invalid Shipping Date","Valid") -> Valid | AE65: =IF(AND(B65<>"",NOT(ISNUMBER(B65))),"Text Not Date","Valid") -> Valid | AF65: =IF(ISNUMBER(B65),"Valid","Invalid") -> Valid | AG65: =IF(ISNUMBER(C65),"Valid","Invalid") -> Valid | AH65: =IF(OR(B65="",ISBLANK(B65)),"Missing","Valid") -> Valid | AI65: =IF(OR(C65="",ISBLANK(C65)),"Missing","Valid") -> Valid | AJ65: FALSE | AK65: FALSE | AL65: FALSE | AM65: FALSE | AN65: FALSE | AO65: FALSE | AP65: FALSE | AQ65: =IF(OR(P65="",ISBLANK(P65)),0,P65) -> 0.15 | AR65: =N65*O65*(1-AQ65) -> 4815.709 | AS65: =Q65-AR65 -> 0.001 | AT65: =AR65-R65 -> 1787.959 | AU65: =S65-AT65 -> 129.511 | AV65: =AT65/AR65 -> 0.37127638 | AW65: =TEXT(B65,"mmmm") -> January | AX65: =YEAR(B65) -> 2024
A66: ORD-2024-10065 | B66: 45649 | C66: 45655 | D66: CUST-2749 | E66: Aarav Sharma | F66: Corporate | G66: East | H66: Jharkhand | I66: Ranchi | J66: Office Supplies | K66: Paper | L66: Classic Paper 458 | M66: First Class | N66: 7 | O66: 447.84 | P66: 0 | Q66: 3134.88 | R66: 2367.63 | S66: 767.25 | T66: Refunded | U66: Returned | V66: =TEXTJOIN("|",TRUE,A66:U66) -> #NAME? | W66: =IFERROR(__xludf.DUMMYFUNCTION("IF(COUNTIF($A:$A,A60)=1, ""Unique"", IF(COUNTUNIQUE(FILTER($V$2:$V$934,$A$2:$A$934=A60))>1, ""Conflicting Duplicate"", ""Exact Duplicate""))"),"Unique") -> Unique | X66: =COUNTIF(V:V,V66)>1 -> TRUE | Y66: =IF(COUNTIF($A:$A,A66)>1,"Duplicate Order ID","Unique") -> Unique | AA66: =IF( OR(AQ66<0, AQ66>1, C66<B66), "Invalid", IF( OR(G66="Unknown", M66="Unknown"), "Warning", "Clean" ) ) -> Clean | AB66: =IF( OR( B66="", C66="", NOT(ISNUMBER(B66)), NOT(ISNUMBER(C66)), C66<B66 ), "Invalid", "Valid" ) -> Valid | AC66: 6 | AD66: =IF(C66<B66,"Invalid Shipping Date","Valid") -> Valid | AE66: =IF(AND(B66<>"",NOT(ISNUMBER(B66))),"Text Not Date","Valid") -> Valid | AF66: =IF(ISNUMBER(B66),"Valid","Invalid") -> Valid | AG66: =IF(ISNUMBER(C66),"Valid","Invalid") -> Valid | AH66: =IF(OR(B66="",ISBLANK(B66)),"Missing","Valid") -> Valid | AI66: =IF(OR(C66="",ISBLANK(C66)),"Missing","Valid") -> Valid | AJ66: FALSE | AK66: FALSE | AL66: FALSE | AM66: FALSE | AN66: FALSE | AO66: FALSE | AP66: FALSE | AQ66: =IF(OR(P66="",ISBLANK(P66)),0,P66) -> 0 | AR66: =N66*O66*(1-AQ66) -> 3134.88 | AS66: =Q66-AR66 -> 0 | AT66: =AR66-R66 -> 767.25 | AU66: =S66-AT66 -> 0 | AV66: =AT66/AR66 -> 0.24474621 | AW66: =TEXT(B66,"mmmm") -> December | AX66: =YEAR(B66) -> 2024
A67: ORD-2024-10066 | B67: 45404 | C67: 45409 | D67: CUST-2463 | E67: Mira Das | F67: Home Office | G67: West | H67: Maharashtra | I67: Mumbai | J67: Office Supplies | K67: Paper | L67: Pro Paper 552 | M67: Second Class | N67: 1 | O67: 4280.19 | P67: 0.05 | Q67: 4066.18 | R67: 2628.92 | S67: 1437.26 | T67: Paid | U67: Completed | V67: =TEXTJOIN("|",TRUE,A67:U67) -> #NAME? | W67: =IFERROR(__xludf.DUMMYFUNCTION("IF(COUNTIF($A:$A,A61)=1, ""Unique"", IF(COUNTUNIQUE(FILTER($V$2:$V$934,$A$2:$A$934=A61))>1, ""Conflicting Duplicate"", ""Exact Duplicate""))"),"Unique") -> Unique | X67: =COUNTIF(V:V,V67)>1 -> TRUE | Y67: =IF(COUNTIF($A:$A,A67)>1,"Duplicate Order ID","Unique") -> Unique | AA67: =IF( OR(AQ67<0, AQ67>1, C67<B67), "Invalid", IF( OR(G67="Unknown", M67="Unknown"), "Warning", "Clean" ) ) -> Clean | AB67: =IF( OR( B67="", C67="", NOT(ISNUMBER(B67)), NOT(ISNUMBER(C67)), C67<B67 ), "Invalid", "Valid" ) -> Valid | AC67: 5 | AD67: =IF(C67<B67,"Invalid Shipping Date","Valid") -> Valid | AE67: =IF(AND(B67<>"",NOT(ISNUMBER(B67))),"Text Not Date","Valid") -> Valid | AF67: =IF(ISNUMBER(B67),"Valid","Invalid") -> Valid | AG67: =IF(ISNUMBER(C67),"Valid","Invalid") -> Valid | AH67: =IF(OR(B67="",ISBLANK(B67)),"Missing","Valid") -> Valid | AI67: =IF(OR(C67="",ISBLANK(C67)),"Missing","Valid") -> Valid | AJ67: FALSE | AK67: FALSE | AL67: FALSE | AM67: FALSE | AN67: FALSE | AO67: FALSE | AP67: FALSE | AQ67: =IF(OR(P67="",ISBLANK(P67)),0,P67) -> 0.05 | AR67: =N67*O67*(1-AQ67) -> 4066.1805 | AS67: =Q67-AR67 -> -0.0005 | AT67: =AR67-R67 -> 1437.2605 | AU67: =S67-AT67 -> -0.0005 | AV67: =AT67/AR67 -> 0.35346697 | AW67: =TEXT(B67,"mmmm") -> April | AX67: =YEAR(B67) -> 2024
A68: ORD-2025-10067 | B68: 45897 | C68: 45901 | D68: CUST-1504 | E68: Karan Malhotra | F68: Small Business | G68: South | H68: Tamil Nadu | I68: Chennai | J68: Technology | K68: Accessories | L68: Elite Accessories 187 | M68: Same Day | N68: 7 | O68: 1057.46 | P68: 0.05 | Q68: 7032.11 | R68: 4610.34 | S68: 2421.77 | T68: Paid | U68: Completed | V68: =TEXTJOIN("|",TRUE,A68:U68) -> #NAME? | W68: =IFERROR(__xludf.DUMMYFUNCTION("IF(COUNTIF($A:$A,A62)=1, ""Unique"", IF(COUNTUNIQUE(FILTER($V$2:$V$934,$A$2:$A$934=A62))>1, ""Conflicting Duplicate"", ""Exact Duplicate""))"),"Unique") -> Unique | X68: =COUNTIF(V:V,V68)>1 -> TRUE | Y68: =IF(COUNTIF($A:$A,A68)>1,"Duplicate Order ID","Unique") -> Unique | AA68: =IF( OR(AQ68<0, AQ68>1, C68<B68), "Invalid", IF( OR(G68="Unknown", M68="Unknown"), "Warning", "Clean" ) ) -> Clean | AB68: =IF( OR( B68="", C68="", NOT(ISNUMBER(B68)), NOT(ISNUMBER(C68)), C68<B68 ), "Invalid", "Valid" ) -> Valid | AC68: 4 | AD68: =IF(C68<B68,"Invalid Shipping Date","Valid") -> Valid | AE68: =IF(AND(B68<>"",NOT(ISNUMBER(B68))),"Text Not Date","Valid") -> Valid | AF68: =IF(ISNUMBER(B68),"Valid","Invalid") -> Valid | AG68: =IF(ISNUMBER(C68),"Valid","Invalid") -> Valid | AH68: =IF(OR(B68="",ISBLANK(B68)),"Missing","Valid") -> Valid | AI68: =IF(OR(C68="",ISBLANK(C68)),"Missing","Valid") -> Valid | AJ68: FALSE | AK68: FALSE | AL68: FALSE | AM68: FALSE | AN68: FALSE | AO68: FALSE | AP68: FALSE | AQ68: =IF(OR(P68="",ISBLANK(P68)),0,P68) -> 0.05 | AR68: =N68*O68*(1-AQ68) -> 7032.109 | AS68: =Q68-AR68 -> 0.001 | AT68: =AR68-R68 -> 2421.769 | AU68: =S68-AT68 -> 0.001 | AV68: =AT68/AR68 -> 0.3443873 | AW68: =TEXT(B68,"mmmm") -> August | AX68: =YEAR(B68) -> 2025
A69: ORD-2025-10068 | B69: 45691 | C69: 45695 | D69: CUST-8282 | E69: Kabir Singh | F69: Consumer | G69: North | H69: Haryana | I69: Gurugram | J69: Office Supplies | K69: Paper | L69: Eco Paper 922 | M69: First Class | N69: 7 | O69: 3609.34 | P69: 0.05 | Q69: 24002.11 | R69: 18707.57 | S69: 5294.54 | T69: Paid | U69: Completed | V69: =TEXTJOIN("|",TRUE,A69:U69) -> #NAME? | W69: =IFERROR(__xludf.DUMMYFUNCTION("IF(COUNTIF($A:$A,A63)=1, ""Unique"", IF(COUNTUNIQUE(FILTER($V$2:$V$934,$A$2:$A$934=A63))>1, ""Conflicting Duplicate"", ""Exact Duplicate""))"),"Unique") -> Unique | X69: =COUNTIF(V:V,V69)>1 -> TRUE | Y69: =IF(COUNTIF($A:$A,A69)>1,"Duplicate Order ID","Unique") -> Unique | AA69: =IF( OR(AQ69<0, AQ69>1, C69<B69), "Invalid", IF( OR(G69="Unknown", M69="Unknown"), "Warning", "Clean" ) ) -> Clean | AB69: =IF( OR( B69="", C69="", NOT(ISNUMBER(B69)), NOT(ISNUMBER(C69)), C69<B69 ), "Invalid", "Valid" ) -> Valid | AC69: 4 | AD69: =IF(C69<B69,"Invalid Shipping Date","Valid") -> Valid | AE69: =IF(AND(B69<>"",NOT(ISNUMBER(B69))),"Text Not Date","Valid") -> Valid | AF69: =IF(ISNUMBER(B69),"Valid","Invalid") -> Valid | AG69: =IF(ISNUMBER(C69),"Valid","Invalid") -> Valid | AH69: =IF(OR(B69="",ISBLANK(B69)),"Missing","Valid") -> Valid | AI69: =IF(OR(C69="",ISBLANK(C69)),"Missing","Valid") -> Valid | AJ69: FALSE | AK69: FALSE | AL69: FALSE | AM69: FALSE | AN69: FALSE | AO69: FALSE | AP69: FALSE | AQ69: =IF(OR(P69="",ISBLANK(P69)),0,P69) -> 0.05 | AR69: =N69*O69*(1-AQ69) -> 24002.111 | AS69: =Q69-AR69 -> -0.001 | AT69: =AR69-R69 -> 5294.541 | AU69: =S69-AT69 -> -0.001 | AV69: =AT69/AR69 -> 0.22058647 | AW69: =TEXT(B69,"mmmm") -> February | AX69: =YEAR(B69) -> 2025
A70: ORD-2024-10069 | B70: 45606 | C70: 45609 | D70: CUST-6054 | E70: Isha Nair | F70: Corporate | G70: East | H70: Jharkhand | I70: Ranchi | J70: Office Supplies | K70: Storage | L70: Pro Storage 975 | M70: Second Class | N70: 9 | O70: 2211.12 | P70: 0 | Q70: 19900.08 | R70: 10962.66 | S70: 8937.42 | T70: Failed | U70: Returned | V70: =TEXTJOIN("|",TRUE,A70:U70) -> #NAME? | W70: =IFERROR(__xludf.DUMMYFUNCTION("IF(COUNTIF($A:$A,A64)=1, ""Unique"", IF(COUNTUNIQUE(FILTER($V$2:$V$934,$A$2:$A$934=A64))>1, ""Conflicting Duplicate"", ""Exact Duplicate""))"),"Unique") -> Unique | X70: =COUNTIF(V:V,V70)>1 -> TRUE | Y70: =IF(COUNTIF($A:$A,A70)>1,"Duplicate Order ID","Unique") -> Unique | AA70: =IF( OR(AQ70<0, AQ70>1, C70<B70), "Invalid", IF( OR(G70="Unknown", M70="Unknown"), "Warning", "Clean" ) ) -> Clean | AB70: =IF( OR( B70="", C70="", NOT(ISNUMBER(B70)), NOT(ISNUMBER(C70)), C70<B70 ), "Invalid", "Valid" ) -> Valid | AC70: 3 | AD70: =IF(C70<B70,"Invalid Shipping Date","Valid") -> Valid | AE70: =IF(AND(B70<>"",NOT(ISNUMBER(B70))),"Text Not Date","Valid") -> Valid | AF70: =IF(ISNUMBER(B70),"Valid","Invalid") -> Valid | AG70: =IF(ISNUMBER(C70),"Valid","Invalid") -> Valid | AH70: =IF(OR(B70="",ISBLANK(B70)),"Missing","Valid") -> Valid | AI70: =IF(OR(C70="",ISBLANK(C70)),"Missing","Valid") -> Valid | AJ70: FALSE | AK70: FALSE | AL70: FALSE | AM70: FALSE | AN70: FALSE | AO70: FALSE | AP70: FALSE | AQ70: =IF(OR(P70="",ISBLANK(P70)),0,P70) -> 0 | AR70: =N70*O70*(1-AQ70) -> 19900.08 | AS70: =Q70-AR70 -> 0 | AT70: =AR70-R70 -> 8937.42 | AU70: =S70-AT70 -> 0 | AV70: =AT70/AR70 -> 0.44911478 | AW70: =TEXT(B70,"mmmm") -> November | AX70: =YEAR(B70) -> 2024
A71: ORD-2024-10070 | B71: 45391 | C71: 45396 | D71: CUST-5979 | E71: Neha Gupta | F71: Small Business | G71: West | H71: Gujarat | I71: Ahmedabad | J71: Technology | K71: Machines | L71: Prime Machines 782 | M71: Same Day | N71: 7 | O71: 3417.09 | P71: 0.1 | Q71: 21527.67 | R71: 18287.58 | S71: 3240.09 | T71: Refunded | U71: Returned | V71: =TEXTJOIN("|",TRUE,A71:U71) -> #NAME? | W71: =IFERROR(__xludf.DUMMYFUNCTION("IF(COUNTIF($A:$A,A65)=1, ""Unique"", IF(COUNTUNIQUE(FILTER($V$2:$V$934,$A$2:$A$934=A65))>1, ""Conflicting Duplicate"", ""Exact Duplicate""))"),"Unique") -> Unique | X71: =COUNTIF(V:V,V71)>1 -> TRUE | Y71: =IF(COUNTIF($A:$A,A71)>1,"Duplicate Order ID","Unique") -> Unique | AA71: =IF( OR(AQ71<0, AQ71>1, C71<B71), "Invalid", IF( OR(G71="Unknown", M71="Unknown"), "Warning", "Clean" ) ) -> Clean | AB71: =IF( OR( B71="", C71="", NOT(ISNUMBER(B71)), NOT(ISNUMBER(C71)), C71<B71 ), "Invalid", "Valid" ) -> Valid | AC71: 5 | AD71: =IF(C71<B71,"Invalid Shipping Date","Valid") -> Valid | AE71: =IF(AND(B71<>"",NOT(ISNUMBER(B71))),"Text Not Date","Valid") -> Valid | AF71: =IF(ISNUMBER(B71),"Valid","Invalid") -> Valid | AG71: =IF(ISNUMBER(C71),"Valid","Invalid") -> Valid | AH71: =IF(OR(B71="",ISBLANK(B71)),"Missing","Valid") -> Valid | AI71: =IF(OR(C71="",ISBLANK(C71)),"Missing","Valid") -> Valid | AJ71: FALSE | AK71: FALSE | AL71: FALSE | AM71: FALSE | AN71: FALSE | AO71: FALSE | AP71: FALSE | AQ71: =IF(OR(P71="",ISBLANK(P71)),0,P71) -> 0.1 | AR71: =N71*O71*(1-AQ71) -> 21527.667 | AS71: =Q71-AR71 -> 0.003 | AT71: =AR71-R71 -> 3240.087 | AU71: =S71-AT71 -> 0.003 | AV71: =AT71/AR71 -> 0.15050804 | AW71: =TEXT(B71,"mmmm") -> April | AX71: =YEAR(B71) -> 2024
A72: ORD-2025-10071 | B72: 45891 | C72: 45896 | D72: CUST-5582 | E72: Karan Malhotra | F72: Corporate | G72: South | H72: Andhra Pradesh | I72: Vijayawada | J72: Technology | K72: Phones | L72: Max Phones 661 | M72: First Class | N72: 2 | O72: 905.87 | P72: 0.15 | Q72: 1539.98 | R72: 1070.2 | S72: 469.78 | T72: Paid | U72: Completed | V72: =TEXTJOIN("|",TRUE,A72:U72) -> #NAME? | W72: =IFERROR(__xludf.DUMMYFUNCTION("IF(COUNTIF($A:$A,A66)=1, ""Unique"", IF(COUNTUNIQUE(FILTER($V$2:$V$934,$A$2:$A$934=A66))>1, ""Conflicting Duplicate"", ""Exact Duplicate""))"),"Unique") -> Unique | X72: =COUNTIF(V:V,V72)>1 -> TRUE | Y72: =IF(COUNTIF($A:$A,A72)>1,"Duplicate Order ID","Unique") -> Unique | AA72: =IF( OR(AQ72<0, AQ72>1, C72<B72), "Invalid", IF( OR(G72="Unknown", M72="Unknown"), "Warning", "Clean" ) ) -> Clean | AB72: =IF( OR( B72="", C72="", NOT(ISNUMBER(B72)), NOT(ISNUMBER(C72)), C72<B72 ), "Invalid", "Valid" ) -> Valid | AC72: 5 | AD72: =IF(C72<B72,"Invalid Shipping Date","Valid") -> Valid | AE72: =IF(AND(B72<>"",NOT(ISNUMBER(B72))),"Text Not Date","Valid") -> Valid | AF72: =IF(ISNUMBER(B72),"Valid","Invalid") -> Valid | AG72: =IF(ISNUMBER(C72),"Valid","Invalid") -> Valid | AH72: =IF(OR(B72="",ISBLANK(B72)),"Missing","Valid") -> Valid | AI72: =IF(OR(C72="",ISBLANK(C72)),"Missing","Valid") -> Valid | AJ72: FALSE | AK72: FALSE | AL72: FALSE | AM72: FALSE | AN72: FALSE | AO72: FALSE | AP72: FALSE | AQ72: =IF(OR(P72="",ISBLANK(P72)),0,P72) -> 0.15 | AR72: =N72*O72*(1-AQ72) -> 1539.979 | AS72: =Q72-AR72 -> 0.001 | AT72: =AR72-R72 -> 469.779 | AU72: =S72-AT72 -> 0.001 | AV72: =AT72/AR72 -> 0.30505546 | AW72: =TEXT(B72,"mmmm") -> August | AX72: =YEAR(B72) -> 2025
A73: ORD-2025-10072 | B73: 45763 | C73: 45770 | D73: CUST-3308 | E73: Mira Das | F73: Small Business | G73: West | H73: Goa | I73: Panaji | J73: Technology | K73: Machines | L73: Elite Machines 836 | M73: Standard Class | N73: 6 | O73: 2027.32 | P73: 0.1 | Q73: 10947.53 | R73: 6447.36 | S73: 4500.17 | T73: Paid | U73: Completed | V73: =TEXTJOIN("|",TRUE,A73:U73) -> #NAME? | W73: =IFERROR(__xludf.DUMMYFUNCTION("IF(COUNTIF($A:$A,A67)=1, ""Unique"", IF(COUNTUNIQUE(FILTER($V$2:$V$934,$A$2:$A$934=A67))>1, ""Conflicting Duplicate"", ""Exact Duplicate""))"),"Unique") -> Unique | X73: =COUNTIF(V:V,V73)>1 -> TRUE | Y73: =IF(COUNTIF($A:$A,A73)>1,"Duplicate Order ID","Unique") -> Unique | AA73: =IF( OR(AQ73<0, AQ73>1, C73<B73), "Invalid", IF( OR(G73="Unknown", M73="Unknown"), "Warning", "Clean" ) ) -> Clean | AB73: =IF( OR( B73="", C73="", NOT(ISNUMBER(B73)), NOT(ISNUMBER(C73)), C73<B73 ), "Invalid", "Valid" ) -> Valid | AC73: 7 | AD73: =IF(C73<B73,"Invalid Shipping Date","Valid") -> Valid | AE73: =IF(AND(B73<>"",NOT(ISNUMBER(B73))),"Text Not Date","Valid") -> Valid | AF73: =IF(ISNUMBER(B73),"Valid","Invalid") -> Valid | AG73: =IF(ISNUMBER(C73),"Valid","Invalid") -> Valid | AH73: =IF(OR(B73="",ISBLANK(B73)),"Missing","Valid") -> Valid | AI73: =IF(OR(C73="",ISBLANK(C73)),"Missing","Valid") -> Valid | AJ73: FALSE | AK73: FALSE | AL73: FALSE | AM73: FALSE | AN73: FALSE | AO73: FALSE | AP73: FALSE | AQ73: =IF(OR(P73="",ISBLANK(P73)),0,P73) -> 0.1 | AR73: =N73*O73*(1-AQ73) -> 10947.528 | AS73: =Q73-AR73 -> 0.002 | AT73: =AR73-R73 -> 4500.168 | AU73: =S73-AT73 -> 0.002 | AV73: =AT73/AR73 -> 0.41106705 | AW73: =TEXT(B73,"mmmm") -> April | AX73: =YEAR(B73) -> 2025
A74: ORD-2024-10073 | B74: 45333 | C74: 45329 | D74: CUST-5018 | E74: Karan Malhotra | F74: Home Office | G74: South | H74: Tamil Nadu | I74: Chennai | J74: Furniture | K74: Tables | L74: Prime Tables 902 | M74: First Class | N74: 7 | O74: 2287.47 | P74: 0.15 | Q74: 13610.45 | R74: 10039.05 | S74: 3571.4 | T74: Paid | U74: Completed | V74: =TEXTJOIN("|",TRUE,A74:U74) -> #NAME? | W74: =IFERROR(__xludf.DUMMYFUNCTION("IF(COUNTIF($A:$A,A68)=1, ""Unique"", IF(COUNTUNIQUE(FILTER($V$2:$V$934,$A$2:$A$934=A68))>1, ""Conflicting Duplicate"", ""Exact Duplicate""))"),"Unique") -> Unique | X74: =COUNTIF(V:V,V74)>1 -> TRUE | Y74: =IF(COUNTIF($A:$A,A74)>1,"Duplicate Order ID","Unique") -> Unique | AA74: =IF( OR(AQ74<0, AQ74>1, C74<B74), "Invalid", IF( OR(G74="Unknown", M74="Unknown"), "Warning", "Clean" ) ) -> Invalid | AB74: =IF( OR( B74="", C74="", NOT(ISNUMBER(B74)), NOT(ISNUMBER(C74)), C74<B74 ), "Invalid", "Valid" ) -> Invalid | AC74: -4 | AD74: =IF(C74<B74,"Invalid Shipping Date","Valid") -> Invalid Shipping Date | AE74: =IF(AND(B74<>"",NOT(ISNUMBER(B74))),"Text Not Date","Valid") -> Valid | AF74: =IF(ISNUMBER(B74),"Valid","Invalid") -> Valid | AG74: =IF(ISNUMBER(C74),"Valid","Invalid") -> Valid | AH74: =IF(OR(B74="",ISBLANK(B74)),"Missing","Valid") -> Valid | AI74: =IF(OR(C74="",ISBLANK(C74)),"Missing","Valid") -> Valid | AJ74: FALSE | AK74: FALSE | AL74: FALSE | AM74: FALSE | AN74: FALSE | AO74: TRUE | AP74: TRUE | AQ74: =IF(OR(P74="",ISBLANK(P74)),0,P74) -> 0.15 | AR74: =N74*O74*(1-AQ74) -> 13610.446 | AS74: =Q74-AR74 -> 0.0035 | AT74: =AR74-R74 -> 3571.3965 | AU74: =S74-AT74 -> 0.0035 | AV74: =AT74/AR74 -> 0.26240113 | AW74: =TEXT(B74,"mmmm") -> February | AX74: =YEAR(B74) -> 2024
A75: ORD-2025-10074 | B75: 45745 | C75: 45750 | D75: CUST-2342 | E75: Sneha Kapoor | F75: Corporate | G75: East | H75: West Bengal | I75: Kolkata | J75: Furniture | K75: Bookcases | L75: Smart Bookcases 167 | M75: First Class | N75: 5 | O75: 1425.74 | P75: 0 | Q75: 7128.7 | R75: 4382.15 | S75: 2746.55 | T75: Paid | U75: Completed | V75: =TEXTJOIN("|",TRUE,A75:U75) -> #NAME? | W75: =IFERROR(__xludf.DUMMYFUNCTION("IF(COUNTIF($A:$A,A69)=1, ""Unique"", IF(COUNTUNIQUE(FILTER($V$2:$V$934,$A$2:$A$934=A69))>1, ""Conflicting Duplicate"", ""Exact Duplicate""))"),"Unique") -> Unique | X75: =COUNTIF(V:V,V75)>1 -> TRUE | Y75: =IF(COUNTIF($A:$A,A75)>1,"Duplicate Order ID","Unique") -> Unique | AA75: =IF( OR(AQ75<0, AQ75>1, C75<B75), "Invalid", IF( OR(G75="Unknown", M75="Unknown"), "Warning", "Clean" ) ) -> Clean | AB75: =IF( OR( B75="", C75="", NOT(ISNUMBER(B75)), NOT(ISNUMBER(C75)), C75<B75 ), "Invalid", "Valid" ) -> Valid | AC75: 5 | AD75: =IF(C75<B75,"Invalid Shipping Date","Valid") -> Valid | AE75: =IF(AND(B75<>"",NOT(ISNUMBER(B75))),"Text Not Date","Valid") -> Valid | AF75: =IF(ISNUMBER(B75),"Valid","Invalid") -> Valid | AG75: =IF(ISNUMBER(C75),"Valid","Invalid") -> Valid | AH75: =IF(OR(B75="",ISBLANK(B75)),"Missing","Valid") -> Valid | AI75: =IF(OR(C75="",ISBLANK(C75)),"Missing","Valid") -> Valid | AJ75: FALSE | AK75: FALSE | AL75: FALSE | AM75: FALSE | AN75: FALSE | AO75: FALSE | AP75: FALSE | AQ75: =IF(OR(P75="",ISBLANK(P75)),0,P75) -> 0 | AR75: =N75*O75*(1-AQ75) -> 7128.7 | AS75: =Q75-AR75 -> 0 | AT75: =AR75-R75 -> 2746.55 | AU75: =S75-AT75 -> 0 | AV75: =AT75/AR75 -> 0.38528063 | AW75: =TEXT(B75,"mmmm") -> March | AX75: =YEAR(B75) -> 2025
A76: ORD-2025-10075 | B76: 45715 | C76: 45717 | D76: CUST-6201 | E76: Vikram Iyer | F76: Small Business | G76: East | H76: West Bengal | I76: Kolkata | J76: Furniture | K76: Chairs | L76: Max Chairs 244 | M76: Standard Class | N76: 6 | O76: 551.64 | P76: 0 | Q76: 3309.84 | R76: 2671.08 | S76: 638.76 | T76: Paid | U76: Completed | V76: =TEXTJOIN("|",TRUE,A76:U76) -> #NAME? | W76: =IFERROR(__xludf.DUMMYFUNCTION("IF(COUNTIF($A:$A,A70)=1, ""Unique"", IF(COUNTUNIQUE(FILTER($V$2:$V$934,$A$2:$A$934=A70))>1, ""Conflicting Duplicate"", ""Exact Duplicate""))"),"Unique") -> Unique | X76: =COUNTIF(V:V,V76)>1 -> TRUE | Y76: =IF(COUNTIF($A:$A,A76)>1,"Duplicate Order ID","Unique") -> Unique | AA76: =IF( OR(AQ76<0, AQ76>1, C76<B76), "Invalid", IF( OR(G76="Unknown", M76="Unknown"), "Warning", "Clean" ) ) -> Clean | AB76: =IF( OR( B76="", C76="", NOT(ISNUMBER(B76)), NOT(ISNUMBER(C76)), C76<B76 ), "Invalid", "Valid" ) -> Valid | AC76: 2 | AD76: =IF(C76<B76,"Invalid Shipping Date","Valid") -> Valid | AE76: =IF(AND(B76<>"",NOT(ISNUMBER(B76))),"Text Not Date","Valid") -> Valid | AF76: =IF(ISNUMBER(B76),"Valid","Invalid") -> Valid | AG76: =IF(ISNUMBER(C76),"Valid","Invalid") -> Valid | AH76: =IF(OR(B76="",ISBLANK(B76)),"Missing","Valid") -> Valid | AI76: =IF(OR(C76="",ISBLANK(C76)),"Missing","Valid") -> Valid | AJ76: FALSE | AK76: FALSE | AL76: FALSE | AM76: FALSE | AN76: FALSE | AO76: FALSE | AP76: FALSE | AQ76: =IF(OR(P76="",ISBLANK(P76)),0,P76) -> 0 | AR76: =N76*O76*(1-AQ76) -> 3309.84 | AS76: =Q76-AR76 -> 0 | AT76: =AR76-R76 -> 638.76 | AU76: =S76-AT76 -> 0 | AV76: =AT76/AR76 -> 0.19298818 | AW76: =TEXT(B76,"mmmm") -> February | AX76: =YEAR(B76) -> 2025
A77: ORD-2025-10076 | B77: 45891 | C77: 45896 | D77: CUST-5808 | E77: Priya Menon | F77: Small Business | G77: East | H77: Odisha | I77: Bhubaneswar | J77: Office Supplies | K77: Labels | L77: Eco Labels 653 | M77: First Class | N77: 3 | O77: 3294.82 | P77: 0.2 | Q77: 7907.57 | R77: 5391.18 | S77: 2516.39 | T77: Paid | U77: Completed | V77: =TEXTJOIN("|",TRUE,A77:U77) -> #NAME? | W77: =IFERROR(__xludf.DUMMYFUNCTION("IF(COUNTIF($A:$A,A71)=1, ""Unique"", IF(COUNTUNIQUE(FILTER($V$2:$V$934,$A$2:$A$934=A71))>1, ""Conflicting Duplicate"", ""Exact Duplicate""))"),"Unique") -> Unique | X77: =COUNTIF(V:V,V77)>1 -> TRUE | Y77: =IF(COUNTIF($A:$A,A77)>1,"Duplicate Order ID","Unique") -> Unique | AA77: =IF( OR(AQ77<0, AQ77>1, C77<B77), "Invalid", IF( OR(G77="Unknown", M77="Unknown"), "Warning", "Clean" ) ) -> Clean | AB77: =IF( OR( B77="", C77="", NOT(ISNUMBER(B77)), NOT(ISNUMBER(C77)), C77<B77 ), "Invalid", "Valid" ) -> Valid | AC77: 5 | AD77: =IF(C77<B77,"Invalid Shipping Date","Valid") -> Valid | AE77: =IF(AND(B77<>"",NOT(ISNUMBER(B77))),"Text Not Date","Valid") -> Valid | AF77: =IF(ISNUMBER(B77),"Valid","Invalid") -> Valid | AG77: =IF(ISNUMBER(C77),"Valid","Invalid") -> Valid | AH77: =IF(OR(B77="",ISBLANK(B77)),"Missing","Valid") -> Valid | AI77: =IF(OR(C77="",ISBLANK(C77)),"Missing","Valid") -> Valid | AJ77: FALSE | AK77: FALSE | AL77: FALSE | AM77: FALSE | AN77: FALSE | AO77: FALSE | AP77: FALSE | AQ77: =IF(OR(P77="",ISBLANK(P77)),0,P77) -> 0.2 | AR77: =N77*O77*(1-AQ77) -> 7907.568 | AS77: =Q77-AR77 -> 0.002 | AT77: =AR77-R77 -> 2516.388 | AU77: =S77-AT77 -> 0.002 | AV77: =AT77/AR77 -> 0.31822527 | AW77: =TEXT(B77,"mmmm") -> August | AX77: =YEAR(B77) -> 2025
A78: ORD-2024-10077 | B78: 45599 | C78: 45607 | D78: CUST-2642 | E78: Ananya Rao | F78: Corporate | G78: East | H78: Jharkhand | I78: Ranchi | J78: Office Supplies | K78: Labels | L78: Max Labels 617 | M78: Second Class | N78: 3 | O78: 3406.27 | P78: 0 | Q78: 10218.81 | R78: 7616.97 | S78: 2601.84 | T78: Paid | U78: Completed | V78: =TEXTJOIN("|",TRUE,A78:U78) -> #NAME? | W78: =IFERROR(__xludf.DUMMYFUNCTION("IF(COUNTIF($A:$A,A72)=1, ""Unique"", IF(COUNTUNIQUE(FILTER($V$2:$V$934,$A$2:$A$934=A72))>1, ""Conflicting Duplicate"", ""Exact Duplicate""))"),"Unique") -> Unique | X78: =COUNTIF(V:V,V78)>1 -> TRUE | Y78: =IF(COUNTIF($A:$A,A78)>1,"Duplicate Order ID","Unique") -> Unique | AA78: =IF( OR(AQ78<0, AQ78>1, C78<B78), "Invalid", IF( OR(G78="Unknown", M78="Unknown"), "Warning", "Clean" ) ) -> Clean | AB78: =IF( OR( B78="", C78="", NOT(ISNUMBER(B78)), NOT(ISNUMBER(C78)), C78<B78 ), "Invalid", "Valid" ) -> Valid | AC78: 8 | AD78: =IF(C78<B78,"Invalid Shipping Date","Valid") -> Valid | AE78: =IF(AND(B78<>"",NOT(ISNUMBER(B78))),"Text Not Date","Valid") -> Valid | AF78: =IF(ISNUMBER(B78),"Valid","Invalid") -> Valid | AG78: =IF(ISNUMBER(C78),"Valid","Invalid") -> Valid | AH78: =IF(OR(B78="",ISBLANK(B78)),"Missing","Valid") -> Valid | AI78: =IF(OR(C78="",ISBLANK(C78)),"Missing","Valid") -> Valid | AJ78: FALSE | AK78: FALSE | AL78: FALSE | AM78: FALSE | AN78: FALSE | AO78: FALSE | AP78: FALSE | AQ78: =IF(OR(P78="",ISBLANK(P78)),0,P78) -> 0 | AR78: =N78*O78*(1-AQ78) -> 10218.81 | AS78: =Q78-AR78 -> 0 | AT78: =AR78-R78 -> 2601.84 | AU78: =S78-AT78 -> 0 | AV78: =AT78/AR78 -> 0.25461282 | AW78: =TEXT(B78,"mmmm") -> November | AX78: =YEAR(B78) -> 2024
A79: ORD-2025-10078 | B79: 45846 | C79: 45850 | D79: CUST-4385 | E79: Rohan Mehta | F79: Home Office | G79: North | H79: Uttar Pradesh | I79: Noida | J79: Furniture | K79: Furnishings | L79: Pro Furnishings 529 | M79: Standard Class | N79: 1 | O79: 2582.2 | P79: 0.15 | Q79: 2194.87 | R79: 1223.17 | S79: 971.7 | T79: Refunded | U79: Cancelled | V79: =TEXTJOIN("|",TRUE,A79:U79) -> #NAME? | W79: =IFERROR(__xludf.DUMMYFUNCTION("IF(COUNTIF($A:$A,A73)=1, ""Unique"", IF(COUNTUNIQUE(FILTER($V$2:$V$934,$A$2:$A$934=A73))>1, ""Conflicting Duplicate"", ""Exact Duplicate""))"),"Unique") -> Unique | X79: =COUNTIF(V:V,V79)>1 -> TRUE | Y79: =IF(COUNTIF($A:$A,A79)>1,"Duplicate Order ID","Unique") -> Unique | AA79: =IF( OR(AQ79<0, AQ79>1, C79<B79), "Invalid", IF( OR(G79="Unknown", M79="Unknown"), "Warning", "Clean" ) ) -> Clean | AB79: =IF( OR( B79="", C79="", NOT(ISNUMBER(B79)), NOT(ISNUMBER(C79)), C79<B79 ), "Invalid", "Valid" ) -> Valid | AC79: 4 | AD79: =IF(C79<B79,"Invalid Shipping Date","Valid") -> Valid | AE79: =IF(AND(B79<>"",NOT(ISNUMBER(B79))),"Text Not Date","Valid") -> Valid | AF79: =IF(ISNUMBER(B79),"Valid","Invalid") -> Valid | AG79: =IF(ISNUMBER(C79),"Valid","Invalid") -> Valid | AH79: =IF(OR(B79="",ISBLANK(B79)),"Missing","Valid") -> Valid | AI79: =IF(OR(C79="",ISBLANK(C79)),"Missing","Valid") -> Valid | AJ79: FALSE | AK79: FALSE | AL79: FALSE | AM79: FALSE | AN79: FALSE | AO79: FALSE | AP79: FALSE | AQ79: =IF(OR(P79="",ISBLANK(P79)),0,P79) -> 0.15 | AR79: =N79*O79*(1-AQ79) -> 2194.87 | AS79: =Q79-AR79 -> 0 | AT79: =AR79-R79 -> 971.7 | AU79: =S79-AT79 -> 0 | AV79: =AT79/AR79 -> 0.44271415 | AW79: =TEXT(B79,"mmmm") -> July | AX79: =YEAR(B79) -> 2025
A80: ORD-2025-10079 | B80: 45854 | C80: 45859 | D80: CUST-8043 | E80: Sneha Kapoor | F80: Corporate | G80: East | H80: West Bengal | I80: Kolkata | J80: Furniture | K80: Tables | L80: Smart Tables 561 | M80: First Class | N80: 5 | O80: 2129.51 | P80: 0.15 | Q80: 9050.42 | R80: 6778.85 | S80: 2271.57 | T80: Paid | U80: Completed | V80: =TEXTJOIN("|",TRUE,A80:U80) -> #NAME? | W80: =IFERROR(__xludf.DUMMYFUNCTION("IF(COUNTIF($A:$A,A74)=1, ""Unique"", IF(COUNTUNIQUE(FILTER($V$2:$V$934,$A$2:$A$934=A74))>1, ""Conflicting Duplicate"", ""Exact Duplicate""))"),"Unique") -> Unique | X80: =COUNTIF(V:V,V80)>1 -> TRUE | Y80: =IF(COUNTIF($A:$A,A80)>1,"Duplicate Order ID","Unique") -> Unique | AA80: =IF( OR(AQ80<0, AQ80>1, C80<B80), "Invalid", IF( OR(G80="Unknown", M80="Unknown"), "Warning", "Clean" ) ) -> Clean | AB80: =IF( OR( B80="", C80="", NOT(ISNUMBER(B80)), NOT(ISNUMBER(C80)), C80<B80 ), "Invalid", "Valid" ) -> Valid | AC80: 5 | AD80: =IF(C80<B80,"Invalid Shipping Date","Valid") -> Valid | AE80: =IF(AND(B80<>"",NOT(ISNUMBER(B80))),"Text Not Date","Valid") -> Valid | AF80: =IF(ISNUMBER(B80),"Valid","Invalid") -> Valid | AG80: =IF(ISNUMBER(C80),"Valid","Invalid") -> Valid | AH80: =IF(OR(B80="",ISBLANK(B80)),"Missing","Valid") -> Valid | AI80: =IF(OR(C80="",ISBLANK(C80)),"Missing","Valid") -> Valid | AJ80: FALSE | AK80: FALSE | AL80: FALSE | AM80: FALSE | AN80: FALSE | AO80: FALSE | AP80: FALSE | AQ80: =IF(OR(P80="",ISBLANK(P80)),0,P80) -> 0.15 | AR80: =N80*O80*(1-AQ80) -> 9050.4175 | AS80: =Q80-AR80 -> 0.0025 | AT80: =AR80-R80 -> 2271.5675 | AU80: =S80-AT80 -> 0.0025 | AV80: =AT80/AR80 -> 0.25099035 | AW80: =TEXT(B80,"mmmm") -> July | AX80: =YEAR(B80) -> 2025
A81: ORD-2025-10080 | B81: 45927 | C81: 45933 | D81: CUST-9978 | E81: Diya Patel | F81: Home Office | G81: South | H81: Tamil Nadu | I81: Chennai | J81: Furniture | K81: Chairs | L81: Prime Chairs 838 | M81: Same Day | N81: 9 | O81: 4131.52 | P81: 0.1 | Q81: 33465.31 | R81: 24781.26 | S81: 8684.05 | T81: Paid | U81: Completed | V81: =TEXTJOIN("|",TRUE,A81:U81) -> #NAME? | W81: =IFERROR(__xludf.DUMMYFUNCTION("IF(COUNTIF($A:$A,A75)=1, ""Unique"", IF(COUNTUNIQUE(FILTER($V$2:$V$934,$A$2:$A$934=A75))>1, ""Conflicting Duplicate"", ""Exact Duplicate""))"),"Unique") -> Unique | X81: =COUNTIF(V:V,V81)>1 -> TRUE | Y81: =IF(COUNTIF($A:$A,A81)>1,"Duplicate Order ID","Unique") -> Unique | AA81: =IF( OR(AQ81<0, AQ81>1, C81<B81), "Invalid", IF( OR(G81="Unknown", M81="Unknown"), "Warning", "Clean" ) ) -> Clean | AB81: =IF( OR( B81="", C81="", NOT(ISNUMBER(B81)), NOT(ISNUMBER(C81)), C81<B81 ), "Invalid", "Valid" ) -> Valid | AC81: 6 | AD81: =IF(C81<B81,"Invalid Shipping Date","Valid") -> Valid | AE81: =IF(AND(B81<>"",NOT(ISNUMBER(B81))),"Text Not Date","Valid") -> Valid | AF81: =IF(ISNUMBER(B81),"Valid","Invalid") -> Valid | AG81: =IF(ISNUMBER(C81),"Valid","Invalid") -> Valid | AH81: =IF(OR(B81="",ISBLANK(B81)),"Missing","Valid") -> Valid | AI81: =IF(OR(C81="",ISBLANK(C81)),"Missing","Valid") -> Valid | AJ81: FALSE | AK81: FALSE | AL81: FALSE | AM81: FALSE | AN81: FALSE | AO81: FALSE | AP81: FALSE | AQ81: =IF(OR(P81="",ISBLANK(P81)),0,P81) -> 0.1 | AR81: =N81*O81*(1-AQ81) -> 33465.312 | AS81: =Q81-AR81 -> -0.002 | AT81: =AR81-R81 -> 8684.052 | AU81: =S81-AT81 -> -0.002 | AV81: =AT81/AR81 -> 0.25949413 | AW81: =TEXT(B81,"mmmm") -> September | AX81: =YEAR(B81) -> 2025
A82: ORD-2024-10081 | B82: 45514 | C82: 45518 | D82: CUST-2094 | E82: Aarav Sharma | F82: Small Business | G82: North | H82: Delhi | I82: New Delhi | J82: Office Supplies | K82: Storage | L82: Elite Storage 371 | M82: Second Class | N82: 4 | O82: 1182.32 | P82: 0.1 | Q82: 4256.35 | R82: 2495.33 | S82: 1761.02 | T82: Pending | U82: Returned | V82: =TEXTJOIN("|",TRUE,A82:U82) -> #NAME? | W82: =IFERROR(__xludf.DUMMYFUNCTION("IF(COUNTIF($A:$A,A76)=1, ""Unique"", IF(COUNTUNIQUE(FILTER($V$2:$V$934,$A$2:$A$934=A76))>1, ""Conflicting Duplicate"", ""Exact Duplicate""))"),"Unique") -> Unique | X82: =COUNTIF(V:V,V82)>1 -> TRUE | Y82: =IF(COUNTIF($A:$A,A82)>1,"Duplicate Order ID","Unique") -> Unique | AA82: =IF( OR(AQ82<0, AQ82>1, C82<B82), "Invalid", IF( OR(G82="Unknown", M82="Unknown"), "Warning", "Clean" ) ) -> Clean | AB82: =IF( OR( B82="", C82="", NOT(ISNUMBER(B82)), NOT(ISNUMBER(C82)), C82<B82 ), "Invalid", "Valid" ) -> Valid | AC82: 4 | AD82: =IF(C82<B82,"Invalid Shipping Date","Valid") -> Valid | AE82: =IF(AND(B82<>"",NOT(ISNUMBER(B82))),"Text Not Date","Valid") -> Valid | AF82: =IF(ISNUMBER(B82),"Valid","Invalid") -> Valid | AG82: =IF(ISNUMBER(C82),"Valid","Invalid") -> Valid | AH82: =IF(OR(B82="",ISBLANK(B82)),"Missing","Valid") -> Valid | AI82: =IF(OR(C82="",ISBLANK(C82)),"Missing","Valid") -> Valid | AJ82: FALSE | AK82: FALSE | AL82: FALSE | AM82: FALSE | AN82: FALSE | AO82: FALSE | AP82: FALSE | AQ82: =IF(OR(P82="",ISBLANK(P82)),0,P82) -> 0.1 | AR82: =N82*O82*(1-AQ82) -> 4256.352 | AS82: =Q82-AR82 -> -0.002 | AT82: =AR82-R82 -> 1761.022 | AU82: =S82-AT82 -> -0.002 | AV82: =AT82/AR82 -> 0.41373975 | AW82: =TEXT(B82,"mmmm") -> August | AX82: =YEAR(B82) -> 2024
A83: ORD-2025-10082 | B83: 45732 | C83: 45733 | D83: CUST-7907 | E83: Karan Malhotra | F83: Home Office | G83: West | H83: Goa | I83: Panaji | J83: Office Supplies | K83: Labels | L83: Eco Labels 662 | M83: Same Day | N83: 3 | O83: 1841.91 | P83: 0 | Q83: 5525.73 | R83: 3093.42 | S83: 2432.31 | T83: Paid | U83: Completed | V83: =TEXTJOIN("|",TRUE,A83:U83) -> #NAME? | W83: =IFERROR(__xludf.DUMMYFUNCTION("IF(COUNTIF($A:$A,A77)=1, ""Unique"", IF(COUNTUNIQUE(FILTER($V$2:$V$934,$A$2:$A$934=A77))>1, ""Conflicting Duplicate"", ""Exact Duplicate""))"),"Unique") -> Unique | X83: =COUNTIF(V:V,V83)>1 -> TRUE | Y83: =IF(COUNTIF($A:$A,A83)>1,"Duplicate Order ID","Unique") -> Unique | AA83: =IF( OR(AQ83<0, AQ83>1, C83<B83), "Invalid", IF( OR(G83="Unknown", M83="Unknown"), "Warning", "Clean" ) ) -> Clean | AB83: =IF( OR( B83="", C83="", NOT(ISNUMBER(B83)), NOT(ISNUMBER(C83)), C83<B83 ), "Invalid", "Valid" ) -> Valid | AC83: 1 | AD83: =IF(C83<B83,"Invalid Shipping Date","Valid") -> Valid | AE83: =IF(AND(B83<>"",NOT(ISNUMBER(B83))),"Text Not Date","Valid") -> Valid | AF83: =IF(ISNUMBER(B83),"Valid","Invalid") -> Valid | AG83: =IF(ISNUMBER(C83),"Valid","Invalid") -> Valid | AH83: =IF(OR(B83="",ISBLANK(B83)),"Missing","Valid") -> Valid | AI83: =IF(OR(C83="",ISBLANK(C83)),"Missing","Valid") -> Valid | AJ83: FALSE | AK83: FALSE | AL83: FALSE | AM83: FALSE | AN83: FALSE | AO83: FALSE | AP83: FALSE | AQ83: =IF(OR(P83="",ISBLANK(P83)),0,P83) -> 0 | AR83: =N83*O83*(1-AQ83) -> 5525.73 | AS83: =Q83-AR83 -> 0 | AT83: =AR83-R83 -> 2432.31 | AU83: =S83-AT83 -> 0 | AV83: =AT83/AR83 -> 0.44017894 | AW83: =TEXT(B83,"mmmm") -> March | AX83: =YEAR(B83) -> 2025
A84: ORD-2024-10083 | B84: 45507 | C84: 45508 | D84: CUST-6516 | E84: Arjun Bose | F84: Consumer | G84: North | H84: Uttar Pradesh | I84: Noida | J84: Technology | K84: Copiers | L84: Smart Copiers 702 | M84: Second Class | N84: 6 | O84: 1001.73 | P84: 0 | Q84: 6010.38 | R84: 3762.85 | S84: 2247.53 | T84: Failed | U84: Returned | V84: =TEXTJOIN("|",TRUE,A84:U84) -> #NAME? | W84: =IFERROR(__xludf.DUMMYFUNCTION("IF(COUNTIF($A:$A,A78)=1, ""Unique"", IF(COUNTUNIQUE(FILTER($V$2:$V$934,$A$2:$A$934=A78))>1, ""Conflicting Duplicate"", ""Exact Duplicate""))"),"Unique") -> Unique | X84: =COUNTIF(V:V,V84)>1 -> TRUE | Y84: =IF(COUNTIF($A:$A,A84)>1,"Duplicate Order ID","Unique") -> Unique | AA84: =IF( OR(AQ84<0, AQ84>1, C84<B84), "Invalid", IF( OR(G84="Unknown", M84="Unknown"), "Warning", "Clean" ) ) -> Clean | AB84: =IF( OR( B84="", C84="", NOT(ISNUMBER(B84)), NOT(ISNUMBER(C84)), C84<B84 ), "Invalid", "Valid" ) -> Valid | AC84: 1 | AD84: =IF(C84<B84,"Invalid Shipping Date","Valid") -> Valid | AE84: =IF(AND(B84<>"",NOT(ISNUMBER(B84))),"Text Not Date","Valid") -> Valid | AF84: =IF(ISNUMBER(B84),"Valid","Invalid") -> Valid | AG84: =IF(ISNUMBER(C84),"Valid","Invalid") -> Valid | AH84: =IF(OR(B84="",ISBLANK(B84)),"Missing","Valid") -> Valid | AI84: =IF(OR(C84="",ISBLANK(C84)),"Missing","Valid") -> Valid | AJ84: FALSE | AK84: FALSE | AL84: FALSE | AM84: FALSE | AN84: FALSE | AO84: FALSE | AP84: FALSE | AQ84: =IF(OR(P84="",ISBLANK(P84)),0,P84) -> 0 | AR84: =N84*O84*(1-AQ84) -> 6010.38 | AS84: =Q84-AR84 -> 0 | AT84: =AR84-R84 -> 2247.53 | AU84: =S84-AT84 -> 0 | AV84: =AT84/AR84 -> 0.37394141 | AW84: =TEXT(B84,"mmmm") -> August | AX84: =YEAR(B84) -> 2024
A85: ORD-2024-10084 | B85: 45591 | C85: 45594 | D85: CUST-4989 | E85: Aditi Sen | F85: Home Office | G85: West | H85: Maharashtra | I85: Mumbai | J85: Furniture | K85: Tables | L85: Elite Tables 362 | M85: Second Class | N85: 9 | O85: 131.74 | P85: 0.2 | Q85: 948.53 | R85: 674.62 | S85: 273.91 | T85: Paid | U85: Completed | V85: =TEXTJOIN("|",TRUE,A85:U85) -> #NAME? | W85: =IFERROR(__xludf.DUMMYFUNCTION("IF(COUNTIF($A:$A,A79)=1, ""Unique"", IF(COUNTUNIQUE(FILTER($V$2:$V$934,$A$2:$A$934=A79))>1, ""Conflicting Duplicate"", ""Exact Duplicate""))"),"Unique") -> Unique | X85: =COUNTIF(V:V,V85)>1 -> TRUE | Y85: =IF(COUNTIF($A:$A,A85)>1,"Duplicate Order ID","Unique") -> Unique | AA85: =IF( OR(AQ85<0, AQ85>1, C85<B85), "Invalid", IF( OR(G85="Unknown", M85="Unknown"), "Warning", "Clean" ) ) -> Clean | AB85: =IF( OR( B85="", C85="", NOT(ISNUMBER(B85)), NOT(ISNUMBER(C85)), C85<B85 ), "Invalid", "Valid" ) -> Valid | AC85: 3 | AD85: =IF(C85<B85,"Invalid Shipping Date","Valid") -> Valid | AE85: =IF(AND(B85<>"",NOT(ISNUMBER(B85))),"Text Not Date","Valid") -> Valid | AF85: =IF(ISNUMBER(B85),"Valid","Invalid") -> Valid | AG85: =IF(ISNUMBER(C85),"Valid","Invalid") -> Valid | AH85: =IF(OR(B85="",ISBLANK(B85)),"Missing","Valid") -> Valid | AI85: =IF(OR(C85="",ISBLANK(C85)),"Missing","Valid") -> Valid | AJ85: FALSE | AK85: FALSE | AL85: FALSE | AM85: FALSE | AN85: FALSE | AO85: FALSE | AP85: FALSE | AQ85: =IF(OR(P85="",ISBLANK(P85)),0,P85) -> 0.2 | AR85: =N85*O85*(1-AQ85) -> 948.528 | AS85: =Q85-AR85 -> 0.002 | AT85: =AR85-R85 -> 273.908 | AU85: =S85-AT85 -> 0.002 | AV85: =AT85/AR85 -> 0.28877165 | AW85: =TEXT(B85,"mmmm") -> October | AX85: =YEAR(B85) -> 2024
A86: ORD-2024-10085 | B86: 45566 | C86: 45568 | D86: CUST-3758 | E86: Rohan Mehta | F86: Corporate | G86: South | H86: Tamil Nadu | I86: Chennai | J86: Technology | K86: Phones | L86: Elite Phones 781 | M86: Second Class | N86: 6 | O86: 570.28 | P86: 0.2 | Q86: 2737.34 | R86: 2085.44 | S86: 651.9 | T86: Paid | U86: Completed | V86: =TEXTJOIN("|",TRUE,A86:U86) -> #NAME? | W86: =IFERROR(__xludf.DUMMYFUNCTION("IF(COUNTIF($A:$A,A80)=1, ""Unique"", IF(COUNTUNIQUE(FILTER($V$2:$V$934,$A$2:$A$934=A80))>1, ""Conflicting Duplicate"", ""Exact Duplicate""))"),"Unique") -> Unique | X86: =COUNTIF(V:V,V86)>1 -> TRUE | Y86: =IF(COUNTIF($A:$A,A86)>1,"Duplicate Order ID","Unique") -> Unique | AA86: =IF( OR(AQ86<0, AQ86>1, C86<B86), "Invalid", IF( OR(G86="Unknown", M86="Unknown"), "Warning", "Clean" ) ) -> Clean | AB86: =IF( OR( B86="", C86="", NOT(ISNUMBER(B86)), NOT(ISNUMBER(C86)), C86<B86 ), "Invalid", "Valid" ) -> Valid | AC86: 2 | AD86: =IF(C86<B86,"Invalid Shipping Date","Valid") -> Valid | AE86: =IF(AND(B86<>"",NOT(ISNUMBER(B86))),"Text Not Date","Valid") -> Valid | AF86: =IF(ISNUMBER(B86),"Valid","Invalid") -> Valid | AG86: =IF(ISNUMBER(C86),"Valid","Invalid") -> Valid | AH86: =IF(OR(B86="",ISBLANK(B86)),"Missing","Valid") -> Valid | AI86: =IF(OR(C86="",ISBLANK(C86)),"Missing","Valid") -> Valid | AJ86: FALSE | AK86: FALSE | AL86: FALSE | AM86: FALSE | AN86: FALSE | AO86: FALSE | AP86: FALSE | AQ86: =IF(OR(P86="",ISBLANK(P86)),0,P86) -> 0.2 | AR86: =N86*O86*(1-AQ86) -> 2737.344 | AS86: =Q86-AR86 -> -0.004 | AT86: =AR86-R86 -> 651.904 | AU86: =S86-AT86 -> -0.004 | AV86: =AT86/AR86 -> 0.23815202 | AW86: =TEXT(B86,"mmmm") -> October | AX86: =YEAR(B86) -> 2024
A87: ORD-2024-10086 | B87: 45503 | C87: 45509 | D87: CUST-6702 | E87: Kabir Singh | F87: Corporate | G87: North | H87: Delhi | I87: New Delhi | J87: Office Supplies | K87: Binders | L87: Eco Binders 456 | M87: Standard Class | N87: 1 | O87: 608.64 | P87: 0 | Q87: 608.64 | R87: 343.99 | S87: 264.65 | T87: Paid | U87: Cancelled | V87: =TEXTJOIN("|",TRUE,A87:U87) -> #NAME? | W87: =IFERROR(__xludf.DUMMYFUNCTION("IF(COUNTIF($A:$A,A81)=1, ""Unique"", IF(COUNTUNIQUE(FILTER($V$2:$V$934,$A$2:$A$934=A81))>1, ""Conflicting Duplicate"", ""Exact Duplicate""))"),"Unique") -> Unique | X87: =COUNTIF(V:V,V87)>1 -> TRUE | Y87: =IF(COUNTIF($A:$A,A87)>1,"Duplicate Order ID","Unique") -> Unique | AA87: =IF( OR(AQ87<0, AQ87>1, C87<B87), "Invalid", IF( OR(G87="Unknown", M87="Unknown"), "Warning", "Clean" ) ) -> Clean | AB87: =IF( OR( B87="", C87="", NOT(ISNUMBER(B87)), NOT(ISNUMBER(C87)), C87<B87 ), "Invalid", "Valid" ) -> Valid | AC87: 6 | AD87: =IF(C87<B87,"Invalid Shipping Date","Valid") -> Valid | AE87: =IF(AND(B87<>"",NOT(ISNUMBER(B87))),"Text Not Date","Valid") -> Valid | AF87: =IF(ISNUMBER(B87),"Valid","Invalid") -> Valid | AG87: =IF(ISNUMBER(C87),"Valid","Invalid") -> Valid | AH87: =IF(OR(B87="",ISBLANK(B87)),"Missing","Valid") -> Valid | AI87: =IF(OR(C87="",ISBLANK(C87)),"Missing","Valid") -> Valid | AJ87: FALSE | AK87: FALSE | AL87: FALSE | AM87: FALSE | AN87: FALSE | AO87: FALSE | AP87: FALSE | AQ87: =IF(OR(P87="",ISBLANK(P87)),0,P87) -> 0 | AR87: =N87*O87*(1-AQ87) -> 608.64 | AS87: =Q87-AR87 -> 0 | AT87: =AR87-R87 -> 264.65 | AU87: =S87-AT87 -> 0 | AV87: =AT87/AR87 -> 0.4348219 | AW87: =TEXT(B87,"mmmm") -> July | AX87: =YEAR(B87) -> 2024
A88: ORD-2024-10087 | B88: 45474 | C88: 45474 | D88: CUST-9148 | E88: Ananya Rao | F88: Small Business | G88: North | H88: Delhi | I88: New Delhi | J88: Technology | K88: Copiers | L88: Basic Copiers 525 | M88: Second Class | N88: 3 | O88: 885.28 | P88: 0.1 | Q88: 2390.26 | R88: 1495.94 | S88: 894.32 | T88: Refunded | U88: Cancelled | V88: =TEXTJOIN("|",TRUE,A88:U88) -> #NAME? | W88: =IFERROR(__xludf.DUMMYFUNCTION("IF(COUNTIF($A:$A,A82)=1, ""Unique"", IF(COUNTUNIQUE(FILTER($V$2:$V$934,$A$2:$A$934=A82))>1, ""Conflicting Duplicate"", ""Exact Duplicate""))"),"Unique") -> Unique | X88: =COUNTIF(V:V,V88)>1 -> TRUE | Y88: =IF(COUNTIF($A:$A,A88)>1,"Duplicate Order ID","Unique") -> Unique | AA88: =IF( OR(AQ88<0, AQ88>1, C88<B88), "Invalid", IF( OR(G88="Unknown", M88="Unknown"), "Warning", "Clean" ) ) -> Clean | AB88: =IF( OR( B88="", C88="", NOT(ISNUMBER(B88)), NOT(ISNUMBER(C88)), C88<B88 ), "Invalid", "Valid" ) -> Valid | AC88: 0 | AD88: =IF(C88<B88,"Invalid Shipping Date","Valid") -> Valid | AE88: =IF(AND(B88<>"",NOT(ISNUMBER(B88))),"Text Not Date","Valid") -> Valid | AF88: =IF(ISNUMBER(B88),"Valid","Invalid") -> Valid | AG88: =IF(ISNUMBER(C88),"Valid","Invalid") -> Valid | AH88: =IF(OR(B88="",ISBLANK(B88)),"Missing","Valid") -> Valid | AI88: =IF(OR(C88="",ISBLANK(C88)),"Missing","Valid") -> Valid | AJ88: FALSE | AK88: FALSE | AL88: FALSE | AM88: FALSE | AN88: FALSE | AO88: FALSE | AP88: FALSE | AQ88: =IF(OR(P88="",ISBLANK(P88)),0,P88) -> 0.1 | AR88: =N88*O88*(1-AQ88) -> 2390.256 | AS88: =Q88-AR88 -> 0.004 | AT88: =AR88-R88 -> 894.316 | AU88: =S88-AT88 -> 0.004 | AV88: =AT88/AR88 -> 0.37415072 | AW88: =TEXT(B88,"mmmm") -> July | AX88: =YEAR(B88) -> 2024
A89: ORD-2024-10088 | B89: 45506 | C89: 45507 | D89: CUST-5829 | E89: Vikram Iyer | F89: Consumer | G89: East | H89: Assam | I89: Guwahati | J89: Office Supplies | K89: Binders | L89: Eco Binders 258 | M89: Standard Class | N89: 7 | O89: 3345.22 | P89: 0 | Q89: 23416.54 | R89: 15490.89 | S89: 7925.65 | T89: Paid | U89: Completed | V89: =TEXTJOIN("|",TRUE,A89:U89) -> #NAME? | W89: =IFERROR(__xludf.DUMMYFUNCTION("IF(COUNTIF($A:$A,A83)=1, ""Unique"", IF(COUNTUNIQUE(FILTER($V$2:$V$934,$A$2:$A$934=A83))>1, ""Conflicting Duplicate"", ""Exact Duplicate""))"),"Unique") -> Unique | X89: =COUNTIF(V:V,V89)>1 -> TRUE | Y89: =IF(COUNTIF($A:$A,A89)>1,"Duplicate Order ID","Unique") -> Unique | AA89: =IF( OR(AQ89<0, AQ89>1, C89<B89), "Invalid", IF( OR(G89="Unknown", M89="Unknown"), "Warning", "Clean" ) ) -> Clean | AB89: =IF( OR( B89="", C89="", NOT(ISNUMBER(B89)), NOT(ISNUMBER(C89)), C89<B89 ), "Invalid", "Valid" ) -> Valid | AC89: 1 | AD89: =IF(C89<B89,"Invalid Shipping Date","Valid") -> Valid | AE89: =IF(AND(B89<>"",NOT(ISNUMBER(B89))),"Text Not Date","Valid") -> Valid | AF89: =IF(ISNUMBER(B89),"Valid","Invalid") -> Valid | AG89: =IF(ISNUMBER(C89),"Valid","Invalid") -> Valid | AH89: =IF(OR(B89="",ISBLANK(B89)),"Missing","Valid") -> Valid | AI89: =IF(OR(C89="",ISBLANK(C89)),"Missing","Valid") -> Valid | AJ89: FALSE | AK89: FALSE | AL89: FALSE | AM89: FALSE | AN89: FALSE | AO89: FALSE | AP89: FALSE | AQ89: =IF(OR(P89="",ISBLANK(P89)),0,P89) -> 0 | AR89: =N89*O89*(1-AQ89) -> 23416.54 | AS89: =Q89-AR89 -> 0 | AT89: =AR89-R89 -> 7925.65 | AU89: =S89-AT89 -> 0 | AV89: =AT89/AR89 -> 0.33846375 | AW89: =TEXT(B89,"mmmm") -> August | AX89: =YEAR(B89) -> 2024
A90: ORD-2024-10089 | B90: 45375 | C90: 45378 | D90: CUST-6059 | E90: Rohan Mehta | F90: Small Business | G90: West | H90: Maharashtra | I90: Mumbai | J90: Furniture | K90: Bookcases | L90: Max Bookcases 398 | M90: Standard Class | N90: 2 | O90: 3284.75 | P90: 0.05 | Q90: 6241.02 | R90: 5345.88 | S90: 895.14 | T90: Paid | U90: Completed | V90: =TEXTJOIN("|",TRUE,A90:U90) -> #NAME? | W90: =IFERROR(__xludf.DUMMYFUNCTION("IF(COUNTIF($A:$A,A84)=1, ""Unique"", IF(COUNTUNIQUE(FILTER($V$2:$V$934,$A$2:$A$934=A84))>1, ""Conflicting Duplicate"", ""Exact Duplicate""))"),"Unique") -> Unique | X90: =COUNTIF(V:V,V90)>1 -> TRUE | Y90: =IF(COUNTIF($A:$A,A90)>1,"Duplicate Order ID","Unique") -> Unique | AA90: =IF( OR(AQ90<0, AQ90>1, C90<B90), "Invalid", IF( OR(G90="Unknown", M90="Unknown"), "Warning", "Clean" ) ) -> Clean | AB90: =IF( OR( B90="", C90="", NOT(ISNUMBER(B90)), NOT(ISNUMBER(C90)), C90<B90 ), "Invalid", "Valid" ) -> Valid | AC90: 3 | AD90: =IF(C90<B90,"Invalid Shipping Date","Valid") -> Valid | AE90: =IF(AND(B90<>"",NOT(ISNUMBER(B90))),"Text Not Date","Valid") -> Valid | AF90: =IF(ISNUMBER(B90),"Valid","Invalid") -> Valid | AG90: =IF(ISNUMBER(C90),"Valid","Invalid") -> Valid | AH90: =IF(OR(B90="",ISBLANK(B90)),"Missing","Valid") -> Valid | AI90: =IF(OR(C90="",ISBLANK(C90)),"Missing","Valid") -> Valid | AJ90: FALSE | AK90: FALSE | AL90: FALSE | AM90: FALSE | AN90: FALSE | AO90: FALSE | AP90: FALSE | AQ90: =IF(OR(P90="",ISBLANK(P90)),0,P90) -> 0.05 | AR90: =N90*O90*(1-AQ90) -> 6241.025 | AS90: =Q90-AR90 -> -0.005 | AT90: =AR90-R90 -> 895.145 | AU90: =S90-AT90 -> -0.005 | AV90: =AT90/AR90 -> 0.14342916 | AW90: =TEXT(B90,"mmmm") -> March | AX90: =YEAR(B90) -> 2024
A91: ORD-2024-10090 | B91: 45540 | C91: 45540 | D91: CUST-7744 | E91: Kabir Singh | F91: Consumer | G91: South | H91: Andhra Pradesh | I91: Vijayawada | J91: Furniture | K91: Bookcases | L91: Smart Bookcases 857 | M91: Standard Class | N91: 7 | O91: 3761.09 | P91: 0.2 | Q91: 21062.1 | R91: 12057.13 | S91: 9004.97 | T91: Pending | U91: Cancelled | V91: =TEXTJOIN("|",TRUE,A91:U91) -> #NAME? | W91: =IFERROR(__xludf.DUMMYFUNCTION("IF(COUNTIF($A:$A,A85)=1, ""Unique"", IF(COUNTUNIQUE(FILTER($V$2:$V$934,$A$2:$A$934=A85))>1, ""Conflicting Duplicate"", ""Exact Duplicate""))"),"Unique") -> Unique | X91: =COUNTIF(V:V,V91)>1 -> TRUE | Y91: =IF(COUNTIF($A:$A,A91)>1,"Duplicate Order ID","Unique") -> Unique | AA91: =IF( OR(AQ91<0, AQ91>1, C91<B91), "Invalid", IF( OR(G91="Unknown", M91="Unknown"), "Warning", "Clean" ) ) -> Clean | AB91: =IF( OR( B91="", C91="", NOT(ISNUMBER(B91)), NOT(ISNUMBER(C91)), C91<B91 ), "Invalid", "Valid" ) -> Valid | AC91: 0 | AD91: =IF(C91<B91,"Invalid Shipping Date","Valid") -> Valid | AE91: =IF(AND(B91<>"",NOT(ISNUMBER(B91))),"Text Not Date","Valid") -> Valid | AF91: =IF(ISNUMBER(B91),"Valid","Invalid") -> Valid | AG91: =IF(ISNUMBER(C91),"Valid","Invalid") -> Valid | AH91: =IF(OR(B91="",ISBLANK(B91)),"Missing","Valid") -> Valid | AI91: =IF(OR(C91="",ISBLANK(C91)),"Missing","Valid") -> Valid | AJ91: FALSE | AK91: FALSE | AL91: FALSE | AM91: FALSE | AN91: FALSE | AO91: FALSE | AP91: FALSE | AQ91: =IF(OR(P91="",ISBLANK(P91)),0,P91) -> 0.2 | AR91: =N91*O91*(1-AQ91) -> 21062.104 | AS91: =Q91-AR91 -> -0.004 | AT91: =AR91-R91 -> 9004.974 | AU91: =S91-AT91 -> -0.004 | AV91: =AT91/AR91 -> 0.4275439 | AW91: =TEXT(B91,"mmmm") -> September | AX91: =YEAR(B91) -> 2024
A92: ORD-2025-10091 | B92: 45893 | C92: 45898 | D92: CUST-5909 | E92: Aarav Sharma | F92: Small Business | G92: East | H92: Bihar | I92: Patna | J92: Technology | K92: Copiers | L92: Smart Copiers 556 | M92: First Class | N92: 3 | O92: 3703.96 | P92: 0.15 | Q92: 9445.1 | R92: 5586.28 | S92: 3858.82 | T92: Paid | U92: Completed | V92: =TEXTJOIN("|",TRUE,A92:U92) -> #NAME? | W92: =IFERROR(__xludf.DUMMYFUNCTION("IF(COUNTIF($A:$A,A86)=1, ""Unique"", IF(COUNTUNIQUE(FILTER($V$2:$V$934,$A$2:$A$934=A86))>1, ""Conflicting Duplicate"", ""Exact Duplicate""))"),"Unique") -> Unique | X92: =COUNTIF(V:V,V92)>1 -> TRUE | Y92: =IF(COUNTIF($A:$A,A92)>1,"Duplicate Order ID","Unique") -> Duplicate Order ID | AA92: =IF( OR(AQ92<0, AQ92>1, C92<B92), "Invalid", IF( OR(G92="Unknown", M92="Unknown"), "Warning", "Clean" ) ) -> Clean | AB92: =IF( OR( B92="", C92="", NOT(ISNUMBER(B92)), NOT(ISNUMBER(C92)), C92<B92 ), "Invalid", "Valid" ) -> Valid | AC92: 5 | AD92: =IF(C92<B92,"Invalid Shipping Date","Valid") -> Valid | AE92: =IF(AND(B92<>"",NOT(ISNUMBER(B92))),"Text Not Date","Valid") -> Valid | AF92: =IF(ISNUMBER(B92),"Valid","Invalid") -> Valid | AG92: =IF(ISNUMBER(C92),"Valid","Invalid") -> Valid | AH92: =IF(OR(B92="",ISBLANK(B92)),"Missing","Valid") -> Valid | AI92: =IF(OR(C92="",ISBLANK(C92)),"Missing","Valid") -> Valid | AJ92: FALSE | AK92: FALSE | AL92: FALSE | AM92: FALSE | AN92: FALSE | AO92: FALSE | AP92: FALSE | AQ92: =IF(OR(P92="",ISBLANK(P92)),0,P92) -> 0.15 | AR92: =N92*O92*(1-AQ92) -> 9445.098 | AS92: =Q92-AR92 -> 0.002 | AT92: =AR92-R92 -> 3858.818 | AU92: =S92-AT92 -> 0.002 | AV92: =AT92/AR92 -> 0.40855246 | AW92: =TEXT(B92,"mmmm") -> August | AX92: =YEAR(B92) -> 2025
A93: ORD-2025-10092 | B93: 45718 | C93: 45724 | D93: CUST-6409 | E93: Sneha Kapoor | F93: Corporate | G93: West | H93: Madhya Pradesh | I93: Indore | J93: Technology | K93: Copiers | L93: Prime Copiers 575 | M93: Second Class | N93: 9 | O93: 269.68 | P93: 0 | Q93: 2427.12 | R93: 1538.35 | S93: 804.53 | T93: Paid | U93: Completed | V93: =TEXTJOIN("|",TRUE,A93:U93) -> #NAME? | W93: =IFERROR(__xludf.DUMMYFUNCTION("IF(COUNTIF($A:$A,A87)=1, ""Unique"", IF(COUNTUNIQUE(FILTER($V$2:$V$934,$A$2:$A$934=A87))>1, ""Conflicting Duplicate"", ""Exact Duplicate""))"),"Unique") -> Unique | X93: =COUNTIF(V:V,V93)>1 -> TRUE | Y93: =IF(COUNTIF($A:$A,A93)>1,"Duplicate Order ID","Unique") -> Unique | AA93: =IF( OR(AQ93<0, AQ93>1, C93<B93), "Invalid", IF( OR(G93="Unknown", M93="Unknown"), "Warning", "Clean" ) ) -> Clean | AB93: =IF( OR( B93="", C93="", NOT(ISNUMBER(B93)), NOT(ISNUMBER(C93)), C93<B93 ), "Invalid", "Valid" ) -> Valid | AC93: 6 | AD93: =IF(C93<B93,"Invalid Shipping Date","Valid") -> Valid | AE93: =IF(AND(B93<>"",NOT(ISNUMBER(B93))),"Text Not Date","Valid") -> Valid | AF93: =IF(ISNUMBER(B93),"Valid","Invalid") -> Valid | AG93: =IF(ISNUMBER(C93),"Valid","Invalid") -> Valid | AH93: =IF(OR(B93="",ISBLANK(B93)),"Missing","Valid") -> Valid | AI93: =IF(OR(C93="",ISBLANK(C93)),"Missing","Valid") -> Valid | AJ93: FALSE | AK93: FALSE | AL93: FALSE | AM93: FALSE | AN93: FALSE | AO93: FALSE | AP93: FALSE | AQ93: =IF(OR(P93="",ISBLANK(P93)),0,P93) -> 0 | AR93: =N93*O93*(1-AQ93) -> 2427.12 | AS93: =Q93-AR93 -> 0 | AT93: =AR93-R93 -> 888.77 | AU93: =S93-AT93 -> -84.24 | AV93: =AT93/AR93 -> 0.36618297 | AW93: =TEXT(B93,"mmmm") -> March | AX93: =YEAR(B93) -> 2025
A94: ORD-2025-10093 | B94: 45680 | C94: 45683 | D94: CUST-3014 | E94: Aarav Sharma | F94: Consumer | G94: West | H94: Madhya Pradesh | I94: Indore | J94: Office Supplies | K94: Paper | L94: Elite Paper 669 | M94: Standard Class | N94: 9 | O94: 4458.26 | P94: 0.1 | Q94: 36111.91 | R94: 29194.5 | S94: 6917.41 | T94: Paid | U94: Completed | V94: =TEXTJOIN("|",TRUE,A94:U94) -> #NAME? | W94: =IFERROR(__xludf.DUMMYFUNCTION("IF(COUNTIF($A:$A,A88)=1, ""Unique"", IF(COUNTUNIQUE(FILTER($V$2:$V$934,$A$2:$A$934=A88))>1, ""Conflicting Duplicate"", ""Exact Duplicate""))"),"Unique") -> Unique | X94: =COUNTIF(V:V,V94)>1 -> TRUE | Y94: =IF(COUNTIF($A:$A,A94)>1,"Duplicate Order ID","Unique") -> Unique | AA94: =IF( OR(AQ94<0, AQ94>1, C94<B94), "Invalid", IF( OR(G94="Unknown", M94="Unknown"), "Warning", "Clean" ) ) -> Clean | AB94: =IF( OR( B94="", C94="", NOT(ISNUMBER(B94)), NOT(ISNUMBER(C94)), C94<B94 ), "Invalid", "Valid" ) -> Valid | AC94: 3 | AD94: =IF(C94<B94,"Invalid Shipping Date","Valid") -> Valid | AE94: =IF(AND(B94<>"",NOT(ISNUMBER(B94))),"Text Not Date","Valid") -> Valid | AF94: =IF(ISNUMBER(B94),"Valid","Invalid") -> Valid | AG94: =IF(ISNUMBER(C94),"Valid","Invalid") -> Valid | AH94: =IF(OR(B94="",ISBLANK(B94)),"Missing","Valid") -> Valid | AI94: =IF(OR(C94="",ISBLANK(C94)),"Missing","Valid") -> Valid | AJ94: FALSE | AK94: FALSE | AL94: FALSE | AM94: FALSE | AN94: FALSE | AO94: FALSE | AP94: FALSE | AQ94: =IF(OR(P94="",ISBLANK(P94)),0,P94) -> 0.1 | AR94: =N94*O94*(1-AQ94) -> 36111.906 | AS94: =Q94-AR94 -> 0.004 | AT94: =AR94-R94 -> 6917.406 | AU94: =S94-AT94 -> 0.004 | AV94: =AT94/AR94 -> 0.19155472 | AW94: =TEXT(B94,"mmmm") -> January | AX94: =YEAR(B94) -> 2025
A95: ORD-2024-10094 | B95: 45298 | C95: 45304 | D95: CUST-6106 | E95: Rohan Mehta | F95: Corporate | G95: North | H95: Uttar Pradesh | I95: Noida | J95: Office Supplies | K95: Binders | L95: Eco Binders 780 | M95: Standard Class | N95: 7 | O95: 2788.97 | P95: -0.09 | Q95: 19522.79 | R95: 12455.78 | S95: 7067.01 | T95: Paid | U95: Completed | V95: =TEXTJOIN("|",TRUE,A95:U95) -> #NAME? | W95: =IFERROR(__xludf.DUMMYFUNCTION("IF(COUNTIF($A:$A,A89)=1, ""Unique"", IF(COUNTUNIQUE(FILTER($V$2:$V$934,$A$2:$A$934=A89))>1, ""Conflicting Duplicate"", ""Exact Duplicate""))"),"Unique") -> Unique | X95: =COUNTIF(V:V,V95)>1 -> TRUE | Y95: =IF(COUNTIF($A:$A,A95)>1,"Duplicate Order ID","Unique") -> Unique | AA95: =IF( OR(AQ95<0, AQ95>1, C95<B95), "Invalid", IF( OR(G95="Unknown", M95="Unknown"), "Warning", "Clean" ) ) -> Invalid | AB95: =IF( OR( B95="", C95="", NOT(ISNUMBER(B95)), NOT(ISNUMBER(C95)), C95<B95 ), "Invalid", "Valid" ) -> Valid | AC95: 6 | AD95: =IF(C95<B95,"Invalid Shipping Date","Valid") -> Valid | AE95: =IF(AND(B95<>"",NOT(ISNUMBER(B95))),"Text Not Date","Valid") -> Valid | AF95: =IF(ISNUMBER(B95),"Valid","Invalid") -> Valid | AG95: =IF(ISNUMBER(C95),"Valid","Invalid") -> Valid | AH95: =IF(OR(B95="",ISBLANK(B95)),"Missing","Valid") -> Valid | AI95: =IF(OR(C95="",ISBLANK(C95)),"Missing","Valid") -> Valid | AJ95: FALSE | AK95: FALSE | AL95: FALSE | AM95: TRUE | AN95: FALSE | AO95: FALSE | AP95: TRUE | AQ95: =IF(OR(P95="",ISBLANK(P95)),0,P95) -> -0.09 | AR95: =N95*O95*(1-AQ95) -> 21279.841 | AS95: =Q95-AR95 -> -1757.0511 | AT95: =AR95-R95 -> 8824.0611 | AU95: =S95-AT95 -> -1757.0511 | AV95: =AT95/AR95 -> 0.41466762 | AW95: =TEXT(B95,"mmmm") -> January | AX95: =YEAR(B95) -> 2024
A96: ORD-2024-10095 | B96: 45541 | C96: 45544 | D96: CUST-1926 | E96: Diya Patel | F96: Consumer | G96: North | H96: Haryana | I96: Gurugram | J96: Technology | K96: Phones | L96: Elite Phones 723 | M96: Second Class | N96: 7 | O96: 3781.53 | P96: 0 | Q96: 26470.71 | R96: 21367.6 | S96: 5103.11 | T96: Pending | U96: Cancelled | V96: =TEXTJOIN("|",TRUE,A96:U96) -> #NAME? | W96: =IFERROR(__xludf.DUMMYFUNCTION("IF(COUNTIF($A:$A,A90)=1, ""Unique"", IF(COUNTUNIQUE(FILTER($V$2:$V$934,$A$2:$A$934=A90))>1, ""Conflicting Duplicate"", ""Exact Duplicate""))"),"Unique") -> Unique | X96: =COUNTIF(V:V,V96)>1 -> TRUE | Y96: =IF(COUNTIF($A:$A,A96)>1,"Duplicate Order ID","Unique") -> Unique | AA96: =IF( OR(AQ96<0, AQ96>1, C96<B96), "Invalid", IF( OR(G96="Unknown", M96="Unknown"), "Warning", "Clean" ) ) -> Clean | AB96: =IF( OR( B96="", C96="", NOT(ISNUMBER(B96)), NOT(ISNUMBER(C96)), C96<B96 ), "Invalid", "Valid" ) -> Valid | AC96: 3 | AD96: =IF(C96<B96,"Invalid Shipping Date","Valid") -> Valid | AE96: =IF(AND(B96<>"",NOT(ISNUMBER(B96))),"Text Not Date","Valid") -> Valid | AF96: =IF(ISNUMBER(B96),"Valid","Invalid") -> Valid | AG96: =IF(ISNUMBER(C96),"Valid","Invalid") -> Valid | AH96: =IF(OR(B96="",ISBLANK(B96)),"Missing","Valid") -> Valid | AI96: =IF(OR(C96="",ISBLANK(C96)),"Missing","Valid") -> Valid | AJ96: FALSE | AK96: FALSE | AL96: FALSE | AM96: FALSE | AN96: FALSE | AO96: FALSE | AP96: FALSE | AQ96: =IF(OR(P96="",ISBLANK(P96)),0,P96) -> 0 | AR96: =N96*O96*(1-AQ96) -> 26470.71 | AS96: =Q96-AR96 -> 0 | AT96: =AR96-R96 -> 5103.11 | AU96: =S96-AT96 -> 0 | AV96: =AT96/AR96 -> 0.19278327 | AW96: =TEXT(B96,"mmmm") -> September | AX96: =YEAR(B96) -> 2024
A97: ORD-2025-10096 | B97: 45905 | C97: 45910 | D97: CUST-2687 | E97: Sneha Kapoor | F97: Corporate | G97: West | H97: Goa | I97: Panaji | J97: Furniture | K97: Bookcases | L97: Classic Bookcases 988 | M97: Same Day | N97: 6 | O97: 1754.13 | P97: 0 | Q97: 10524.78 | R97: 8841.05 | S97: 1683.73 | T97: Paid | U97: Completed | V97: =TEXTJOIN("|",TRUE,A97:U97) -> #NAME? | W97: =IFERROR(__xludf.DUMMYFUNCTION("IF(COUNTIF($A:$A,A91)=1, ""Unique"", IF(COUNTUNIQUE(FILTER($V$2:$V$934,$A$2:$A$934=A91))>1, ""Conflicting Duplicate"", ""Exact Duplicate""))"),"Unique") -> Unique | X97: =COUNTIF(V:V,V97)>1 -> TRUE | Y97: =IF(COUNTIF($A:$A,A97)>1,"Duplicate Order ID","Unique") -> Unique | AA97: =IF( OR(AQ97<0, AQ97>1, C97<B97), "Invalid", IF( OR(G97="Unknown", M97="Unknown"), "Warning", "Clean" ) ) -> Clean | AB97: =IF( OR( B97="", C97="", NOT(ISNUMBER(B97)), NOT(ISNUMBER(C97)), C97<B97 ), "Invalid", "Valid" ) -> Valid | AC97: 5 | AD97: =IF(C97<B97,"Invalid Shipping Date","Valid") -> Valid | AE97: =IF(AND(B97<>"",NOT(ISNUMBER(B97))),"Text Not Date","Valid") -> Valid | AF97: =IF(ISNUMBER(B97),"Valid","Invalid") -> Valid | AG97: =IF(ISNUMBER(C97),"Valid","Invalid") -> Valid | AH97: =IF(OR(B97="",ISBLANK(B97)),"Missing","Valid") -> Valid | AI97: =IF(OR(C97="",ISBLANK(C97)),"Missing","Valid") -> Valid | AJ97: FALSE | AK97: FALSE | AL97: FALSE | AM97: FALSE | AN97: FALSE | AO97: FALSE | AP97: FALSE | AQ97: =IF(OR(P97="",ISBLANK(P97)),0,P97) -> 0 | AR97: =N97*O97*(1-AQ97) -> 10524.78 | AS97: =Q97-AR97 -> 0 | AT97: =AR97-R97 -> 1683.73 | AU97: =S97-AT97 -> 0 | AV97: =AT97/AR97 -> 0.15997769 | AW97: =TEXT(B97,"mmmm") -> September | AX97: =YEAR(B97) -> 2025
A98: ORD-2024-10097 | B98: 45448 | C98: 45450 | D98: CUST-7283 | E98: Rahul Verma | F98: Home Office | G98: East | H98: Odisha | I98: Bhubaneswar | J98: Technology | K98: Copiers | L98: Smart Copiers 547 | M98: Second Class | N98: 2 | O98: 2259.24 | P98: 0.15 | Q98: 3840.71 | R98: 2516.29 | S98: 1324.42 | T98: Paid | U98: Completed | V98: =TEXTJOIN("|",TRUE,A98:U98) -> #NAME? | W98: =IFERROR(__xludf.DUMMYFUNCTION("IF(COUNTIF($A:$A,A92)=1, ""Unique"", IF(COUNTUNIQUE(FILTER($V$2:$V$934,$A$2:$A$934=A92))>1, ""Conflicting Duplicate"", ""Exact Duplicate""))"),"Conflicting Duplicate") -> Conflicting Duplicate | X98: =COUNTIF(V:V,V98)>1 -> TRUE | Y98: =IF(COUNTIF($A:$A,A98)>1,"Duplicate Order ID","Unique") -> Unique | AA98: =IF( OR(AQ98<0, AQ98>1, C98<B98), "Invalid", IF( OR(G98="Unknown", M98="Unknown"), "Warning", "Clean" ) ) -> Clean | AB98: =IF( OR( B98="", C98="", NOT(ISNUMBER(B98)), NOT(ISNUMBER(C98)), C98<B98 ), "Invalid", "Valid" ) -> Valid | AC98: 2 | AD98: =IF(C98<B98,"Invalid Shipping Date","Valid") -> Valid | AE98: =IF(AND(B98<>"",NOT(ISNUMBER(B98))),"Text Not Date","Valid") -> Valid | AF98: =IF(ISNUMBER(B98),"Valid","Invalid") -> Valid | AG98: =IF(ISNUMBER(C98),"Valid","Invalid") -> Valid | AH98: =IF(OR(B98="",ISBLANK(B98)),"Missing","Valid") -> Valid | AI98: =IF(OR(C98="",ISBLANK(C98)),"Missing","Valid") -> Valid | AJ98: FALSE | AK98: FALSE | AL98: FALSE | AM98: FALSE | AN98: FALSE | AO98: FALSE | AP98: FALSE | AQ98: =IF(OR(P98="",ISBLANK(P98)),0,P98) -> 0.15 | AR98: =N98*O98*(1-AQ98) -> 3840.708 | AS98: =Q98-AR98 -> 0.002 | AT98: =AR98-R98 -> 1324.418 | AU98: =S98-AT98 -> 0.002 | AV98: =AT98/AR98 -> 0.34483694 | AW98: =TEXT(B98,"mmmm") -> June | AX98: =YEAR(B98) -> 2024
A99: ORD-2025-10098 | B99: 45877 | C99: 45880 | D99: CUST-8111 | E99: Diya Patel | F99: Small Business | G99: West | H99: Gujarat | I99: Ahmedabad | J99: Office Supplies | K99: Storage | L99: Basic Storage 656 | M99: Same Day | N99: 5 | O99: 3602.36 | P99: 0.2 | Q99: 14409.44 | R99: 8809.97 | S99: 5599.47 | T99: Pending | U99: Returned | V99: =TEXTJOIN("|",TRUE,A99:U99) -> #NAME? | W99: =IFERROR(__xludf.DUMMYFUNCTION("IF(COUNTIF($A:$A,A93)=1, ""Unique"", IF(COUNTUNIQUE(FILTER($V$2:$V$934,$A$2:$A$934=A93))>1, ""Conflicting Duplicate"", ""Exact Duplicate""))"),"Unique") -> Unique | X99: =COUNTIF(V:V,V99)>1 -> TRUE | Y99: =IF(COUNTIF($A:$A,A99)>1,"Duplicate Order ID","Unique") -> Unique | AA99: =IF( OR(AQ99<0, AQ99>1, C99<B99), "Invalid", IF( OR(G99="Unknown", M99="Unknown"), "Warning", "Clean" ) ) -> Clean | AB99: =IF( OR( B99="", C99="", NOT(ISNUMBER(B99)), NOT(ISNUMBER(C99)), C99<B99 ), "Invalid", "Valid" ) -> Valid | AC99: 3 | AD99: =IF(C99<B99,"Invalid Shipping Date","Valid") -> Valid | AE99: =IF(AND(B99<>"",NOT(ISNUMBER(B99))),"Text Not Date","Valid") -> Valid | AF99: =IF(ISNUMBER(B99),"Valid","Invalid") -> Valid | AG99: =IF(ISNUMBER(C99),"Valid","Invalid") -> Valid | AH99: =IF(OR(B99="",ISBLANK(B99)),"Missing","Valid") -> Valid | AI99: =IF(OR(C99="",ISBLANK(C99)),"Missing","Valid") -> Valid | AJ99: FALSE | AK99: FALSE | AL99: FALSE | AM99: FALSE | AN99: FALSE | AO99: FALSE | AP99: FALSE | AQ99: =IF(OR(P99="",ISBLANK(P99)),0,P99) -> 0.2 | AR99: =N99*O99*(1-AQ99) -> 14409.44 | AS99: =Q99-AR99 -> 0 | AT99: =AR99-R99 -> 5599.47 | AU99: =S99-AT99 -> 0 | AV99: =AT99/AR99 -> 0.38859734 | AW99: =TEXT(B99,"mmmm") -> August | AX99: =YEAR(B99) -> 2025
A100: ORD-2024-10099 | B100: 45317 | C100: 45323 | D100: CUST-5434 | E100: Rohan Mehta | F100: Home Office | G100: South | H100: Kerala | I100: Kochi | J100: Technology | K100: Copiers | L100: Elite Copiers 785 | M100: Unknown | N100: 8 | O100: 2108.93 | P100: 0.1 | Q100: 15184.3 | R100: 11270.74 | S100: 3913.56 | T100: Paid | U100: Completed | V100: =TEXTJOIN("|",TRUE,A100:U100) -> #NAME? | W100: =IFERROR(__xludf.DUMMYFUNCTION("IF(COUNTIF($A:$A,A94)=1, ""Unique"", IF(COUNTUNIQUE(FILTER($V$2:$V$934,$A$2:$A$934=A94))>1, ""Conflicting Duplicate"", ""Exact Duplicate""))"),"Unique") -> Unique | X100: =COUNTIF(V:V,V100)>1 -> TRUE | Y100: =IF(COUNTIF($A:$A,A100)>1,"Duplicate Order ID","Unique") -> Unique | AA100: =IF( OR(AQ100<0, AQ100>1, C100<B100), "Invalid", IF( OR(G100="Unknown", M100="Unknown"), "Warning", "Clean" ) ) -> Warning | AB100: =IF( OR( B100="", C100="", NOT(ISNUMBER(B100)), NOT(ISNUMBER(C100)), C100<B100 ), "Invalid", "Valid" ) -> Valid | AC100: 6 | AD100: =IF(C100<B100,"Invalid Shipping Date","Valid") -> Valid | AE100: =IF(AND(B100<>"",NOT(ISNUMBER(B100))),"Text Not Date","Valid") -> Valid | AF100: =IF(ISNUMBER(B100),"Valid","Invalid") -> Valid | AG100: =IF(ISNUMBER(C100),"Valid","Invalid") -> Valid | AH100: =IF(OR(B100="",ISBLANK(B100)),"Missing","Valid") -> Valid | AI100: =IF(OR(C100="",ISBLANK(C100)),"Missing","Valid") -> Valid | AJ100: FALSE | AK100: TRUE | AL100: FALSE | AM100: FALSE | AN100: FALSE | AO100: FALSE | AP100: TRUE | AQ100: =IF(OR(P100="",ISBLANK(P100)),0,P100) -> 0.1 | AR100: =N100*O100*(1-AQ100) -> 15184.296 | AS100: =Q100-AR100 -> 0.004 | AT100: =AR100-R100 -> 3913.556 | AU100: =S100-AT100 -> 0.004 | AV100: =AT100/AR100 -> 0.25773707 | AW100: =TEXT(B100,"mmmm") -> January | AX100: =YEAR(B100) -> 2024
...

Sheet Data Issue working
A1: Issue Type | B1: Count
A2: Missing Order Date | B2: 0
A3: Missing Ship Date | B3: 0
A4: Invalid Order Date | B4: =COUNTIF(cleaned_orders!AF2:AF933,"Invalid") -> 0
A5: Invalid Ship Date | B5: =COUNTIF(cleaned_orders!AG2:AG933,"Invalid") -> 0
A6: Ship Date Before Order Date | B6: =COUNTIF(cleaned_orders!AD2:AD933,"Invalid Shipping Date") -> 22
A9: Column Name | B9: Missing Count
A10: region | B10: =COUNTIF(cleaned_orders!AJ:AJ,TRUE) -> 26
A11: ship_mode | B11: =COUNTIF(cleaned_orders!AK:AK,TRUE) -> 22
A12: discount | B12: =COUNTIF(cleaned_orders!AL:AL,TRUE) -> 18
A13: cost | B13: =COUNTBLANK(cleaned_orders!R2:R933) -> 0
A14: sales | B14: =COUNTBLANK(cleaned_orders!Q2:Q933) -> 0
A16: Invalid Discount Summary
A17: Metric | B17: count
A18: Negative Discount | B18: =COUNTIF(cleaned_orders!P2:P933,"<0") -> 16
A19: Discount<100% | B19: =COUNTIF(cleaned_orders!P3:P934,">1") -> 0
A20: Missing Discount | B20: =COUNTBLANK(cleaned_orders!P2:P933) -> 0

Sheet business_rules
A1: Rule Area | B1: Student-Facing Rule
A2: Raw file | B2: Do not overwrite raw_orders.xlsx. Create cleaned_orders.xlsx separately.
A3: Missing region | B3: Fill as Unknown and flag in quality report.
A4: Missing ship_mode | B4: Fill as Unknown and flag in quality report.
A5: Missing discount | B5: Treat as 0 only if all other sales fields are valid; otherwise flag.
A6: Discount | B6: Flag negative discounts and unusually high discounts as invalid.
A7: Cancelled/Failed/Refunded | B7: Do not include non-completed/failed/refunded records in completed-sales summaries.
A8: Date sequence | B8: Flag ship_date earlier than order_date.
A9: Duplicates | B9: Remove exact duplicate copies; flag conflicting duplicate order IDs.
A10: Calculated fields | B10: Create calculated_sales, calculated_profit, profit_margin, shipping_delay_days, order_month, order_year, and data_quality_flag.
A11: Documentation | B11: Document cleaning decisions and assumptions in cleaning_log.md.
